Workbook

Sheet stage10_integration
A1: STAGE 10 — INTEGRATED STUDY: UK · DE · CN INDUSTRIAL ELECTRICITY PRICES (front page + final QC)
A2: The study in one page: what industry pays, why, and what policy can do. Ten stages, one workbook. Real-2025 USD unless noted (house rule 1/D1: nominal local × Fed H.10 annual-avg FX × US CPI-U; VAT excluded). This front page is formula-linked to the underlying stages; the consistency panel (Section C) and integrity panel (Section D) are live gates. CN price series: 含税 (incl VAT) as published — Q84; de-VAT memo stage6 r189–191.
A4: A. THE HEADLINE — modelled cost stack & system cost, 2025 (real-2025 USD/MWh; statutory components, SUPPLY MARGIN EXCLUDED; source stage6_decomp T3; observed comparators row 9)
B5: Country / archetype | C5: Modelled stack E1 (unrelieved) | D5: Modelled stack E2 (relieved) | E5: System cost (modelled) | F5: Relief channel
B6: United Kingdom (large) | C6: =stage6_decomp!D148 | D6: =stage6_decomp!D149 | E6: =stage6_decomp!G148 | F6: other bill-payers (cross-subsidy)
B7: Germany (large) | C7: =stage6_decomp!D152 | D7: =stage6_decomp!D153 | E7: =stage6_decomp!G152 | F7: taxpayer (EEG on budget + Stromsteuer); §19 network rebate → other users. KTF network subsidy from 2026
B8: China (large) | C8: =stage6_decomp!D156 | F8: reverse: industry → residential (on-bill only; system cost unquantified, ≤ bill)
B9: OBSERVED 2025 (band averages, context): UK QEP Extra Large excl CCL | C9: =timeseries!S78 | D9: DE Eurostat IF | E9: =timeseries!S86 | F9: UK obs − modelled E1 = supply margin (Q30 gate: UK FAIL 2025 — exhibit, not error) | G9: =stage6_decomp!T121
B10: READING: UK and German MODELLED SYSTEM COST is similar (UK $207/$213 vs DE $211/$231 large/medium) — the UK–DE difference is WHO PAYS (policy/gen-capital recovery on UK bills), not the size of the stack. China's ~$87 is an ON-BILL price (different basis; its unquantified system cost ≤ bill). Observed 2025 bills sit ~$80/MWh above the UK modelled stack (supply margin, row 9). See Section B (Stages 6, 9).
A11: B. STAGE-BY-STAGE SYNTHESIS
B12: Stage / building block | C12: Headline finding | D12: Key metric | F12: Source tab
B13: 1-3 Method & anchors | C13: House rule fixes real-2025 USD pipeline (H.10 FX, US CPI, VAT excluded); 10 golden anchors reproduce as permanent regression tests. | E13: GN reproduce ✓ | F13: golden_numbers, fx_deflator, assumptions
B14: 4 Price assembly | C14: Nominal-local industrial series (UK day-ahead/forward; DE Phelix; CN catalogue+market) converted to a common real-2025 USD basis. | E14: see timeseries | F14: stage4_uk/de/cn, timeseries, lcoe, cn_td
B15: 5 Output & intensity | C15: Energy-intensive output paths diverge (UK severe contraction: aluminium index 16, steel 41 by 2024; DE material post-2021 contraction: EI aggregate ~81, aluminium 55; CN long-run expansion, post-2021 plateau/decline in cement/steel/glass) — shown with mandatory causal caution (price ≠ sole cause). | E15: causal caution | F15: stage5_output
B16: 6 Decomposition | C16: Five-bucket cost stack + WHO-PAYS vs WHAT-IT-COSTS: relief relocates cost (UK→bills, DE→taxpayer, CN reverse). All reconciliation gates PASS (internal, by construction — Q46; independent checks: golden numbers + observed-vs-modelled gates, Q30). | E16: 151/151 (by construction) | F16: stage6_decomp, carbon
B17: 7 Network drivers | C17: Network charges the fastest-rising bucket; UK residual +94% (26/27); DE outturn already above BDEW path; CN wire held flat, cost surfaces in system fee. | E17: UK net +60% 25→26 | F17: stage7_network
B18: 8 Supply / tech / flex | C18: None of North Sea gas, nuclear, geothermal or flexibility is a NEAR-TERM price lever (UK a gas price-taker; nuclear 10+yr & high FOAK; geothermal pre-commercial; flex indirect). | E18: not near-term | F18: north_sea_og, nuclear_global, geothermal_uk, flexibility_network
B19: 9 Policy options | C19: Balanced options: cost-SHIFTING (exemptions) vs cost-REDUCING (structural). UK converging on the German taxpayer model (BICS: Exchequer + energy-system funded, final split at Budget 2026; CPS abolition 2028). | E19: 6 levers, tagged | F19: stage9_policy
B20: 10 Integration & QC | C20: This front page + full-workbook QC: 0 formula errors, golden numbers reproduce, signed stages preserved, source/decision/qc integrity, cross-stage consistency. | E20: see C & D | F20: stage10_integration
A22: C. CROSS-STAGE CONSISTENCY CHECKS (live assertions — recompute on open)
B23: Check | C23: Expected | D23: Actual | E23: Diff | F23: Verdict
B24: Stage 9 cost-stack E1 total = Stage 6 (2026) | C24: =stage6_decomp!F166 | D24: =stage9_policy!D11 | E24: =C24-D24 | F24: =IF(ABS(E24)<0.01,"PASS","FAIL")
B25: Golden GN1b (UK XL incl CCL) reproduces | C25: 290.5 | D25: =golden_numbers!K6 | E25: =C25-D25 | F25: =IF(ABS(E25)<0.5,"PASS","FAIL")
B26: Golden GN2 (TNUoS residual /MWh) reproduces | C26: 12.32 | D26: =golden_numbers!K7 | E26: =C26-D26 | F26: =IF(ABS(E26)<0.05,"PASS","FAIL")
B27: Stage 6 UK large E1 reconciliation = 0 (max |2010–25|) | C27: 0 | D27: =SUMPRODUCT(MAX(ABS(stage6_decomp!E13:T13))) | E27: =C27-D27 | F27: =IF(ABS(E27)<0.001,"PASS","FAIL")
B28: Stage 9 who-pays UK E2 cost = Stage 6 T3 | C28: =stage6_decomp!G149 | D28: =stage9_policy!F16 | E28: =C28-D28 | F28: =IF(ABS(E28)<0.01,"PASS","FAIL")
A30: D. WORKBOOK INTEGRITY PANEL (live counts)
B31: Metric | C31: Value | D31: Target | E31: Verdict
B32: Stage 6 reconciliation gates = PASS (internal, by construction — Q46) | C32: =COUNTIF(stage6_decomp!A1:T200,"PASS") | D32: 151 | E32: =IF(C32>=D32,"PASS","CHECK")
B33: Stage 6 gates = FAIL (must be 0) | C33: =COUNTIF(stage6_decomp!A1:T200,"FAIL") | D33: 0 | E33: =IF(C33=0,"PASS","FAIL")
B34: Consistency checks passing (Section C) | C34: =COUNTIF(F24:F28,"PASS") | D34: 5 | E34: =IF(C34=D34,"PASS","FAIL")
B35: Sheets in workbook | C35: =_xlfn.SHEETS() | D35: 24 | E35: =IF(C35=D35,"PASS","FAIL")
B36: Independent validation (not by construction) | C36: GN anchors reproduce (Section C); observed-vs-modelled gates: DE large PASS; UK large/medium & DE medium FAIL 2025 — supply-margin wedge, an exhibit (Q30; timeseries r92–95) | D36: — | E36: RECORDED
A37: E. OVERALL CONCLUSION
B38: UK industrial electricity is expensive for different reasons against different peers. Against GERMANY the modelled system cost is similar (UK $207 vs DE $211 large; $213 vs $231 medium) — network+system and taxes are LOWER in the UK — and the E1 on-bill gap ($207 vs $170) is driven by policy/generation-capital recovery on bills (UK $60 vs DE $12) plus slightly dearer gas-set wholesale; the real UK–DE difference is WHO PAYS. Against CHINA the whole stack sits above (~$87 on-bill, administratively held down, industry cross-subsidising households). Network is the fastest-RISING bucket (UK residual +94% 25/26→26/27) though not above Germany's 2025 level at the large archetype. Relief relocates cost rather than removing it: the UK is moving EII relief off other bill-payers toward Exchequer + energy-system funding (BICS; final split at Budget 2026) — converging on the German taxpayer model. Supply-side options offer little near-term relief; cost-REDUCING levers (gas dependence, network growth, carbon design) are structural and slow. The modelled stack is a statutory floor: observed 2025 bills run ~$80/MWh higher (supply margin, Section A row 9). Policy choice is therefore less about the size of the stack than about who is asked to pay it — and about the slow structural work that actually lowers it.
A40: Decisions D57–D62 · QC Q73–Q82 · this front page is Stage 10. Study complete pending owner approval. Real-2025 USD; VAT excluded; blanks = unavailable (never zero). External-review fix pass 2026-07-19 (Q82/D61–D62): modelled-vs-observed labelling, conclusion aligned to decomposition, BICS funding pending Budget 2026, steel coefficients re-derived. PUBLICATION SPINE per D64 (ChatGPT v40 = challenge annex).

Sheet assumptions
A1: ASSUMPTIONS — editable inputs driving the build-up (stage 1, locked per project instructions)
A2: Blue = hardcoded input (editable). Yellow = key assumption. All verified against primary sources 2026-07-14; see sources tab.
A4: A. ARCHETYPES (locked — house rule 2)
A5: Parameter | B5: Large industrial | C5: Medium industrial | D5: Notes / verification
A6: Annual consumption (MWh/yr) | B6: 500000 | C6: 20000 | D6: Locked.
A7: Load factor / utilisation hours (h/yr) | B7: 8000 | C7: 5000 | D7: Highest-leverage assumption. Mandatory sensitivity at 6,500h (cell B_sens below).
A8: Implied average demand (MW) | B8: =B6/B7 | C8: =C6/C7 | D8: Formula: consumption / hours. Large ≈62.5 MW, medium 4 MW.
A9: Connection — UK | B9: Transmission / EHV | C9: 11–33kV (HV, distribution) | D9: 132kV = distribution in England & Wales, transmission in Scotland — VERIFIED: Electricity Act 1989 s.64(1) & s.4(4), legislation.gov.uk, retr. 2026-07-14.
A10: Connection — DE | B10: Höchst-/Hochspannung | C10: Mittelspannung | D10: Standard German voltage-level taxonomy (StromNEV).
A11: Connection — CN | B11: 220kV及以上 | C11: 10(20)kV | D11: 526号文 tariff classes: 不满1kV / 1-10(20)kV / 35kV / 110kV / 220kV+. RESOLVED (D10, user 2026-07-14): 10(20)kV — physically typical for ~5,000 kVA; conservative. 35kV reported as intra-country spread (Jiangsu T&D ≈ −13% at 35kV).
A13: B. SITES & VERIFIED NETWORK PARAMETERS
A14: Parameter | B14: Value | C14: Applies to | D14: Source / verification (retr. 2026-07-14)
A15: UK site | B15: Humber | C15: both | D15: Locked. Real EII cluster (Immingham/Scunthorpe/Hull).
A16: UK TNUoS demand zone | B16: Zone 5 — Yorkshire | C16: both | D16: NESO Final TNUoS Tariffs 2025/26 v1.0, App. H p.68: zone 5/7 boundary runs south of the Humber; BOTH banks in zone 5.
A17: UK TNUoS locational demand tariff 2025/26 (£/kW) | B17: 0 | C17: large | D17: Zone 5 zero-floored ('Zones 1–7 subject to the zero floor'), Table 9 p.22, Table 11 p.24. Pre-floor: Peak −0.790016, Year Round −4.258236 £/kW (Table 25 p.52).
A18: UK TCR band — large (transmission) | B18: T-Demand4 | C18: large | D18: 500,000 MWh > 189,873 MWh threshold (25/26) and > 163,880 (26/27). NESO Tables sheet TB.
A19: UK TCR residual 2025/26 (£/site/day) | B19: 12796.715 | C19: large | D19: NESO Final TNUoS 2025/26, Table 10 p.23. Band has 5 sites.
A20: UK TCR residual 2026/27 (£/site/day) | B20: 20829.237 | C20: large | D20: NESO Final TNUoS 2026/27, Tables T10/TB. Thresholds re-set for RIIO-3.
A21: UK DNO — both Humber banks | B21: Northern Powergrid (Yorkshire) | C21: medium | D21: VERIFIED: North Lincolnshire is Northern Powergrid, NOT NGED East Midlands (nationalgrid.com Grimsby-Walpole 'Need for project'; northernpowergrid.com/about-us). See decision D5. Licence-name attribution high-confidence, not document-level (qc log).
A22: UK DUoS statement — medium | B22: NPg (Yorkshire) LC14 CDCM 2025-26 | C22: medium | D22: Title verified via site index only (JS-rendered page) — flagged in qc.
A23: UK TCR band — medium (inferred) | B23: HV4 — £317.597969/site/day | C23: medium | D23: INFERRED from published kVA thresholds (HV4 >1,800 kVA); allocation is done by DNO on agreed capacity. estimated=Y; qc log.
A24: DE site | B24: Rhine-Ruhr | C24: both | D24: Locked.
A25: DE TSO | B25: Amprion | C25: large | D25: amprion.net 'Unser Netz' — control area covers NRW/Rhine-Ruhr.
A26: DE transmission charges harmonised? | B26: Yes, since 01.01.2023 | C26: large | D26: StromNEV §3(3), §§14a–14d (bundeseinheitliche ÜNB-Entgelte), gesetze-im-internet.de. Joint ÜNB price sheet 2026 dated 05.12.2025, netztransparenz.de. Locational variable is therefore the DSO region, as hypothesised.
A27: DE DSO | B27: Westnetz | C27: medium | D27: Largest German DSO, Rhine-Ruhr footprint; exact service-area sentence not readable on rendered page (qc log).
A28: DE §19(2) StromNEV — large archetype | B28: Qualifies, Satz 2/3 Nr.3 (≥8,000h & >10 GWh) → floor 10% | C28: large | D28: StromNEV §19(2) current text, gesetze-im-internet.de: floors 20/15/10% at 7,000/7,500/8,000h — FLOORS, not tariffs. In force through 2028; abolition scheduled with StromNEV expiry end-2028, Bandlast grandfathering intended to 31.12.2031 (BNetzA AgNes Orientierungspunkte 22.04.2026, GBK-25-01-1#3, p.17).
A29: DE §19(2) — medium archetype | B29: Does NOT qualify (5,000h < 7,000h) | C29: medium | D29: Satz 2 requires ≥7,000h AND >10 GWh. Atypical-use limb (Satz 1) fails for baseload — to establish in stage 4, not assumed.
A30: DE 2026 transmission subsidy | B30: €6.5bn, federal (KTF) | C30: both | D30: §24c EnWG; Gesetz BGBl. 2025 I Nr. 317, in force 12.12.2025; 2026 only. Deducted from revenue caps → ~57% cut in avg HöS charge (TSO-sourced, verbatim unverified — qc). Incidence: (iii) taxpayer.
A31: CN provincial basket | B31: JS, GD, SD, ZJ, HN, IM, SC | C31: both | D31: Locked. Weights below, 2024 vintage (decision D2), held constant.
A32: CN weight set driving build-up | B32: C | C32: both | D32: TOGGLE: 'A' = closest-to-industrial (mixed categories); 'B' = 全社会 totals; 'C' = 第二产业 secondary industry, consistent basis, with fallbacks for GD (工业) and SC (全社会). RESOLVED (D11, user 2026-07-14): Set C.
A34: C. CHINESE BASKET WEIGHTS (2024 consumption, 亿千瓦时; weights computed = estimated Y). Active set: C (decision D11).
A35: Province | B35: Set A: closest-to-industrial (亿kWh) | C35: Set B: 全社会 total (亿kWh) | D35: Set C: 第二产业 (亿kWh) | E35: Category & source flag
A36: Jiangsu 江苏 | B36: 5752 | C36: 8487 | D36: 5752 | E36: Set A = Set C = 第二产业 (SGCC Jiangsu 2024 CSR data via jiangsu.gov.cn 2025-03-26); 全社会 8486.93 per NEA Jiangsu office.
A37: Guangdong 广东 | B37: 5216.25 | C37: 9121.03 | D37: 5216.25 | E37: FLAG (Set C): GD publishes NO 第二产业 aggregate (checked grid, energy bureau, 统计年鉴2025 表7-6) — fallback to 工业 5216.25 per D11. Derived alternative 工业5217.39+建筑业102.68=5320.07 (yearbook 7-6, NBS energy classification) noted, not used.
A38: Shandong 山东 | B38: 6005.1 | C38: 8319.7 | D38: 6071.1 | E38: Set A = 工业; Set C = 第二产业 6071.1 (+2.8%) — Shandong Statistics Bureau note 2025-01-22, VERIFIED.
A39: Zhejiang 浙江 | B39: 4435.4 | C39: 6780 | D39: 4515.5 | E39: Set A = 工业; Set C = 第二产业 4515.5 (+7.8%) — 国网浙江 via 新华网 2025-01-20, VERIFIED (grid-company data flag).
A40: Henan 河南 | B40: 2283.25 | C40: 4319.94 | D40: 2330.71 | E40: Set A = 工业; Set C = 第二产业 2330.71 (本年累计, NEA Henan Table 2; row check 87.14+2330.71+925.09+977=4319.94 ✓), VERIFIED.
A41: Inner Mongolia 内蒙古 | B41: 4539.12 | C41: 5193.41 | D41: 4539.12 | E41: Set A = Set C = 第二产业. FLAG: source is industry-association republication of grid statistics (now read directly; no better official source exists — 2024 statistical bulletin has no consumption breakdown). Swing constituent — report basket with/without.
A42: Sichuan 四川 | B42: 4000 | C42: 4000 | D42: 2404.56 | E42: Set C = 第二产业 2404.56 亿千瓦时 (2024, +3.36%) — Q6 CLOSED 2026-07-15 via 硕电汇/北极星 year-end summary (news.bjx.com.cn/html/20250123/1424280.shtml, image tables); components sum to 全社会 3999.69 exactly (38.84+2404.56+780.93+775.36). Set A/B still 全社会 placeholder 4000 — flagged (active set = C per D11).
A43: Sum | B43: =SUM(B36:B42) | C43: =SUM(C36:C42) | D43: =SUM(D36:D42)
A44: Normalised weights (formula-driven):
A45: Province | B45: Weight A | C45: Weight B | D45: Weight C | E45: Active weight (per toggle B32)
A46: Jiangsu 江苏 | B46: =B36/$B$43 | C46: =C36/$C$43 | D46: =D36/$D$43 | E46: =IF($B$32="A",B46,IF($B$32="B",C46,D46))
A47: Guangdong 广东 | B47: =B37/$B$43 | C47: =C37/$C$43 | D47: =D37/$D$43 | E47: =IF($B$32="A",B47,IF($B$32="B",C47,D47))
A48: Shandong 山东 | B48: =B38/$B$43 | C48: =C38/$C$43 | D48: =D38/$D$43 | E48: =IF($B$32="A",B48,IF($B$32="B",C48,D48))
A49: Zhejiang 浙江 | B49: =B39/$B$43 | C49: =C39/$C$43 | D49: =D39/$D$43 | E49: =IF($B$32="A",B49,IF($B$32="B",C49,D49))
A50: Henan 河南 | B50: =B40/$B$43 | C50: =C40/$C$43 | D50: =D40/$D$43 | E50: =IF($B$32="A",B50,IF($B$32="B",C50,D50))
A51: Inner Mongolia 内蒙古 | B51: =B41/$B$43 | C51: =C41/$C$43 | D51: =D41/$D$43 | E51: =IF($B$32="A",B51,IF($B$32="B",C51,D51))
A52: Sichuan 四川 | B52: =B42/$B$43 | C52: =C42/$C$43 | D52: =D42/$D$43 | E52: =IF($B$32="A",B52,IF($B$32="B",C52,D52))
A54: D. OTHER LOCKED CONVENTIONS & SENSITIVITY INPUTS
A55: Hedging / procurement convention | B55: Rolling year-ahead baseload | D55: Locked; identical in all three countries. Day-ahead (N2EX/EPEX) is an input, not the price. Mandatory sensitivity vs day-ahead-indexed (stage 4).
A56: Load-factor sensitivity (h/yr) | B56: 6500 | D56: Mandatory: whole build-up re-run at non-qualifying load factor; German 7,000h threshold charted explicitly (stage 4).
A57: FX source | B57: Federal Reserve H.10 / G.5A annual averages (via FRED) | D57: Decision D1, user-approved 2026-07-14. One source, all three currencies.
A58: Deflator | B58: US CPI-U annual average, NSA (BLS CUUR0000SA0) | D58: House rule 1. 2025 annual average final (321.943).
A59: Currency/unit convention | B59: Real 2025 USD/MWh; market FX; no PPP; VAT excluded (CN series 含税 as published — Q84) | D59: House rule 1. Chart footnote fixed.
A60: Snapshot years | B60: 2025 AND 2026 | D60: All three regimes change in 2026 (UK NCC 60→90%; DE €6.5bn subsidy + §19 reform path; CN 136号文 + 4th-period T&D). 2025→2026 delta is an explicit exhibit.
A61: UK EII relief parameters (verified) | B61: 100% CfD/RO/FiT exemption (from 04/2024); 100% CM exemption (10/2024); NCC 60% (04/2025, backdated 04/2024) → 90% from 01.04.2026 | D61: DBT consultation response upd. 31.10.2025, gov.uk; SI 2024/409; SI 2026/243. Recovery: EII Support Levy on licensed suppliers — incidence (ii) other electricity users. NCC pays 12 months in arrears.
A62: Medium archetype E2 status | B62: EII status assumed — UK reliefs + DE BesAR apply (no §19: fails 7,000h) | D62: Decision D24, user-approved 2026-07-15. Stated on every E2 chart.
A64: E. STAGE 8 INPUTS (evidence stage; every value tagged; blank=unavailable, NOT zero)
A65: Real-2025 basis | B65: real 2025 USD (house rule 1) / real 2025 GBP (UK deflator, Stage-8 only) | E65: USD via fx_deflator; GBP via HMT GDP deflator S120
A66: Nuclear proxy WACC (real) | B66: 0.07 | E66: Stage-8 nuclear indicative LCOE proxies (Vogtle) + Flamanville central case
A67: Nuclear proxy life (yr) | B67: 60 | E67: OECD/NEA convention; capital-recovery-factor basis
A68: Capital recovery factor @7%/60yr | B68: =0.07*(1.07^60)/((1.07^60)-1) | E68: CRF for annualised-cost proxies (shown, not hard-coded)
A69: Vogtle assumed capacity factor | B69: 0.9 | E69: ASSUMED — Vogtle annual generation not disclosed (GAP); conservative CF on 2x1117 MW net
A70: Vogtle net capacity (MW) | B70: 2234 | E70: 2 x 1117 MWe net (Georgia Power fact sheet / IAEA PRIS)
A71: Vogtle O&M+fuel assumption (USD/MWh, 2018) | B71: 20.93 | E71: DISCLOSED PROXY = OECD/NEA 2020 US LWR O&M 11.60 + fuel 9.33 (2018 USD); Vogtle-specific value is GAP
A72: Flexibility baseline GB peak 2024 (GW) | B72: 46 | E72: DUKES 5.10.A GB simultaneous max (Stage-7 anchor)
A73: Flexibility baseline GB supplied 2024 (TWh) | B73: 270.88 | E73: DUKES 5.1.2 (Stage-7 anchor)
A74: Flexibility firm peak reduction low/central/high (GW) | B74: 3 / 6 / 12 | E74: SCENARIO inputs (grounded in NIC/CT/FES ranges; this-decade firm reduction)
A75: TNUoS demand residual 2026/27 (GBP bn) | B75: 6.26517 | E75: NESO Final TNUoS Tariffs 2026/27, 30.01.2026, doc 376336, Table 10 (S2) — re-verified against the primary 2026-07-26. Fixed banded GBP/site/day under TCR. Q99 2026-07-26: RE-BASED from the Five-Year View v3.0 forecast of GBP 7.52bn (S107), which was 17% high. Documentation row — no formula reads this cell.
A76: UK GDP deflator basis | B76: HMT GDP deflators June 2026, L8GG, FY, 2025-26=100 | E76: S120; calendar->FY map = FY starting in year Y (estimated=Y)
A78: UK line losses — demand TLM (transmission), all archetypes | B78: 0.008 | C78: Elexon BSC Section T: TLM = 1 + TLF + TLMO-. Demand takes 55% of transmission losses. TLMO- annual averages 0.0077 (BSC yr 2021/22) to 0.0118 (2024/25), 0.0092 (2026/27); Yorkshire (zone 12, GSP _M) TLF is a small negative in all seasons — exact value portal-gated, so the zonal term is set to 0 and the residual TLMO- carries it. Central 0.008, range 0.003-0.012. Cross-check: NESO puts GB transmission losses at ~1.7% of transfer, x55% = 0.94%. S197.
A79: UK line losses — distribution LLF, LARGE (CVA transmission-connected) | B79: 1 | C79: A CVA transmission-connected site takes no distribution LLF. If the large archetype were instead 132 kV on the DNO network the figure would be 1.010 (NPg Yorkshire >22kV demand, annual blend) and the uplift would roughly double — a 1pp swing, flagged. S197.
A80: UK line losses — distribution LLF, MEDIUM (HV network) | B80: 1.024 | C80: Northern Powergrid (Yorkshire) Annex 5, HV Network class, annual blend, charging year 2025/26. Multiplier applied to metered volume in settlement. Effectively FLAT over the panel: P1 1.032 (2017/18) -> 1.029 (2020/21) -> 1.028 (2023/24) -> 1.028 (2025/26); pre-2017 values not found, constant held and flagged. Note LV moved the OTHER way (1.110 -> 1.150) because non-technical losses land there — do not reuse this constant for LV. S197.

Sheet fx_deflator
A1: FX & DEFLATOR — Fed H.10/G.5A annual averages (FRED); BLS CPI-U CUUR0000SA0 M13. Retrieved 2026-07-14.
A2: G.5A release 05.01.2026 cross-checks FRED exactly for 2022–2025. CPI-U 2025 final per BLS API (no footnote flag). No 2026 annual averages exist yet — any 2026 conversion is provisional (decision D6).
H3: HELPER — contiguous 2010–2026 lookup for timeseries formulas (references the blocks above; 2026 FX blank per D6)
A4: Year | B4: USD per GBP | C4: USD per EUR | D4: CNY per USD | E4: CPI-U (1982-84=100) | F4: Deflator to 2025 | H4: Year | I4: USD per GBP | J4: USD per EUR | K4: CNY per USD | L4: CPI-U | M4: Deflator to 2025
A5: 2020 | B5: 1.2829 | C5: 1.141 | D5: 6.9042 | E5: 258.811 | F5: =$E$10/E5 | H5: 2010 | I5: =B13 | J5: =C13 | K5: =D13 | L5: =E13 | M5: =F13
A6: 2021 | B6: 1.3764 | C6: 1.183 | D6: 6.4508 | E6: 270.97 | F6: =$E$10/E6 | H6: 2011 | I6: =B14 | J6: =C14 | K6: =D14 | L6: =E14 | M6: =F14
A7: 2022 | B7: 1.2371 | C7: 1.0534 | D7: 6.729 | E7: 292.655 | F7: =$E$10/E7 | H7: 2012 | I7: =B15 | J7: =C15 | K7: =D15 | L7: =E15 | M7: =F15
A8: 2023 | B8: 1.244 | C8: 1.0817 | D8: 7.0809 | E8: 304.702 | F8: =$E$10/E8 | H8: 2013 | I8: =B16 | J8: =C16 | K8: =D16 | L8: =E16 | M8: =F16
A9: 2024 | B9: 1.2781 | C9: 1.082 | D9: 7.1957 | E9: 313.689 | F9: =$E$10/E9 | H9: 2014 | I9: =B17 | J9: =C17 | K9: =D17 | L9: =E17 | M9: =F17
A10: 2025 | B10: 1.3192 | C10: 1.1306 | D10: 7.1875 | E10: 321.943 | F10: =$E$10/E10 | H10: 2015 | I10: =B18 | J10: =C18 | K10: =D18 | L10: =E18 | M10: =F18
H11: 2016 | I11: =B19 | J11: =C19 | K11: =D19 | L11: =E19 | M11: =F19
A12: Additional years: CPI-U (BLS API, retr. 2026-07-14); FX 2010–2019 added 2026-07-15 (FRED fredgraph.csv annual avg: DEXUSUK, DEXUSEU, DEXCHUS — Fed H.10, per D1). | H12: 2017 | I12: =B20 | J12: =C20 | K12: =D20 | L12: =E20 | M12: =F20
A13: 2010 | B13: 1.5452 | C13: 1.3261 | D13: 6.7696 | E13: 218.056 | F13: =$E$10/E13 | H13: 2018 | I13: =B21 | J13: =C21 | K13: =D21 | L13: =E21 | M13: =F21
A14: 2011 | B14: 1.6043 | C14: 1.3931 | D14: 6.463 | E14: 224.939 | F14: =$E$10/E14 | H14: 2019 | I14: =B22 | J14: =C22 | K14: =D22 | L14: =E22 | M14: =F22
A15: 2012 | B15: 1.5853 | C15: 1.2859 | D15: 6.3093 | E15: 229.594 | F15: =$E$10/E15 | H15: 2020 | I15: =B5 | J15: =C5 | K15: =D5 | L15: =E5 | M15: =F5
A16: 2013 | B16: 1.5642 | C16: 1.3281 | D16: 6.1478 | E16: 232.957 | F16: =$E$10/E16 | H16: 2021 | I16: =B6 | J16: =C6 | K16: =D6 | L16: =E6 | M16: =F6
A17: 2014 | B17: 1.6484 | C17: 1.3297 | D17: 6.162 | E17: 236.736 | F17: =$E$10/E17 | H17: 2022 | I17: =B7 | J17: =C7 | K17: =D7 | L17: =E7 | M17: =F7
A18: 2015 | B18: 1.5284 | C18: 1.1096 | D18: 6.2827 | E18: 237.017 | F18: =$E$10/E18 | H18: 2023 | I18: =B8 | J18: =C8 | K18: =D8 | L18: =E8 | M18: =F8
A19: 2016 | B19: 1.3555 | C19: 1.1072 | D19: 6.64 | E19: 240.007 | F19: =$E$10/E19 | H19: 2024 | I19: =B9 | J19: =C9 | K19: =D9 | L19: =E9 | M19: =F9
A20: 2017 | B20: 1.289 | C20: 1.1301 | D20: 6.7569 | E20: 245.12 | F20: =$E$10/E20 | H20: 2025 | I20: =B10 | J20: =C10 | K20: =D10 | L20: =E10 | M20: =F10
A21: 2018 | B21: 1.3363 | C21: 1.1817 | D21: 6.609 | E21: 251.107 | F21: =$E$10/E21 | H21: 2026
A22: 2019 | B22: 1.2768 | C22: 1.1194 | D22: 6.9081 | E22: 255.657 | F22: =$E$10/E22

Sheet golden_numbers
A1: GOLDEN NUMBERS — published anchors reproduced through the full house-rule pipeline (nominal local → Fed H.10 annual-avg FX → US CPI-U → real 2025 USD/MWh). Permanent regression tests.
A2: Set approved by user 2026-07-14 (decision D3). Conversion columns are FORMULAS reading fx_deflator and assumptions. 'estimated=Y' marks any computed (not retrieved) step. Excludes VAT throughout.
A4: GN | B4: Description | C4: As-published value | D4: Native unit | E4: Data year | F4: FX year | G4: Local /MWh | H4: FX rate | I4: Nominal USD/MWh | J4: Deflator | K4: Real 2025 USD/MWh | L4: estimated? | M4: Modelled/observed | N4: Citation (source — table/page — URL — retrieved 2026-07-14)
A5: GN1a | B5: DESNZ QEP: UK non-domestic electricity price, Extra Large band (>150,000 MWh/yr), 2024 annual, EXCL CCL, excl VAT | C5: 21.697865 | D5: p/kWh | E5: 2024 | F5: 2024 | G5: =C5*10 | H5: =fx_deflator!$B$9 | I5: =IF(D5="CNY/MWh basis",G5/H5,G5*H5) | J5: =fx_deflator!$F$9 | K5: =I5*J5 | L5: N | M5: Observed (published) | N5: DESNZ QEP, Gas & electricity prices in the non-domestic sector, table_341.xlsx, sheet '3.4.1 (Annual excl CCL)' (pub. 30.06.2026) — https://assets.publishing.service.gov.uk/media/6942bd3536f089d38be1f246/table_341.xlsx — retr. 2026-07-14. Displays as 21.70. Note: 3.4.x = non-domestic consumers (not the GB manufacturing tables 3.1.x).
A6: GN1b | B6: Same, INCLUDING CCL (variant) | C6: 22.146382 | D6: p/kWh | E6: 2024 | F6: 2024 | G6: =C6*10 | H6: =fx_deflator!$B$9 | I6: =IF(D6="CNY/MWh basis",G6/H6,G6*H6) | J6: =fx_deflator!$F$9 | K6: =I6*J6 | L6: N | M6: Observed (published) | N6: Same file, sheet '3.4.2 (Annual inc CCL)'. Displays as 22.15. VAT excluded in both.
A7: GN2 | B7: NESO TNUoS 2025/26, T-Demand4 residual (Humber zone 5; locational tariff = 0, zero-floored). Per-MWh line converts the published £/site/day through the LARGE archetype (×365 ÷ assumptions!B6) — construction check, computed | C7: 12796.715 | D7: £/site/day | E7: 2025 | F7: 2025 | G7: =C7*365/assumptions!$B$6 | H7: =fx_deflator!$B$10 | I7: =IF(D7="CNY/MWh basis",G7/H7,G7*H7) | J7: =fx_deflator!$F$10 | K7: =I7*J7 | L7: Y | M7: Published tariff; per-MWh step modelled | N7: NESO, Final TNUoS Tariffs 2025/26 v1.0 (31.01.2025), Table 10 p.23 (residual), Table 9 p.22 & Table 11 p.24 (zero floor zones 1–7), App. H p.68 (zone map) — https://www.neso.energy/document/353086/download — retr. 2026-07-14. 2026/27: £20,829.236682/site/day (doc 376336/376341). FX-year mapping per decision D4.
A8: GN3 | B8: BDEW Strompreisanalyse (Apr 2026 ed.): industrial price, kleine/mittlere Industrie Musterkunde (avg of 5 cases 160 MWh–20 GWh/yr, Mittelspannung, new contracts, incl reduced Stromsteuer), 2025 annual | C8: 17.6 | D8: ct/kWh | E8: 2025 | F8: 2025 | G8: =C8*10 | H8: =fx_deflator!$C$10 | I8: =IF(D8="CNY/MWh basis",G8/H8,G8*H8) | J8: =fx_deflator!$F$10 | K8: =I8*J8 | L8: N | M8: Observed (published) | N8: BDEW-Strompreisanalyse April 2026 (15.04.2026), Folie 12 annual series (2024: 17.3; 2026: 16.7) — https://www.bdew.de/media/documents/BDEW_Strompreisanalyse_042026.pdf — retr. 2026-07-14. 2026 figure NOT converted: no 2026 annual FX exists yet (decision D6). Closest match to MEDIUM archetype.
A9: GN4s1 | B9: Eurostat nrg_pc_205, DE, band IF (70–150 GWh), 2024-S1, X_VAT (excl VAT & other recoverable) | C9: 0.1394 | D9: EUR/kWh | E9: 2024 | F9: 2024 | G9: =C9*1000 | H9: =fx_deflator!$C$9 | I9: =IF(D9="CNY/MWh basis",G9/H9,G9*H9) | J9: =fx_deflator!$F$9 | K9: =I9*J9 | L9: N | M9: Observed (published) | N9: Eurostat dissemination API, nrg_pc_205, geo=DE, nrg_cons=MWH70000-149999, tax=X_VAT, currency=EUR (dataset update 2026-05-19) — retr. 2026-07-14. X_TAX variant: 0.1276 (S1) / 0.1313 (S2).
A10: GN4s2 | B10: Same, 2024-S2 | C10: 0.143 | D10: EUR/kWh | E10: 2024 | F10: 2024 | G10: =C10*1000 | H10: =fx_deflator!$C$9 | I10: =IF(D10="CNY/MWh basis",G10/H10,G10*H10) | J10: =fx_deflator!$F$9 | K10: =I10*J10 | L10: N | M10: Observed (published) | N10: As GN4s1.
A11: GN4 | B11: Eurostat IF DE 2024 annual = simple semester average — COMPUTED (Eurostat publishes no annual value) | G11: =(G9+G10)/2 | H11: =fx_deflator!$C$9 | I11: =G11*H11 | J11: =fx_deflator!$F$9 | K11: =I11*J11 | L11: Y | M11: Computed from published | N11: Average of GN4s1/GN4s2. estimated=Y.
A12: GN5a | B12: NDRC 526号文: Jiangsu T&D price (输配电价), 工商业 two-part, 220kV+, VOLUMETRIC 电量电价 (3rd regulatory period, eff. 01.06.2023; still applied in SGCC Jiangsu Mar-2026 agency-purchase notice) 含税 as published (Q84). | C12: 0.0597 | D12: CNY/MWh basis | E12: 2025 | F12: 2025 | G12: =C12*1000 | H12: =fx_deflator!$D$10 | I12: =IF(D12="CNY/MWh basis",G12/H12,G12*H12) | J12: =fx_deflator!$F$10 | K12: =I12*J12 | L12: N | M12: Observed (published) | N12: 国家发展改革委 发改价格〔2023〕526号, annex 省级电网输配电价表, 江苏 row 工商业·两部制 — https://www.ndrc.gov.cn/xxgk/zcfb/tz/202305/P020230515609052875117.pdf — retr. 2026-07-14. Cross-check: SGCC Jiangsu 2026-03 代理购电公告 附件6 (0.0597 / 41.6 / 26.0). Includes VAT & base-period cross-subsidy; excludes 政府性基金及附加, line loss (3.18%), pumped-storage capacity fee. Native unit 元/千瓦时.
A13: GN5b | B13: Same row: DEMAND charge 需量电价 41.6 元/kW·月, converted to per-MWh through the LARGE archetype: ×12 months ÷ (hours×MW→MWh per kW = B7/1000) — computed | C13: 41.6 | D13: CNY/MWh basis | E13: 2025 | F13: 2025 | G13: =C13*12/(assumptions!$B$7/1000) | H13: =fx_deflator!$D$10 | I13: =IF(D13="CNY/MWh basis",G13/H13,G13*H13) | J13: =fx_deflator!$F$10 | K13: =I13*J13 | L13: Y | M13: Published tariff; per-MWh step modelled | N13: Same table/row, column 需量电价. Capacity variant 容量电价 26.0 元/kVA·月. At 8,000h: 499.2 元/kW·yr ÷ 8 MWh/kW = 62.4 元/MWh. Load-factor sensitivity runs through assumptions!B7.
A14: GN5 | B14: Jiangsu 220kV all-in T&D for large archetype (volumetric + demand) — construction check | I14: =I12+I13 | J14: =fx_deflator!$F$10 | K14: =I14*J14 | L14: Y | M14: Modelled from published | N14: Sum of GN5a + GN5b nominal USD. Note 4th-period notice (发改价格〔2026〕1077号, reported 10.07.2026) reportedly supersedes from 2026 — UNVERIFIED at primary level, see qc Q1.
A16: Chart/table footnote (house rule 1): "Real 2025 USD/MWh. Converted at annual-average market FX. Excludes VAT (UK/DE; CN carried 含税 as published — Q84)."

Sheet lcoe
A1: LCOE COMPARISON — UK / DE / CN (stage 3). LCOE IS CONTEXT, NOT CAUSE: it is not the driver of industrial retail prices; the archetype build-up (stages 4/6) is the study's spine.
A2: Footnote (all USD columns): Real 2025 USD/MWh. Converted at annual-average market FX. Excludes VAT. As-published values quoted exactly in native units/price base; every conversion and every modelled figure is estimated=Y.
A4: 1. AS-PUBLISHED LCOE + MANDATORY ASSUMPTIONS (WACC, CF, fuel, carbon, lifetime, capex)
A5: Ctry | B5: Technology | C5: Source / edition | D5: LCOE low | E5: LCOE high/pt | F5: Native unit | G5: Price base | H5: Data yr | I5: WACC (native) | J5: WACC basis | K5: CF / FLH | L5: Life (y) | M5: Capex as published | N5: Fuel assumption | O5: Carbon assumption | P5: estimated? | Q5: Real25 USD low | R5: Real25 USD high/pt | S5: Citation (retrieved 2026-07-14)
A6: UK | B6: CCGT H-class | C6: DESNZ EGC 2023, Tbl 10 + Annex A | E6: 114 | F6: £/MWh | G6: real 2021 GBP | H6: 2025 comm. | I6: 7.5% | J6: hurdle, pre-tax real | K6: 93% LF | L6: 25 | M6: £610/kW + infra | N6: component £43/MWh (EGC 2023 basis) | O6: component £60/MWh | P6: N | R6: =E6*fx_deflator!$B$6*fx_deflator!$F$6 | S6: DESNZ, Electricity Generation Costs 2023 (Nov 2023), Table 10 p.24; Annex A 2023 sheets 'Additional estimates 2025' / 'Technical and cost assumptions' — gov.uk — retr. 2026-07-14. USER DECISION D16: 2023 edition used for 2025 commissioning; EGC 2025 (Jan 2026) starts at 2030 and uses a different carbon methodology — not like-for-like.
A7: UK | B7: OCGT (300MW, 2000h) | C7: DESNZ EGC 2023, Annex A | E7: 197 | F7: £/MWh | G7: real 2021 GBP | H7: 2025 comm. | I7: 7.1% | J7: hurdle, pre-tax real | K7: 22% LF | L7: 25 | M7: £530/kW + infra | N7: component £67/MWh | O7: component £94/MWh | P7: N | R7: =E7*fx_deflator!$B$6*fx_deflator!$F$6 | S7: Annex A 2023, 'Additional estimates 2025', column 'OCGT 300MW 2000 hr' Total = 197.
A8: UK | B8: Onshore wind | C8: DESNZ EGC 2023, Tbl 10 | E8: 38 | F8: £/MWh | G8: real 2021 GBP | H8: 2025 comm. | I8: 5.2% | J8: hurdle, pre-tax real | K8: 45% LF | L8: 25 | M8: £1,230/kW + infra | N8: — | O8: — | P8: N | R8: =E8*fx_deflator!$B$6*fx_deflator!$F$6 | S8: Table 10 p.24.
A9: UK | B9: Offshore wind | C9: DESNZ EGC 2023, Tbl 10 | E9: 44 | F9: £/MWh | G9: real 2021 GBP | H9: 2025 comm. | I9: 6.3% | J9: hurdle, pre-tax real | K9: 61% LF | L9: 30 | M9: £1,630/kW + infra | N9: — | O9: — | P9: N | R9: =E9*fx_deflator!$B$6*fx_deflator!$F$6 | S9: Table 10 p.24.
A10: UK | B10: Solar PV (large) | C10: DESNZ EGC 2023, Tbl 10 | E10: 41 | F10: £/MWh | G10: real 2021 GBP | H10: 2025 comm. | I10: 5.0% | J10: hurdle, pre-tax real | K10: 11% LF | L10: 35 | M10: £450/kW + infra | N10: — | O10: — | P10: N | R10: =E10*fx_deflator!$B$6*fx_deflator!$F$6 | S10: Table 10 p.24.
A11: UK | B11: Coal | C11: — | P11: GAP | S11: NOT COVERED by DESNZ series (recent editions). Gap is a finding.
A12: UK | B12: Nuclear | C12: — | P12: GAP | S12: NOT PUBLISHED: EGC 2025 withholds Sizewell C / SMR costs as commercially sensitive; no nuclear LCOE in 2023/2020 editions (last: 2016 edition, not retrieved).
A13: DE | B13: Lignite (new build) | C13: Fraunhofer ISE Jul 2024 | D13: 15.1 | E13: 25.7 | F13: ct/kWh | G13: real 2024 EUR | H13: 2024 | I13: 6.8% | J13: WACC real (nom 8.6%) | K13: 4,300–6,300 FLH | L13: 40 | M13: €1,850–2,550/kW | N13: €2.3/MWh_th | O13: EU ETS €75–90/t (2024) | P13: N | Q13: =D13*10*fx_deflator!$C$9*fx_deflator!$F$9 | R13: =E13*10*fx_deflator!$C$9*fx_deflator!$F$9 | S13: Fraunhofer ISE, Stromgestehungskosten Erneuerbare Energien, Juli 2024, pp.3/19 (bands), Tabellen 1–7 (assumptions) — ise.fraunhofer.de — retr. 2026-07-14. Bands: low capex+best resource / high capex+worst.
A14: DE | B14: Hard coal (new build) | C14: Fraunhofer ISE Jul 2024 | D14: 17.3 | E14: 29.3 | F14: ct/kWh | G14: real 2024 EUR | H14: 2024 | I14: 6.8% | J14: WACC real | K14: 3,000–5,200 FLH | L14: 30 | M14: €1,700–2,300/kW | N14: €11.6/MWh_th | O14: EU ETS €75–90/t | P14: N | Q14: =D14*10*fx_deflator!$C$9*fx_deflator!$F$9 | R14: =E14*10*fx_deflator!$C$9*fx_deflator!$F$9 | S14: Same, pp.3/19.
A15: DE | B15: CCGT (GuD) | C15: Fraunhofer ISE Jul 2024 | D15: 10.9 | E15: 18.1 | F15: ct/kWh | G15: real 2024 EUR | H15: 2024 | I15: 6.4% | J15: WACC real | K15: 3,000–6,300 FLH | L15: 30 | M15: €900–1,300/kW | N15: €38/MWh_th (27 from 2030) | O15: EU ETS €75–90/t | P15: N | Q15: =D15*10*fx_deflator!$C$9*fx_deflator!$F$9 | R15: =E15*10*fx_deflator!$C$9*fx_deflator!$F$9 | S15: Same, pp.3–4/19 (p.4 prints 18.0 — internal source discrepancy, flagged qc).
A16: DE | B16: OCGT (Gasturbine) | C16: Fraunhofer ISE Jul 2024 | D16: 15.4 | E16: 32.6 | F16: ct/kWh | G16: real 2024 EUR | H16: 2024 | I16: 6.4% | J16: WACC real | K16: 500–3,000 FLH | L16: 30 | M16: €450–700/kW | N16: €38/MWh_th | O16: EU ETS €75–90/t | P16: N | Q16: =D16*10*fx_deflator!$C$9*fx_deflator!$F$9 | R16: =E16*10*fx_deflator!$C$9*fx_deflator!$F$9 | S16: Same, pp.3/19.
A17: DE | B17: Onshore wind | C17: Fraunhofer ISE Jul 2024 | D17: 4.3 | E17: 9.2 | F17: ct/kWh | G17: real 2024 EUR | H17: 2024 | I17: 3.9% | J17: WACC real | K17: 1,800–3,200 FLH | L17: 25 | M17: €1,300–1,900/kW | N17: — | O17: — | P17: N | Q17: =D17*10*fx_deflator!$C$9*fx_deflator!$F$9 | R17: =E17*10*fx_deflator!$C$9*fx_deflator!$F$9 | S17: Same, pp.3/19.
A18: DE | B18: Offshore wind | C18: Fraunhofer ISE Jul 2024 | D18: 5.5 | E18: 10.3 | F18: ct/kWh | G18: real 2024 EUR | H18: 2024 | I18: 6.0% | J18: WACC real | K18: 3,200–4,500 FLH | L18: 25 | M18: €2,200–3,400/kW (incl. shore connection) | N18: — | O18: — | P18: N | Q18: =D18*10*fx_deflator!$C$9*fx_deflator!$F$9 | R18: =E18*10*fx_deflator!$C$9*fx_deflator!$F$9 | S18: Same, pp.3/19.
A19: DE | B19: Solar PV (Freifläche) | C19: Fraunhofer ISE Jul 2024 | D19: 4.1 | E19: 6.9 | F19: ct/kWh | G19: real 2024 EUR | H19: 2024 | I19: 3.5% | J19: WACC real | K19: 935–1,280 kWh/kWp | L19: 30 | M19: €700–900/kW | N19: — | O19: — | P19: N | Q19: =D19*10*fx_deflator!$C$9*fx_deflator!$F$9 | R19: =E19*10*fx_deflator!$C$9*fx_deflator!$F$9 | S19: Same, pp.18–19/21.
A20: DE | B20: Nuclear (new build) | C20: Fraunhofer ISE Jul 2024 | D20: 13.6 | E20: 49 | F20: ct/kWh | G20: real 2024 EUR | H20: 2024 | I20: 7.8% | J20: WACC real | K20: 4,300–6,300 FLH | L20: 45 | M20: €6,000–16,000/kW | N20: uranium €8/MWh_th | O20: — | P20: N | Q20: =D20*10*fx_deflator!$C$9*fx_deflator!$F$9 | R20: =E20*10*fx_deflator!$C$9*fx_deflator!$F$9 | S20: Same, pp.3/19. EXCLUDES back-end/decommissioning/final storage (p.3) — health warning on any chart.
A21: CN | B21: Coal (new build) | C21: IEA WEO 2025, Tbl B.4a | E21: 65 | F21: USD/MWh | G21: 2024 USD | H21: 2024 | I21: 8–9% | J21: standard WACC, thermal | K21: 50% CF | L21: n/p | M21: $800/kW | N21: 10-yr avg from 2024 | O21: in scenario | P21: N | R21: =E21*fx_deflator!$F$9 | S21: IEA, World Energy Outlook 2025 (12.11.2025), Annex B, Table B.4a p.454 (2024 values identical in B.4b) — iea.org — retr. 2026-07-14. USER DECISION D17: international analyses for CN thermal/nuclear.
A22: CN | B22: Gas CCGT | C22: IEA WEO 2025, Tbl B.4a | E22: 100 | F22: USD/MWh | G22: 2024 USD | H22: 2024 | I22: 8–9% | J22: standard WACC, thermal | K22: 30% CF | L22: n/p | M22: $560/kW | N22: 10-yr avg from 2024 | O22: in scenario | P22: N | R22: =E22*fx_deflator!$F$9 | S22: Same table.
A23: CN | B23: Nuclear | C23: IEA WEO 2025, Tbl B.4a | E23: 70 | F23: USD/MWh | G23: 2024 USD | H23: 2024 | I23: 8–9% | J23: standard WACC | K23: 75% CF | L23: n/p | M23: $2,800/kW (NOAK) | N23: — | O23: — | P23: N | R23: =E23*fx_deflator!$F$9 | S23: Same table.
A24: CN | B24: Solar PV (utility) | C24: IEA WEO 2025, Tbl B.4a | E24: 45 | F24: USD/MWh | G24: 2024 USD | H24: 2024 | I24: 4–7% | J24: Cost of Capital Observatory | K24: 12% CF | L24: n/p | M24: $590/kW | N24: — | O24: — | P24: N | R24: =E24*fx_deflator!$F$9 | S24: Same table.
A25: CN | B25: Onshore wind | C25: IEA WEO 2025, Tbl B.4a | E25: 40 | F25: USD/MWh | G25: 2024 USD | H25: 2024 | I25: 4–7% | J25: as PV | K25: 23% CF | L25: n/p | M25: $860/kW | N25: — | O25: — | P25: N | R25: =E25*fx_deflator!$F$9 | S25: Same table.
A26: CN | B26: Offshore wind | C26: IEA WEO 2025, Tbl B.4a | E26: 60 | F26: USD/MWh | G26: 2024 USD | H26: 2024 | I26: 5–8% | J26: offshore band | K26: 30% CF | L26: n/p | M26: $1,520/kW | N26: — | O26: — | P26: N | R26: =E26*fx_deflator!$F$9 | S26: Same table.
A27: CN | B27: Solar PV (utility) | C27: CREEI 造价报告 2024 (28.05.2025) | E27: 0.2 | F27: 元/kWh | G27: 2024 CNY | H27: 2024 | I27: 5% | J27: 折现率 (real/nom unstated — qc) | K27: 1,200 h | L27: n/p | M27: ≈3,450 元/kW | N27: — | O27: — | P27: N | R27: =E27*1000/fx_deflator!$D$9*fx_deflator!$F$9 | S27: 水电水利规划设计总院, 中国可再生能源工程造价管理报告2024年度 — primary PDF not retrievable; verified via 2 independent reproductions (CPEM 29.05.2025; 光伏們/Sina 28.05.2025) — retr. 2026-07-14. Flag qc Q13.
A28: CN | B28: Onshore wind | C28: CREEI 造价报告 2024 | E28: 0.18 | F28: 元/kWh | G28: 2024 CNY | H28: 2024 | I28: 5% | J28: as above | K28: 2,000 h | L28: n/p | M28: ≈4,200 元/kW | N28: — | O28: — | P28: N | R28: =E28*1000/fx_deflator!$D$9*fx_deflator!$F$9 | S28: As above.
A29: CN | B29: Offshore wind | C29: CREEI 造价报告 2024 | D29: 0.25 | E29: 0.33 | F29: 元/kWh | G29: 2024 CNY | H29: 2024 | I29: 5% | J29: as above | K29: 2,800 h | L29: n/p | M29: 9,000–12,500 元/kW (typ. 9,680) | N29: — | O29: — | P29: N | Q29: =D29*1000/fx_deflator!$D$9*fx_deflator!$F$9 | R29: =E29*1000/fx_deflator!$D$9*fx_deflator!$F$9 | S29: As above.
A30: CN | B30: Solar PV / onshore / offshore | C30: IRENA RPGC 2024 (Jul 2025) — cross-check | F30: USD/kWh | G30: 2024 USD | H30: 2024 | I30: ≈5% real after-tax (default) | J30: IRENA benchmark | K30: offshore CF 37% | L30: 25 | M30: offshore TIC $1,520/kW | N30: — | O30: — | P30: N | S30: IRENA, Renewable Power Generation Costs in 2024, pp.13–18/31/43–46: PV $0.033, onshore $0.029, offshore $0.056/kWh — retr. 2026-07-14. Cross-check only; converted rows below use WEO/CREEI.
A31: CN | B31: Coal / CCGT / nuclear @7% real | C31: IEA/NEA EGC 2020 (published harmonised) | F31: USD/MWh | G31: 2018 USD | H31: 2025 comm. | I31: 7% real | J31: standardised | K31: 85% CF | L31: 40/30/60 | M31: $800/560/2500 per kW | N31: coal $88/t 6000kcal; gas $9.1/MBtu | O31: $30/tCO2 harmonised | P31: N | S31: IEA/NEA, Projected Costs of Generating Electricity 2020, Tables 3.11a/3.12/3.13a — coal 74.66, CCGT 84.00, nuclear 66.01 USD/MWh @7% — retr. 2026-07-14. 2020 vintage: pre-dates 2021–24 Chinese capex declines. Converted in section 2.
A32: CN | B32: OCGT | C32: — | P32: GAP | S32: NO source anywhere (incl. EGC 2020 — China submitted no OCGT). Complete gap; a finding.
A33: UK | B33: Nuclear — Hinkley Point C CfD price (NOT an LCOE) | C33: NAO, Sizewell C (HC 33), 20.05.2026, para 2.19 | E33: 128.94 | F33: £/MWh | G33: 2025 prices | H33: contract, 35 yrs from operation | I33: n/a | J33: negotiated price embedding EDF return | K33: n/a | L33: 35 (contract) | M33: £31-35bn build (NAO 2023 range) | N33: in price | O33: in price | P33: N | R33: 170.1 | S33: NAO Sizewell C 2026 p.44: HPC CfD = GBP 128.94/MWh in 2025 prices, on the GBP 89.50 (2012-price) basis — the GBP 3 reduction from 92.50 TRIGGERED at the SZC FID of 22.07.2025 (NAO para 1.14). Contractual indexation: CPI D7BT, base Oct-2011 = 94.5, reset each 1 April on January CPI (LCCC SPA Guidance Feb 2026 v7): 2025/26 season 89.50 x 135.4/94.5 = 128.24; 2026/27 = 132.12. A negotiated PRICE embedding the developer return, not an LCOE (NAO 2017: consumers locked into a risky and expensive project). USD = x1.3192 (2025 avg). S200.
A34: DE | B34: Nuclear — restart of closed fleet | C34: Radiant Energy Group, Restarting Germany’s Reactors: Viability and Outlook, Jun 2026, pp.15-19 | D34: 37 | E34: 71 | F34: EUR/MWh | G34: 2026 prices | H34: 2026 | I34: 4.25% (state) / 7.38% (private) | J34: WACC scenarios II / I | K34: 147 TWh/yr fleet | L34: 20-yr repayment | M34: EUR 1.0-4.8bn/unit; program EUR 39.3bn | N34: industry-expert opex/fuel | O34: EUR 4/MWh waste/decom | P34: Y | Q34: 41.83 | R34: 80.27 | S34: 14 restartable reactors, 18.7 GW, in 3 priority groups; group LCOE means: state-backed (Scen II) A/B EUR 37, C 58; private (Scen I) A 41 / B 42 / C 71; cheapest unit Brokdorf 31-33. Range entered = 37 (Scen II A/B) to 71 (Scen I C). CAVEATS: restart-advocacy-adjacent source, anonymous industry opex sourcing, not peer-reviewed; 35% baseline overrun adder +/-20% is in the numbers. Nearest independent anchor: IEA/NEA EGC 2020 Table 8.1 LTO (lifetime extension) USD 26.4-48.5/MWh, central 31-36 at 7%/85%CF (S200). USD = x1.1306 (2025 avg; 2026 annual FX does not exist yet per D6 — deviation immaterial vs the model’s own overrun band). estimated=Y.
A35: 2. HARMONISED-WACC VARIANT — ALL MODELLED (estimated=Y). Method (decision D15): capital component = capex × CRF(WACC, life) ÷ annual generation per kW; residual = published LCOE − capital component (holds fuel, carbon, O&M); harmonised LCOE = capital at common WACC + residual. Common rate:
A36: Common real WACC (editable input; user-approved 2026-07-14): | D36: 0.07
A37: Ctry | B37: Tech / case | C37: Basis | D37: Capex total (loc/kW) | E37: Gen (MWh/kW·yr) | F37: Life (y) | G37: Native WACC | H37: CRF native | I37: CRF common | J37: Capital native (/MWh) | K37: Published LCOE (loc/MWh) | L37: Residual | M37: Resid. chk | N37: Harmonised (loc/MWh) | O37: est? | P37: Real25 USD/MWh | R37: Notes
A38: UK | B38: CCGT H-class | C38: DESNZ 2023 inputs | D38: 624.42 | E38: 8.1468 | F38: 25 | G38: 0.075 | H38: =G38*(1+G38)^F38/((1+G38)^F38-1) | I38: =$D$36*(1+$D$36)^F38/((1+$D$36)^F38-1) | J38: =D38*H38/E38 | K38: 114 | L38: =K38-J38 | M38: =IF(L38<0,"NEG-flag","ok") | N38: =D38*I38/E38+L38 | O38: Y | P38: =N38*fx_deflator!$B$6*fx_deflator!$F$6 | R38: Capex £610/kW + infra £17.3m/1200MW. Gen = 8.76×93%.
A39: UK | B39: OCGT 300MW 2000h | C39: DESNZ 2023 inputs | D39: 579.78 | E39: 1.9272 | F39: 25 | G39: 0.071 | H39: =G39*(1+G39)^F39/((1+G39)^F39-1) | I39: =$D$36*(1+$D$36)^F39/((1+$D$36)^F39-1) | J39: =D39*H39/E39 | K39: 197 | L39: =K39-J39 | M39: =IF(L39<0,"NEG-flag","ok") | N39: =D39*I39/E39+L39 | O39: Y | P39: =N39*fx_deflator!$B$6*fx_deflator!$F$6 | R39: £530/kW + £15.5m/311.36MW; 8.76×22%.
A40: UK | B40: Onshore wind | C40: DESNZ 2023 inputs | D40: 1304.07 | E40: 3.942 | F40: 25 | G40: 0.052 | H40: =G40*(1+G40)^F40/((1+G40)^F40-1) | I40: =$D$36*(1+$D$36)^F40/((1+$D$36)^F40-1) | J40: =D40*H40/E40 | K40: 38 | L40: =K40-J40 | M40: =IF(L40<0,"NEG-flag","ok") | N40: =D40*I40/E40+L40 | O40: Y | P40: =N40*fx_deflator!$B$6*fx_deflator!$F$6 | R40: £1,230/kW + £3.8m/51.3MW; 8.76×45%.
A41: UK | B41: Offshore wind | C41: DESNZ 2023 inputs | D41: 1694.3 | E41: 5.3436 | F41: 30 | G41: 0.063 | H41: =G41*(1+G41)^F41/((1+G41)^F41-1) | I41: =$D$36*(1+$D$36)^F41/((1+$D$36)^F41-1) | J41: =D41*H41/E41 | K41: 44 | L41: =K41-J41 | M41: =IF(L41<0,"NEG-flag","ok") | N41: =D41*I41/E41+L41 | O41: Y | P41: =N41*fx_deflator!$B$6*fx_deflator!$F$6 | R41: £1,630/kW + £64.3m/1000MW; 8.76×61%.
A42: UK | B42: Solar PV large | C42: DESNZ 2023 inputs | D42: 520 | E42: 0.9636 | F42: 35 | G42: 0.05 | H42: =G42*(1+G42)^F42/((1+G42)^F42-1) | I42: =$D$36*(1+$D$36)^F42/((1+$D$36)^F42-1) | J42: =D42*H42/E42 | K42: 41 | L42: =K42-J42 | M42: =IF(L42<0,"NEG-flag","ok") | N42: =D42*I42/E42+L42 | O42: Y | P42: =N42*fx_deflator!$B$6*fx_deflator!$F$6 | R42: £450/kW + £1.4m/20MW; 8.76×11%.
A43: DE | B43: Lignite — min | C43: ISE 2024 inputs | D43: 1850 | E43: 6.3 | F43: 40 | G43: 0.068 | H43: =G43*(1+G43)^F43/((1+G43)^F43-1) | I43: =$D$36*(1+$D$36)^F43/((1+$D$36)^F43-1) | J43: =D43*H43/E43 | K43: 151 | L43: =K43-J43 | M43: =IF(L43<0,"NEG-flag","ok") | N43: =D43*I43/E43+L43 | O43: Y | P43: =N43*fx_deflator!$C$9*fx_deflator!$F$9 | R43: Band convention: min = low capex + best FLH.
A44: DE | B44: Lignite — max | C44: ISE 2024 inputs | D44: 2550 | E44: 4.3 | F44: 40 | G44: 0.068 | H44: =G44*(1+G44)^F44/((1+G44)^F44-1) | I44: =$D$36*(1+$D$36)^F44/((1+$D$36)^F44-1) | J44: =D44*H44/E44 | K44: 257 | L44: =K44-J44 | M44: =IF(L44<0,"NEG-flag","ok") | N44: =D44*I44/E44+L44 | O44: Y | P44: =N44*fx_deflator!$C$9*fx_deflator!$F$9 | R44: max = high capex + worst FLH.
A45: DE | B45: Hard coal — min | C45: ISE 2024 inputs | D45: 1700 | E45: 5.2 | F45: 30 | G45: 0.068 | H45: =G45*(1+G45)^F45/((1+G45)^F45-1) | I45: =$D$36*(1+$D$36)^F45/((1+$D$36)^F45-1) | J45: =D45*H45/E45 | K45: 173 | L45: =K45-J45 | M45: =IF(L45<0,"NEG-flag","ok") | N45: =D45*I45/E45+L45 | O45: Y | P45: =N45*fx_deflator!$C$9*fx_deflator!$F$9
A46: DE | B46: Hard coal — max | C46: ISE 2024 inputs | D46: 2300 | E46: 3 | F46: 30 | G46: 0.068 | H46: =G46*(1+G46)^F46/((1+G46)^F46-1) | I46: =$D$36*(1+$D$36)^F46/((1+$D$36)^F46-1) | J46: =D46*H46/E46 | K46: 293 | L46: =K46-J46 | M46: =IF(L46<0,"NEG-flag","ok") | N46: =D46*I46/E46+L46 | O46: Y | P46: =N46*fx_deflator!$C$9*fx_deflator!$F$9
A47: DE | B47: CCGT — min | C47: ISE 2024 inputs | D47: 900 | E47: 6.3 | F47: 30 | G47: 0.064 | H47: =G47*(1+G47)^F47/((1+G47)^F47-1) | I47: =$D$36*(1+$D$36)^F47/((1+$D$36)^F47-1) | J47: =D47*H47/E47 | K47: 109 | L47: =K47-J47 | M47: =IF(L47<0,"NEG-flag","ok") | N47: =D47*I47/E47+L47 | O47: Y | P47: =N47*fx_deflator!$C$9*fx_deflator!$F$9
A48: DE | B48: CCGT — max | C48: ISE 2024 inputs | D48: 1300 | E48: 3 | F48: 30 | G48: 0.064 | H48: =G48*(1+G48)^F48/((1+G48)^F48-1) | I48: =$D$36*(1+$D$36)^F48/((1+$D$36)^F48-1) | J48: =D48*H48/E48 | K48: 181 | L48: =K48-J48 | M48: =IF(L48<0,"NEG-flag","ok") | N48: =D48*I48/E48+L48 | O48: Y | P48: =N48*fx_deflator!$C$9*fx_deflator!$F$9
A49: DE | B49: OCGT — min | C49: ISE 2024 inputs | D49: 450 | E49: 3 | F49: 30 | G49: 0.064 | H49: =G49*(1+G49)^F49/((1+G49)^F49-1) | I49: =$D$36*(1+$D$36)^F49/((1+$D$36)^F49-1) | J49: =D49*H49/E49 | K49: 154 | L49: =K49-J49 | M49: =IF(L49<0,"NEG-flag","ok") | N49: =D49*I49/E49+L49 | O49: Y | P49: =N49*fx_deflator!$C$9*fx_deflator!$F$9
A50: DE | B50: OCGT — max | C50: ISE 2024 inputs | D50: 700 | E50: 0.5 | F50: 30 | G50: 0.064 | H50: =G50*(1+G50)^F50/((1+G50)^F50-1) | I50: =$D$36*(1+$D$36)^F50/((1+$D$36)^F50-1) | J50: =D50*H50/E50 | K50: 326 | L50: =K50-J50 | M50: =IF(L50<0,"NEG-flag","ok") | N50: =D50*I50/E50+L50 | O50: Y | P50: =N50*fx_deflator!$C$9*fx_deflator!$F$9
A51: DE | B51: Onshore — min | C51: ISE 2024 inputs | D51: 1300 | E51: 3.2 | F51: 25 | G51: 0.039 | H51: =G51*(1+G51)^F51/((1+G51)^F51-1) | I51: =$D$36*(1+$D$36)^F51/((1+$D$36)^F51-1) | J51: =D51*H51/E51 | K51: 43 | L51: =K51-J51 | M51: =IF(L51<0,"NEG-flag","ok") | N51: =D51*I51/E51+L51 | O51: Y | P51: =N51*fx_deflator!$C$9*fx_deflator!$F$9
A52: DE | B52: Onshore — max | C52: ISE 2024 inputs | D52: 1900 | E52: 1.8 | F52: 25 | G52: 0.039 | H52: =G52*(1+G52)^F52/((1+G52)^F52-1) | I52: =$D$36*(1+$D$36)^F52/((1+$D$36)^F52-1) | J52: =D52*H52/E52 | K52: 92 | L52: =K52-J52 | M52: =IF(L52<0,"NEG-flag","ok") | N52: =D52*I52/E52+L52 | O52: Y | P52: =N52*fx_deflator!$C$9*fx_deflator!$F$9
A53: DE | B53: Offshore — min | C53: ISE 2024 inputs | D53: 2200 | E53: 4.5 | F53: 25 | G53: 0.06 | H53: =G53*(1+G53)^F53/((1+G53)^F53-1) | I53: =$D$36*(1+$D$36)^F53/((1+$D$36)^F53-1) | J53: =D53*H53/E53 | K53: 55 | L53: =K53-J53 | M53: =IF(L53<0,"NEG-flag","ok") | N53: =D53*I53/E53+L53 | O53: Y | P53: =N53*fx_deflator!$C$9*fx_deflator!$F$9
A54: DE | B54: Offshore — max | C54: ISE 2024 inputs | D54: 3400 | E54: 3.2 | F54: 25 | G54: 0.06 | H54: =G54*(1+G54)^F54/((1+G54)^F54-1) | I54: =$D$36*(1+$D$36)^F54/((1+$D$36)^F54-1) | J54: =D54*H54/E54 | K54: 103 | L54: =K54-J54 | M54: =IF(L54<0,"NEG-flag","ok") | N54: =D54*I54/E54+L54 | O54: Y | P54: =N54*fx_deflator!$C$9*fx_deflator!$F$9
A55: DE | B55: Solar PV — min | C55: ISE 2024 inputs | D55: 700 | E55: 1.28 | F55: 30 | G55: 0.035 | H55: =G55*(1+G55)^F55/((1+G55)^F55-1) | I55: =$D$36*(1+$D$36)^F55/((1+$D$36)^F55-1) | J55: =D55*H55/E55 | K55: 41 | L55: =K55-J55 | M55: =IF(L55<0,"NEG-flag","ok") | N55: =D55*I55/E55+L55 | O55: Y | P55: =N55*fx_deflator!$C$9*fx_deflator!$F$9 | R55: Yield 1,280 kWh/kWp (South).
A56: DE | B56: Solar PV — max | C56: ISE 2024 inputs | D56: 900 | E56: 0.935 | F56: 30 | G56: 0.035 | H56: =G56*(1+G56)^F56/((1+G56)^F56-1) | I56: =$D$36*(1+$D$36)^F56/((1+$D$36)^F56-1) | J56: =D56*H56/E56 | K56: 69 | L56: =K56-J56 | M56: =IF(L56<0,"NEG-flag","ok") | N56: =D56*I56/E56+L56 | O56: Y | P56: =N56*fx_deflator!$C$9*fx_deflator!$F$9 | R56: Yield 935 kWh/kWp (North).
A57: DE | B57: Nuclear — min | C57: ISE 2024 inputs | D57: 6000 | E57: 6.3 | F57: 45 | G57: 0.078 | H57: =G57*(1+G57)^F57/((1+G57)^F57-1) | I57: =$D$36*(1+$D$36)^F57/((1+$D$36)^F57-1) | J57: =D57*H57/E57 | K57: 136 | L57: =K57-J57 | M57: =IF(L57<0,"NEG-flag","ok") | N57: =D57*I57/E57+L57 | O57: Y | P57: =N57*fx_deflator!$C$9*fx_deflator!$F$9 | R57: Excl. back-end (source caveat).
A58: DE | B58: Nuclear — max | C58: ISE 2024 inputs | D58: 16000 | E58: 4.3 | F58: 45 | G58: 0.078 | H58: =G58*(1+G58)^F58/((1+G58)^F58-1) | I58: =$D$36*(1+$D$36)^F58/((1+$D$36)^F58-1) | J58: =D58*H58/E58 | K58: 490 | L58: =K58-J58 | M58: =IF(L58<0,"NEG-flag","ok") | N58: =D58*I58/E58+L58 | O58: Y | P58: =N58*fx_deflator!$C$9*fx_deflator!$F$9
A59: CN | B59: Coal | C59: WEO 2025 re-annuitised | D59: 800 | E59: 4.38 | F59: 40 | G59: 0.085 | H59: =G59*(1+G59)^F59/((1+G59)^F59-1) | I59: =$D$36*(1+$D$36)^F59/((1+$D$36)^F59-1) | J59: =D59*H59/E59 | K59: 65 | L59: =K59-J59 | M59: =IF(L59<0,"NEG-flag","ok") | N59: =D59*I59/E59+L59 | O59: Y | P59: =N59*fx_deflator!$F$9 | R59: WACC = mid of WEO 8–9% band (unpublished point — qc Q14); lifetime per EGC convention (qc Q15).
A60: CN | B60: Gas CCGT | C60: WEO 2025 re-annuitised | D60: 560 | E60: 2.628 | F60: 30 | G60: 0.085 | H60: =G60*(1+G60)^F60/((1+G60)^F60-1) | I60: =$D$36*(1+$D$36)^F60/((1+$D$36)^F60-1) | J60: =D60*H60/E60 | K60: 100 | L60: =K60-J60 | M60: =IF(L60<0,"NEG-flag","ok") | N60: =D60*I60/E60+L60 | O60: Y | P60: =N60*fx_deflator!$F$9 | R60: As above.
A61: CN | B61: Nuclear | C61: WEO 2025 re-annuitised | D61: 2800 | E61: 6.57 | F61: 60 | G61: 0.085 | H61: =G61*(1+G61)^F61/((1+G61)^F61-1) | I61: =$D$36*(1+$D$36)^F61/((1+$D$36)^F61-1) | J61: =D61*H61/E61 | K61: 70 | L61: =K61-J61 | M61: =IF(L61<0,"NEG-flag","ok") | N61: =D61*I61/E61+L61 | O61: Y | P61: =N61*fx_deflator!$F$9 | R61: As above.
A62: CN | B62: Solar PV | C62: CREEI re-annuitised | D62: 3450 | E62: 1.2 | F62: 25 | G62: 0.05 | H62: =G62*(1+G62)^F62/((1+G62)^F62-1) | I62: =$D$36*(1+$D$36)^F62/((1+$D$36)^F62-1) | J62: =D62*H62/E62 | K62: 200 | L62: =K62-J62 | M62: =IF(L62<0,"NEG-flag","ok") | N62: =D62*I62/E62+L62 | O62: Y | P62: =N62/fx_deflator!$D$9*fx_deflator!$F$9 | R62: n=25 assumed (qc Q15). Residual ≈ −4 元/MWh (implied opex ~0) — qc Q18.
A63: CN | B63: Onshore wind | C63: CREEI re-annuitised | D63: 4200 | E63: 2 | F63: 25 | G63: 0.05 | H63: =G63*(1+G63)^F63/((1+G63)^F63-1) | I63: =$D$36*(1+$D$36)^F63/((1+$D$36)^F63-1) | J63: =D63*H63/E63 | K63: 180 | L63: =K63-J63 | M63: =IF(L63<0,"NEG-flag","ok") | N63: =D63*I63/E63+L63 | O63: Y | P63: =N63/fx_deflator!$D$9*fx_deflator!$F$9 | R63: n=25 assumed.
A64: CN | B64: Offshore wind | C64: CREEI re-annuitised | D64: 9680 | E64: 2.8 | F64: 25 | G64: 0.05 | H64: =G64*(1+G64)^F64/((1+G64)^F64-1) | I64: =$D$36*(1+$D$36)^F64/((1+$D$36)^F64-1) | J64: =D64*H64/E64 | K64: 290 | L64: =K64-J64 | M64: =IF(L64<0,"NEG-flag","ok") | N64: =D64*I64/E64+L64 | O64: Y | P64: =N64/fx_deflator!$D$9*fx_deflator!$F$9 | R64: Published band 250–330; mid used (flag).
A65: CN | B65: Coal (published @7%) | C65: IEA/NEA EGC 2020 | K65: 74.66 | N65: =K65 | O65: N | P65: =N65*fx_deflator!$F$21 | R65: PUBLISHED harmonised @7% real, 2018 USD (Tbl 3.12) — no model; cross-check for WEO re-annuitised row. 2020 vintage flagged.
A66: CN | B66: Gas CCGT (published @7%) | C66: IEA/NEA EGC 2020 | K66: 84 | N66: =K66 | O66: N | P66: =N66*fx_deflator!$F$21 | R66: Tbl 3.11a. As above.
A67: CN | B67: Nuclear (published @7%) | C67: IEA/NEA EGC 2020 | K67: 66.01 | N67: =K67 | O67: N | P67: =N67*fx_deflator!$F$21 | R67: Tbl 3.13a. As above.
A69: Chart footnote (house rule 1): "Real 2025 USD/MWh. Converted at annual-average market FX. Excludes VAT." All section-2 values modelled (estimated=Y); label as such on every chart.

Sheet cn_td
A1: CHINA T&D PRICES (输配电价) — 工商业 两部制, seven basket provinces. 3rd period (526号, eff. 01.06.2023) and 4th period (1077号, eff. 01.08.2026). Retrieved 2026-07-14 from primary NDRC annex PDFs.
A2: Native units: 电量电价 元/千瓦时; 需量电价 元/千瓦·月; 容量电价 元/千伏安·月. Prices incl. VAT & base-period cross-subsidy; excl. 政府性基金及附加, line loss (per-province 上网环节线损率 noted), system operation fees. Calendar-2026 series = 7/12 × 3rd + 5/12 × 4th (D13-R).
A4: Province | B4: P3 220kV 电量 | C4: P3 220kV 需量 | D4: P4 220kV 电量 | E4: P4 220kV 需量 | F4: P3 10kV 电量 | G4: P4 10kV 电量 | H4: Notes (P3/P4 capacity variants; line-loss rates; source pages)
A5: Jiangsu 江苏 | B5: 0.0597 | C5: 41.6 | D5: 0.0518 | E5: 41.6 | F5: 0.1357 | G5: 0.1298 | H5: 容量: P3/P4 26.0 (220kV), 32.0 (10kV). 需量 10kV: 51.2/51.2. 线损率: P3 3.18% → P4 省内 2.83%. P4 annex p.12.
A6: Guangdong 广东 | B6: 0.0457 | C6: 26.1 | D6: 0.0449 | E6: 26.1 | F6: 0.0985 | G6: 0.0979 | H6: P4: 35~110kV merged class; 容量 16.3 (220kV), 22.6 (10kV); 需量 10kV 36.1; 省内线损率 3.31%; ex-Shenzhen average; annex p.21. P3 extracted 2026-07-15 (annex pp. per page index).
A7: Shandong 山东 | B7: 0.1041 | C7: 32 | D7: 0.089 | E7: 32 | F7: 0.1491 | G7: 0.14 | H7: P4: 容量 20.0/25.0; 需量 10kV 40.0; 线损率 3.07%; annex p.17. P3 extracted 2026-07-15.
A8: Zhejiang 浙江 | B8: 0.0688 | C8: 38.3 | D8: 0.0663 | E8: 37.6 | F8: 0.126 | G8: 0.125 | H8: P4: 容量 23.5/29.5; 需量 10kV 47.2; annex p.13. P3 extracted 2026-07-15.
A9: Henan 河南 | B9: 0.103 | C9: 30.5 | D9: 0.098 | E9: 30.4 | F9: 0.168 | G9: 0.1655 | H9: P4: 容量 19.0/25.0; 需量 10kV 40.0; 省内线损率 4.82%; annex p.18. P3 extracted 2026-07-15.
A10: Inner Mongolia 蒙西 | B10: 0.0455 | C10: 31.2 | D10: 0.0429 | E10: 31.2 | F10: 0.0795 | G10: 0.0787 | H10: P4: 容量 19.5/21.5; 需量 10kV 34.4; 线损率 2.81%; uniquely has <1kV two-part class; annex p.7. Basket uses 蒙西 (west grid) — 蒙东 not extracted (decision-log if needed). P3 extracted 2026-07-15.
A11: Sichuan 四川 | B11: 0.0478 | C11: 24 | D11: 0.0466 | E11: 24 | F11: 0.139 | G11: 0.1391 | H11: P4: 容量 15.0/22.0; 需量 10kV 35.0; 省内线损率 5.64%; extensive hydro-export notes; annex p.26. P3 extracted 2026-07-15.
A13: Sources: 发改价格〔2023〕526号 annex (P020230515609052875117.pdf); 发改价格〔2026〕1077号 annex 1 (P020260710613207914509.pdf) — both ndrc.gov.cn, retrieved 2026-07-14. P4 structural changes: new 单一制 110/220kV classes; standardised 0.03 元/kWh inter-provincial mutual-aid export price; pumped-storage/gas capacity-fee notes removed from tables (系统运行费 definition sits in 发改价格规〔2025〕1490号 — not yet retrieved, qc).
A14: P3 values for GD/SD/ZJ/HN/蒙西/SC extracted 2026-07-15 from 526号 annex PDF (in-session re-download, pdfplumber): 两部制 rows, pages 蒙西 p.7, 浙江 p.13, 山东 p.17, 河南 p.18, 广东 p.21, 四川 p.26 (0-indexed). Cross-checks: SD 10kV 0.1491 = SD Oct-2025 bill 输配 0.1491 ✓; HN 10kV 0.1680 = HN May-2025 bill 输配 0.168 ✓. P3 10kV 需量 in stage4_cn.

Sheet timeseries
A1: ALL-IN PRICE TIME SERIES — stage 4 build (2026-07-15). Both archetypes × E1/E2 × 3 countries, 2010–2026 (D19). Formula-driven from stage4_uk / stage4_de / stage4_cn / cn_td / assumptions. Nominal local currency per MWh; real 2025 USD/MWh block below (no 2026 conversion, D6). E1/E2 are MODELLED, not observed. Build-up EXCLUDES supply cost & margin (function 6) — noted at the validation gate. Blank cell = source gap (anti-fabrication) — see completeness rows.
A2: Structural breaks to mark on every chart — UK: CfD-ILR 2016 · EII exemptions 2018 → 100% 04/2024 · TCR DUoS 04/2022, TNUoS bands + BSUoS reform 04/2023 · NCC 04/2025 (backdated 04/2024), 90% 04/2026 · wholesale = day-ahead PROXY pre-2022 (D22). DE: §19 floors 2014 (2011–13 exemption era not modelled — gap) · Offshore/SPK 2013 · BesAR-2014 redesign · KWKG/Offshore privileged rates company-specific 2017/2019 (E2=E1, D25) · DE-AT split 10/2018 · EEG→0 07/2022, budget 2023 · ÜNB harmonisation 2023 · €6.5bn subsidy 2026 (incidence iii). CN: renormalised basket, coverage row shown (D23) · 2021-10 catalogue end (2021 = Jan–Sep basis) · 代理购电 12/2021 · 526号 06/2023 · 容量电价 2024 · 136号文 06/2025 · 1077号 08/2026 (month-weighted, D13-R). CN E1=E2 (no formal exemption regime — functional equivalents owned in text).
A4: Ctry | B4: Series / component | C4: Case | D4: 2010 | E4: 2011 | F4: 2012 | G4: 2013 | H4: 2014 | I4: 2015 | J4: 2016 | K4: 2017 | L4: 2018 | M4: 2019 | N4: 2020 | O4: 2021 | P4: 2022 | Q4: 2023 | R4: 2024 | S4: 2025 | T4: 2026 | U4: Method / source note
A5: UK — LARGE archetype (500 GWh, 8,000h, transmission-connected, Humber zone 5). Nominal £/MWh.
A6: UK | B6: Wholesale (rolling year-ahead; day-ahead PROXY ≤2021, D22) | C6: E1+E2 | D6: =stage4_uk!D9 | E6: =stage4_uk!E9 | F6: =stage4_uk!F9 | G6: =stage4_uk!G9 | H6: =stage4_uk!H9 | I6: =stage4_uk!I9 | J6: =stage4_uk!J9 | K6: =stage4_uk!K9 | ... T6: =stage4_uk!T9 | U6: stage4_uk. estimated=Y (annualised); 2010 DA Jun–Dec; 2026 partial obs-yr.
A7: UK | B7: TNUoS (triad-era £/kW × 1000/h; TCR residual T-Demand4 ×365/MWh from 2023) | C7: per arch. | D7: =stage4_uk!D25*1000/assumptions!$B$7 | E7: =stage4_uk!E25*1000/assumptions!$B$7 | F7: =stage4_uk!F25*1000/assumptions!$B$7 | G7: =stage4_uk!G25*1000/assumptions!$B$7 | H7: =stage4_uk!H25*1000/assumptions!$B$7 | I7: =stage4_uk!I25*1000/assumptions!$B$7 | J7: =stage4_uk!J25*1000/assumptions!$B$7 | K7: =stage4_uk!K25*1000/assumptions!$B$7 | ... P7: =stage4_uk!P25*1000/assumptions!$B$7 | Q7: =stage4_uk!Q26*365/assumptions!$B$6 | R7: =stage4_uk!R26*365/assumptions!$B$6 | S7: =stage4_uk!S26*365/assumptions!$B$6 | T7: =stage4_uk!T26*365/assumptions!$B$6 | U7: Flat-baseload: triad demand = avg demand (est=Y). Zone-5 locational zero-floored throughout.
A8: UK | B8: BSUoS (outturn unweighted avg 2010–22, own comp. from NESO HH RF; FT primary-verified 2023+) | C8: E1+E2 | D8: =stage4_uk!D30 | E8: =stage4_uk!E30 | F8: =stage4_uk!F30 | G8: =stage4_uk!G30 | H8: =stage4_uk!H30 | I8: =stage4_uk!I30 | J8: =stage4_uk!J30 | K8: =stage4_uk!K30 | ... T8: =stage4_uk!T30 | U8: Demand-only from 04/2023 (CMP308/361).
A9: UK | B9: AAHEDC (2010/11–2020/21 from NG final tariff letters; Shetland step 2021/22 flagged) | C9: E1+E2 | D9: =stage4_uk!D31*10 | E9: =stage4_uk!E31*10 | F9: =stage4_uk!F31*10 | G9: =stage4_uk!G31*10 | H9: =stage4_uk!H31*10 | I9: =stage4_uk!I31*10 | J9: =stage4_uk!J31*10 | K9: =stage4_uk!K31*10 | ... T9: =stage4_uk!T31*10 | U9: p/kWh × 10. Excluded from NCC base (unverified — conservative).
A10: UK | B10: RO (buy-out × obligation) | C10: E1 | D10: =stage4_uk!D14 | E10: =stage4_uk!E14 | F10: =stage4_uk!F14 | G10: =stage4_uk!G14 | H10: =stage4_uk!H14 | I10: =stage4_uk!I14 | J10: =stage4_uk!J14 | K10: =stage4_uk!K14 | ... T10: =stage4_uk!T14 | U10: estimated=Y (ignores recycle value).
A11: UK | B11: CfD ILR annual avg (scheme from 2016; 2015/16 GAP) | C11: E1 | J11: =stage4_uk!J19 | K11: =stage4_uk!K19 | L11: =stage4_uk!L19 | M11: =stage4_uk!M19 | N11: =stage4_uk!N19 | O11: =stage4_uk!O19 | P11: =stage4_uk!P19 | Q11: =stage4_uk!Q19 | ... T11: =stage4_uk!T19
A12: UK | B12: FiT levelisation (2010–14 D27 est.; SY16/2025 unpublished — blank) | C12: E1 | D12: =stage4_uk!D20 | E12: =stage4_uk!E20 | F12: =stage4_uk!F20 | G12: =stage4_uk!G20 | H12: =stage4_uk!H20 | I12: =stage4_uk!I20 | J12: =stage4_uk!J20 | K12: =stage4_uk!K20 | ... R12: =stage4_uk!R20 | U12: Ofgem levelisation notices located.
A13: UK | B13: Capacity Market (derived per-MWh, D30; 2023 pre-final; scheme from 2016/17) | C13: E1 | K13: =stage4_uk!K21 | L13: =stage4_uk!L21 | M13: =stage4_uk!M21 | N13: =stage4_uk!N21 | O13: =stage4_uk!O21 | P13: =stage4_uk!P21 | Q13: =stage4_uk!Q21 | R13: =stage4_uk!R21 | ... T13: =stage4_uk!T21 | U13: EMRS Key Payment Figures located. Suspension 11/2018–10/2019.
A14: UK | B14: CCL (main rate) — E1 only. E2 carries ZERO (min/met exemption, D71). Band-average CCL actually paid is measured in r132/r133, not assumed. | C14: E1+E2 | D14: =stage4_uk!D22*10 | E14: =stage4_uk!E22*10 | F14: =stage4_uk!F22*10 | G14: =stage4_uk!G22*10 | H14: =stage4_uk!H22*10 | I14: =stage4_uk!I22*10 | J14: =stage4_uk!J22*10 | K14: =stage4_uk!K22*10 | ... T14: =stage4_uk!T22*10
A15: UK | B15: E1 TOTAL (statutory, excl supply margin; incl ESL 2025+ via stage4_uk r53; completeness row below) | C15: E1 | D15: =SUM(D6:D14)+IF(ISNUMBER(stage4_uk!D53),stage4_uk!D53,0)+IF(ISNUMBER(D107),D107,0) | E15: =SUM(E6:E14)+IF(ISNUMBER(stage4_uk!E53),stage4_uk!E53,0)+IF(ISNUMBER(E107),E107,0) | F15: =SUM(F6:F14)+IF(ISNUMBER(stage4_uk!F53),stage4_uk!F53,0)+IF(ISNUMBER(F107),F107,0) | G15: =SUM(G6:G14)+IF(ISNUMBER(stage4_uk!G53),stage4_uk!G53,0)+IF(ISNUMBER(G107),G107,0) | H15: =SUM(H6:H14)+IF(ISNUMBER(stage4_uk!H53),stage4_uk!H53,0)+IF(ISNUMBER(H107),H107,0) | I15: =SUM(I6:I14)+IF(ISNUMBER(stage4_uk!I53),stage4_uk!I53,0)+IF(ISNUMBER(I107),I107,0) | J15: =SUM(J6:J14)+IF(ISNUMBER(stage4_uk!J53),stage4_uk!J53,0)+IF(ISNUMBER(J107),J107,0) | K15: =SUM(K6:K14)+IF(ISNUMBER(stage4_uk!K53),stage4_uk!K53,0)+IF(ISNUMBER(K107),K107,0) | ... T15: =SUM(T6:T14)+IF(ISNUMBER(stage4_uk!T53),stage4_uk!T53,0)+IF(ISNUMBER(T107),T107,0) | U15: MODELLED.
A16: UK | B16: E1/E2 completeness (missing retrieved components) | C16: note | D16: complete (FiT D27 est.; DUoS recon. D28 [medium]; CM n/a) | E16: complete (FiT D27 est.; DUoS recon.; CM n/a) | F16: complete (FiT D27 est.; DUoS retrieved; CM n/a) | G16: complete (FiT D27 est.; DUoS recon.; CM n/a) | H16: complete (FiT D27 est.; DUoS recon.; CM n/a) | I16: complete (CM n/a) | J16: complete (CM n/a) | K16: complete (CM TA est.) | L16: complete | M16: complete | N16: complete | O16: complete | P16: complete | Q16: complete (CM pre-final total — final unpublished) | R16: complete | S16: excl FiT 2025/26 (unpublished ~7 £/MWh); ESL est. | T16: excl FiT; CM in-year; ESL est.; wholesale part-yr | U16: Understates totals where components missing — gate provisional pre-2024.
A17: UK | B17: E2 network = (TNUoS+BSUoS)×(1−NCC share) + AAHEDC | C17: E2 | D17: =(D7+SUM(D8))*(1-IF(ISNUMBER(stage4_uk!D48),stage4_uk!D48,0))+SUM(D9) | E17: =(E7+SUM(E8))*(1-IF(ISNUMBER(stage4_uk!E48),stage4_uk!E48,0))+SUM(E9) | F17: =(F7+SUM(F8))*(1-IF(ISNUMBER(stage4_uk!F48),stage4_uk!F48,0))+SUM(F9) | G17: =(G7+SUM(G8))*(1-IF(ISNUMBER(stage4_uk!G48),stage4_uk!G48,0))+SUM(G9) | H17: =(H7+SUM(H8))*(1-IF(ISNUMBER(stage4_uk!H48),stage4_uk!H48,0))+SUM(H9) | I17: =(I7+SUM(I8))*(1-IF(ISNUMBER(stage4_uk!I48),stage4_uk!I48,0))+SUM(I9) | J17: =(J7+SUM(J8))*(1-IF(ISNUMBER(stage4_uk!J48),stage4_uk!J48,0))+SUM(J9) | K17: =(K7+SUM(K8))*(1-IF(ISNUMBER(stage4_uk!K48),stage4_uk!K48,0))+SUM(K9) | ... T17: =(T7+SUM(T8))*(1-IF(ISNUMBER(stage4_uk!T48),stage4_uk!T48,0))+SUM(T9) | U17: NCC 60% 2024–25, 90% 2026 (SI 2026/243); recovered via ESL — incidence (ii).
A18: UK | B18: E2 levies = RO/CfD/FiT/CM after exemption shares (FiT+CM now live) | C18: E2 | D18: =SUM(D10)*(1-IF(ISNUMBER(stage4_uk!D45),stage4_uk!D45,0))+SUM(D11)*(1-IF(ISNUMBER(stage4_uk!D44),stage4_uk!D44,0))+SUM(D12)*(1-IF(ISNUMBER(stage4_uk!D46),stage4_uk!D46,0))+SUM(D13)*(1-IF(ISNUMBER(stage4_uk!D47),stage4_uk!D47,0)) | E18: =SUM(E10)*(1-IF(ISNUMBER(stage4_uk!E45),stage4_uk!E45,0))+SUM(E11)*(1-IF(ISNUMBER(stage4_uk!E44),stage4_uk!E44,0))+SUM(E12)*(1-IF(ISNUMBER(stage4_uk!E46),stage4_uk!E46,0))+SUM(E13)*(1-IF(ISNUMBER(stage4_uk!E47),stage4_uk!E47,0)) | F18: =SUM(F10)*(1-IF(ISNUMBER(stage4_uk!F45),stage4_uk!F45,0))+SUM(F11)*(1-IF(ISNUMBER(stage4_uk!F44),stage4_uk!F44,0))+SUM(F12)*(1-IF(ISNUMBER(stage4_uk!F46),stage4_uk!F46,0))+SUM(F13)*(1-IF(ISNUMBER(stage4_uk!F47),stage4_uk!F47,0)) | G18: =SUM(G10)*(1-IF(ISNUMBER(stage4_uk!G45),stage4_uk!G45,0))+SUM(G11)*(1-IF(ISNUMBER(stage4_uk!G44),stage4_uk!G44,0))+SUM(G12)*(1-IF(ISNUMBER(stage4_uk!G46),stage4_uk!G46,0))+SUM(G13)*(1-IF(ISNUMBER(stage4_uk!G47),stage4_uk!G47,0)) | H18: =SUM(H10)*(1-IF(ISNUMBER(stage4_uk!H45),stage4_uk!H45,0))+SUM(H11)*(1-IF(ISNUMBER(stage4_uk!H44),stage4_uk!H44,0))+SUM(H12)*(1-IF(ISNUMBER(stage4_uk!H46),stage4_uk!H46,0))+SUM(H13)*(1-IF(ISNUMBER(stage4_uk!H47),stage4_uk!H47,0)) | I18: =SUM(I10)*(1-IF(ISNUMBER(stage4_uk!I45),stage4_uk!I45,0))+SUM(I11)*(1-IF(ISNUMBER(stage4_uk!I44),stage4_uk!I44,0))+SUM(I12)*(1-IF(ISNUMBER(stage4_uk!I46),stage4_uk!I46,0))+SUM(I13)*(1-IF(ISNUMBER(stage4_uk!I47),stage4_uk!I47,0)) | J18: =SUM(J10)*(1-IF(ISNUMBER(stage4_uk!J45),stage4_uk!J45,0))+SUM(J11)*(1-IF(ISNUMBER(stage4_uk!J44),stage4_uk!J44,0))+SUM(J12)*(1-IF(ISNUMBER(stage4_uk!J46),stage4_uk!J46,0))+SUM(J13)*(1-IF(ISNUMBER(stage4_uk!J47),stage4_uk!J47,0)) | K18: =SUM(K10)*(1-IF(ISNUMBER(stage4_uk!K45),stage4_uk!K45,0))+SUM(K11)*(1-IF(ISNUMBER(stage4_uk!K44),stage4_uk!K44,0))+SUM(K12)*(1-IF(ISNUMBER(stage4_uk!K46),stage4_uk!K46,0))+SUM(K13)*(1-IF(ISNUMBER(stage4_uk!K47),stage4_uk!K47,0)) | ... T18: =SUM(T10)*(1-IF(ISNUMBER(stage4_uk!T45),stage4_uk!T45,0))+SUM(T11)*(1-IF(ISNUMBER(stage4_uk!T44),stage4_uk!T44,0))+SUM(T12)*(1-IF(ISNUMBER(stage4_uk!T46),stage4_uk!T46,0))+SUM(T13)*(1-IF(ISNUMBER(stage4_uk!T47),stage4_uk!T47,0)) | U18: 85% era 2016/2018 → 100% 04/2024. FiT/CM terms absent (series GAP).
A19: UK | B19: E2 TOTAL (relieved EII; assumes full qualification) — CCL = 0 from D71 2026-07-26: mineralogical and metallurgical processes are EXEMPT from the CCL main rates (HMRC Notice CCL1/3 s3.14 + Annex A, from 01.04.2014), which covers the steel / aluminium / cement archetypes. A non-min/met EII (e.g. paper) would instead pay 8% of the main rate under a CCA — flagged, not modelled. | C19: E2 | D19: =D6+D17+D18+IF(ISNUMBER(D108),D108,0) | E19: =E6+E17+E18+IF(ISNUMBER(E108),E108,0) | F19: =F6+F17+F18+IF(ISNUMBER(F108),F108,0) | G19: =G6+G17+G18+IF(ISNUMBER(G108),G108,0) | H19: =H6+H17+H18+IF(ISNUMBER(H108),H108,0) | I19: =I6+I17+I18+IF(ISNUMBER(I108),I108,0) | J19: =J6+J17+J18+IF(ISNUMBER(J108),J108,0) | K19: =K6+K17+K18+IF(ISNUMBER(K108),K108,0) | ... T19: =T6+T17+T18+IF(ISNUMBER(T108),T108,0) | U19: MODELLED. Same completeness caveats as E1.
A20: UK | B20: OBSERVED: QEP Extra Large band, INCL CCL (D71; validation only) | C20: obs | D20: =stage4_uk!D51*10 | E20: =stage4_uk!E51*10 | F20: =stage4_uk!F51*10 | G20: =stage4_uk!G51*10 | H20: =stage4_uk!H51*10 | I20: =stage4_uk!I51*10 | J20: =stage4_uk!J51*10 | K20: =stage4_uk!K51*10 | ... S20: =stage4_uk!S51*10 | U20: DESNZ QEP 3.4.1 annual. Fully delivered incl margin, EXCL CCL.
A21: UK — MEDIUM archetype (20 GWh, 5,000h, HV distribution, NPg Yorkshire). Nominal £/MWh.
A22: UK | B22: Wholesale (as large) | C22: E1+E2 | D22: =stage4_uk!D9 | E22: =stage4_uk!E9 | F22: =stage4_uk!F9 | G22: =stage4_uk!G9 | H22: =stage4_uk!H9 | I22: =stage4_uk!I9 | J22: =stage4_uk!J9 | K22: =stage4_uk!K9 | ... T22: =stage4_uk!T9
A23: UK | B23: TNUoS medium (triad-era £/kW ×1000/h; HV4 residual ×365/MWh from 2023) | C23: per arch. | D23: =stage4_uk!D25*1000/assumptions!$C$7 | E23: =stage4_uk!E25*1000/assumptions!$C$7 | F23: =stage4_uk!F25*1000/assumptions!$C$7 | G23: =stage4_uk!G25*1000/assumptions!$C$7 | H23: =stage4_uk!H25*1000/assumptions!$C$7 | I23: =stage4_uk!I25*1000/assumptions!$C$7 | J23: =stage4_uk!J25*1000/assumptions!$C$7 | K23: =stage4_uk!K25*1000/assumptions!$C$7 | ... P23: =stage4_uk!P25*1000/assumptions!$C$7 | Q23: =stage4_uk!Q27*365/assumptions!$C$6 | R23: =stage4_uk!R27*365/assumptions!$C$6 | S23: =stage4_uk!S27*365/assumptions!$C$6 | T23: =stage4_uk!T27*365/assumptions!$C$6 | U23: Triad demand = avg operating demand 4 MW (est=Y — a 5,000h plant is assumed operating at triads; qc). HV4 band inferred (D12).
A24: UK | B24: DUoS unit rates (red/amber/green × band-hour shares; uniform-operation weighting, est=Y) | C24: medium | D24: =IF(ISNUMBER(stage4_uk!D34),(stage4_uk!D34*stage4_uk!$D$41+stage4_uk!D35*stage4_uk!$E$41+stage4_uk!D36*stage4_uk!$F$41)*10,"") | E24: =IF(ISNUMBER(stage4_uk!E34),(stage4_uk!E34*stage4_uk!$D$41+stage4_uk!E35*stage4_uk!$E$41+stage4_uk!E36*stage4_uk!$F$41)*10,"") | F24: =IF(ISNUMBER(stage4_uk!F34),(stage4_uk!F34*stage4_uk!$D$41+stage4_uk!F35*stage4_uk!$E$41+stage4_uk!F36*stage4_uk!$F$41)*10,"") | G24: =IF(ISNUMBER(stage4_uk!G34),(stage4_uk!G34*stage4_uk!$D$41+stage4_uk!G35*stage4_uk!$E$41+stage4_uk!G36*stage4_uk!$F$41)*10,"") | H24: =IF(ISNUMBER(stage4_uk!H34),(stage4_uk!H34*stage4_uk!$D$41+stage4_uk!H35*stage4_uk!$E$41+stage4_uk!H36*stage4_uk!$F$41)*10,"") | I24: =IF(ISNUMBER(stage4_uk!I34),(stage4_uk!I34*stage4_uk!$D$41+stage4_uk!I35*stage4_uk!$E$41+stage4_uk!I36*stage4_uk!$F$41)*10,"") | J24: =IF(ISNUMBER(stage4_uk!J34),(stage4_uk!J34*stage4_uk!$D$41+stage4_uk!J35*stage4_uk!$E$41+stage4_uk!J36*stage4_uk!$F$41)*10,"") | K24: =IF(ISNUMBER(stage4_uk!K34),(stage4_uk!K34*stage4_uk!$D$41+stage4_uk!K35*stage4_uk!$E$41+stage4_uk!K36*stage4_uk!$F$41)*10,"") | ... T24: =IF(ISNUMBER(stage4_uk!T34),(stage4_uk!T34*stage4_uk!$D$41+stage4_uk!T35*stage4_uk!$E$41+stage4_uk!T36*stage4_uk!$F$41)*10,"") | U24: 2017/18 band definitions differ (flag). GAP 2010–16.
A25: UK | B25: DUoS fixed (p/MPAN/day; TCR Band-4 residual from 2022) | C25: medium | D25: =IF(ISNUMBER(stage4_uk!D37),stage4_uk!D37*365/100/assumptions!$C$6,"") | E25: =IF(ISNUMBER(stage4_uk!E37),stage4_uk!E37*365/100/assumptions!$C$6,"") | F25: =IF(ISNUMBER(stage4_uk!F37),stage4_uk!F37*365/100/assumptions!$C$6,"") | G25: =IF(ISNUMBER(stage4_uk!G37),stage4_uk!G37*365/100/assumptions!$C$6,"") | H25: =IF(ISNUMBER(stage4_uk!H37),stage4_uk!H37*365/100/assumptions!$C$6,"") | I25: =IF(ISNUMBER(stage4_uk!I37),stage4_uk!I37*365/100/assumptions!$C$6,"") | J25: =IF(ISNUMBER(stage4_uk!J37),stage4_uk!J37*365/100/assumptions!$C$6,"") | K25: =IF(ISNUMBER(stage4_uk!K37),stage4_uk!K37*365/100/assumptions!$C$6,"") | ... T25: =IF(ISNUMBER(stage4_uk!T37),stage4_uk!T37*365/100/assumptions!$C$6,"")
A26: UK | B26: DUoS capacity (p/kVA/day × agreed kVA; kVA = avg MW × 1000, pf≈1 est=Y) | C26: medium | D26: =IF(ISNUMBER(stage4_uk!D38),stage4_uk!D38*assumptions!$C$8*1000*365/100/assumptions!$C$6,"") | E26: =IF(ISNUMBER(stage4_uk!E38),stage4_uk!E38*assumptions!$C$8*1000*365/100/assumptions!$C$6,"") | F26: =IF(ISNUMBER(stage4_uk!F38),stage4_uk!F38*assumptions!$C$8*1000*365/100/assumptions!$C$6,"") | G26: =IF(ISNUMBER(stage4_uk!G38),stage4_uk!G38*assumptions!$C$8*1000*365/100/assumptions!$C$6,"") | H26: =IF(ISNUMBER(stage4_uk!H38),stage4_uk!H38*assumptions!$C$8*1000*365/100/assumptions!$C$6,"") | I26: =IF(ISNUMBER(stage4_uk!I38),stage4_uk!I38*assumptions!$C$8*1000*365/100/assumptions!$C$6,"") | J26: =IF(ISNUMBER(stage4_uk!J38),stage4_uk!J38*assumptions!$C$8*1000*365/100/assumptions!$C$6,"") | K26: =IF(ISNUMBER(stage4_uk!K38),stage4_uk!K38*assumptions!$C$8*1000*365/100/assumptions!$C$6,"") | ... T26: =IF(ISNUMBER(stage4_uk!T38),stage4_uk!T38*assumptions!$C$8*1000*365/100/assumptions!$C$6,"") | U26: Reactive not modelled (pf≈1).
A27: UK | B27: BSUoS / AAHEDC / RO / CfD / FiT / CM / CCL / ESL (as large) | C27: E1 | D27: =SUM(D8)+SUM(D9)+D10+SUM(D11)+SUM(D12)+SUM(D13)+D14+IF(ISNUMBER(stage4_uk!D53),stage4_uk!D53,0) | E27: =SUM(E8)+SUM(E9)+E10+SUM(E11)+SUM(E12)+SUM(E13)+E14+IF(ISNUMBER(stage4_uk!E53),stage4_uk!E53,0) | F27: =SUM(F8)+SUM(F9)+F10+SUM(F11)+SUM(F12)+SUM(F13)+F14+IF(ISNUMBER(stage4_uk!F53),stage4_uk!F53,0) | G27: =SUM(G8)+SUM(G9)+G10+SUM(G11)+SUM(G12)+SUM(G13)+G14+IF(ISNUMBER(stage4_uk!G53),stage4_uk!G53,0) | H27: =SUM(H8)+SUM(H9)+H10+SUM(H11)+SUM(H12)+SUM(H13)+H14+IF(ISNUMBER(stage4_uk!H53),stage4_uk!H53,0) | I27: =SUM(I8)+SUM(I9)+I10+SUM(I11)+SUM(I12)+SUM(I13)+I14+IF(ISNUMBER(stage4_uk!I53),stage4_uk!I53,0) | J27: =SUM(J8)+SUM(J9)+J10+SUM(J11)+SUM(J12)+SUM(J13)+J14+IF(ISNUMBER(stage4_uk!J53),stage4_uk!J53,0) | K27: =SUM(K8)+SUM(K9)+K10+SUM(K11)+SUM(K12)+SUM(K13)+K14+IF(ISNUMBER(stage4_uk!K53),stage4_uk!K53,0) | ... T27: =SUM(T8)+SUM(T9)+T10+SUM(T11)+SUM(T12)+SUM(T13)+T14+IF(ISNUMBER(stage4_uk!T53),stage4_uk!T53,0) | U27: Volumetric charges identical per MWh.
A28: UK | B28: E1 TOTAL medium (2010–16 DUoS reconstructed, D28) | C28: E1 | D28: =IF(ISNUMBER(D24),D22+D23+D24+D25+D26+D27+IF(ISNUMBER(D109),D109,0),"") | E28: =IF(ISNUMBER(E24),E22+E23+E24+E25+E26+E27+IF(ISNUMBER(E109),E109,0),"") | F28: =IF(ISNUMBER(F24),F22+F23+F24+F25+F26+F27+IF(ISNUMBER(F109),F109,0),"") | G28: =IF(ISNUMBER(G24),G22+G23+G24+G25+G26+G27+IF(ISNUMBER(G109),G109,0),"") | H28: =IF(ISNUMBER(H24),H22+H23+H24+H25+H26+H27+IF(ISNUMBER(H109),H109,0),"") | I28: =IF(ISNUMBER(I24),I22+I23+I24+I25+I26+I27+IF(ISNUMBER(I109),I109,0),"") | J28: =IF(ISNUMBER(J24),J22+J23+J24+J25+J26+J27+IF(ISNUMBER(J109),J109,0),"") | K28: =IF(ISNUMBER(K24),K22+K23+K24+K25+K26+K27+IF(ISNUMBER(K109),K109,0),"") | ... T28: =IF(ISNUMBER(T24),T22+T23+T24+T25+T26+T27+IF(ISNUMBER(T109),T109,0),"") | U28: MODELLED. Same FiT/CM/BSUoS completeness caveats.
A29: UK | B29: E2 TOTAL medium (EII status assumed, D24) — CCL = 0 per D71 (min/met exemption; see r19 note). | C29: E2 | D29: =IF(ISNUMBER(D24),D22+(D23+D24+D25+D26+SUM(D8))*(1-IF(ISNUMBER(stage4_uk!D48),stage4_uk!D48,0))+SUM(D9)+D10*(1-IF(ISNUMBER(stage4_uk!D45),stage4_uk!D45,0))+SUM(D11)*(1-IF(ISNUMBER(stage4_uk!D44),stage4_uk!D44,0))+SUM(D12)*(1-IF(ISNUMBER(stage4_uk!D46),stage4_uk!D46,0))+SUM(D13)*(1-IF(ISNUMBER(stage4_uk!D47),stage4_uk!D47,0))+IF(ISNUMBER(D110),D110,0),"") | E29: =IF(ISNUMBER(E24),E22+(E23+E24+E25+E26+SUM(E8))*(1-IF(ISNUMBER(stage4_uk!E48),stage4_uk!E48,0))+SUM(E9)+E10*(1-IF(ISNUMBER(stage4_uk!E45),stage4_uk!E45,0))+SUM(E11)*(1-IF(ISNUMBER(stage4_uk!E44),stage4_uk!E44,0))+SUM(E12)*(1-IF(ISNUMBER(stage4_uk!E46),stage4_uk!E46,0))+SUM(E13)*(1-IF(ISNUMBER(stage4_uk!E47),stage4_uk!E47,0))+IF(ISNUMBER(E110),E110,0),"") | F29: =IF(ISNUMBER(F24),F22+(F23+F24+F25+F26+SUM(F8))*(1-IF(ISNUMBER(stage4_uk!F48),stage4_uk!F48,0))+SUM(F9)+F10*(1-IF(ISNUMBER(stage4_uk!F45),stage4_uk!F45,0))+SUM(F11)*(1-IF(ISNUMBER(stage4_uk!F44),stage4_uk!F44,0))+SUM(F12)*(1-IF(ISNUMBER(stage4_uk!F46),stage4_uk!F46,0))+SUM(F13)*(1-IF(ISNUMBER(stage4_uk!F47),stage4_uk!F47,0))+IF(ISNUMBER(F110),F110,0),"") | G29: =IF(ISNUMBER(G24),G22+(G23+G24+G25+G26+SUM(G8))*(1-IF(ISNUMBER(stage4_uk!G48),stage4_uk!G48,0))+SUM(G9)+G10*(1-IF(ISNUMBER(stage4_uk!G45),stage4_uk!G45,0))+SUM(G11)*(1-IF(ISNUMBER(stage4_uk!G44),stage4_uk!G44,0))+SUM(G12)*(1-IF(ISNUMBER(stage4_uk!G46),stage4_uk!G46,0))+SUM(G13)*(1-IF(ISNUMBER(stage4_uk!G47),stage4_uk!G47,0))+IF(ISNUMBER(G110),G110,0),"") | H29: =IF(ISNUMBER(H24),H22+(H23+H24+H25+H26+SUM(H8))*(1-IF(ISNUMBER(stage4_uk!H48),stage4_uk!H48,0))+SUM(H9)+H10*(1-IF(ISNUMBER(stage4_uk!H45),stage4_uk!H45,0))+SUM(H11)*(1-IF(ISNUMBER(stage4_uk!H44),stage4_uk!H44,0))+SUM(H12)*(1-IF(ISNUMBER(stage4_uk!H46),stage4_uk!H46,0))+SUM(H13)*(1-IF(ISNUMBER(stage4_uk!H47),stage4_uk!H47,0))+IF(ISNUMBER(H110),H110,0),"") | I29: =IF(ISNUMBER(I24),I22+(I23+I24+I25+I26+SUM(I8))*(1-IF(ISNUMBER(stage4_uk!I48),stage4_uk!I48,0))+SUM(I9)+I10*(1-IF(ISNUMBER(stage4_uk!I45),stage4_uk!I45,0))+SUM(I11)*(1-IF(ISNUMBER(stage4_uk!I44),stage4_uk!I44,0))+SUM(I12)*(1-IF(ISNUMBER(stage4_uk!I46),stage4_uk!I46,0))+SUM(I13)*(1-IF(ISNUMBER(stage4_uk!I47),stage4_uk!I47,0))+IF(ISNUMBER(I110),I110,0),"") | J29: =IF(ISNUMBER(J24),J22+(J23+J24+J25+J26+SUM(J8))*(1-IF(ISNUMBER(stage4_uk!J48),stage4_uk!J48,0))+SUM(J9)+J10*(1-IF(ISNUMBER(stage4_uk!J45),stage4_uk!J45,0))+SUM(J11)*(1-IF(ISNUMBER(stage4_uk!J44),stage4_uk!J44,0))+SUM(J12)*(1-IF(ISNUMBER(stage4_uk!J46),stage4_uk!J46,0))+SUM(J13)*(1-IF(ISNUMBER(stage4_uk!J47),stage4_uk!J47,0))+IF(ISNUMBER(J110),J110,0),"") | K29: =IF(ISNUMBER(K24),K22+(K23+K24+K25+K26+SUM(K8))*(1-IF(ISNUMBER(stage4_uk!K48),stage4_uk!K48,0))+SUM(K9)+K10*(1-IF(ISNUMBER(stage4_uk!K45),stage4_uk!K45,0))+SUM(K11)*(1-IF(ISNUMBER(stage4_uk!K44),stage4_uk!K44,0))+SUM(K12)*(1-IF(ISNUMBER(stage4_uk!K46),stage4_uk!K46,0))+SUM(K13)*(1-IF(ISNUMBER(stage4_uk!K47),stage4_uk!K47,0))+IF(ISNUMBER(K110),K110,0),"") | ... T29: =IF(ISNUMBER(T24),T22+(T23+T24+T25+T26+SUM(T8))*(1-IF(ISNUMBER(stage4_uk!T48),stage4_uk!T48,0))+SUM(T9)+T10*(1-IF(ISNUMBER(stage4_uk!T45),stage4_uk!T45,0))+SUM(T11)*(1-IF(ISNUMBER(stage4_uk!T44),stage4_uk!T44,0))+SUM(T12)*(1-IF(ISNUMBER(stage4_uk!T46),stage4_uk!T46,0))+SUM(T13)*(1-IF(ISNUMBER(stage4_uk!T47),stage4_uk!T47,0))+IF(ISNUMBER(T110),T110,0),"") | U29: NCC covers TNUoS+DUoS+BSUoS. D24: medium assumed to hold EII certificate — stated on every E2 chart.
A30: UK | B30: OBSERVED: QEP Large band (20–70 GWh), INCL CCL (D71) — archetype at band lower edge (flag) | C30: obs | D30: =stage4_uk!D52*10 | E30: =stage4_uk!E52*10 | F30: =stage4_uk!F52*10 | G30: =stage4_uk!G52*10 | H30: =stage4_uk!H52*10 | I30: =stage4_uk!I52*10 | J30: =stage4_uk!J52*10 | K30: =stage4_uk!K52*10 | ... S30: =stage4_uk!S52*10
A31: DE — LARGE archetype (500 GWh, 8,000h, Höchstspannung, Amprion/bundeseinheitlich). Nominal €/MWh.
A32: DE | B32: Wholesale (Phelix front-year: trading yr Y−1 → delivery Y). 2010 & 2026 GAP (MB coverage) | C32: E1+E2 | E32: =stage4_de!D7 | F32: =stage4_de!E7 | G32: =stage4_de!F7 | H32: =stage4_de!G7 | I32: =stage4_de!H7 | J32: =stage4_de!I7 | K32: =stage4_de!J7 | L32: =stage4_de!K7 | ... T32: =stage4_de!S7 | U32: BNetzA MB series. DE-AT split 10/2018.
A33: DE | B33: Netzentgelte HöS (LP×1000/h + AP×10). 2026 incl. €6.5bn subsidy | C33: E1 network | D33: =stage4_de!D11*1000/assumptions!$B$7+stage4_de!D12*10 | E33: =stage4_de!E11*1000/assumptions!$B$7+stage4_de!E12*10 | F33: =stage4_de!F11*1000/assumptions!$B$7+stage4_de!F12*10 | G33: =stage4_de!G11*1000/assumptions!$B$7+stage4_de!G12*10 | H33: =stage4_de!H11*1000/assumptions!$B$7+stage4_de!H12*10 | I33: =stage4_de!I11*1000/assumptions!$B$7+stage4_de!I12*10 | J33: =stage4_de!J11*1000/assumptions!$B$7+stage4_de!J12*10 | K33: =stage4_de!K11*1000/assumptions!$B$7+stage4_de!K12*10 | ... T33: =stage4_de!T11*1000/assumptions!$B$7+stage4_de!T12*10
A34: DE | B34: 2026 Netz HöS OHNE Bundeszuschuss (info — the counterfactual without incidence-(iii) subsidy) | C34: info | T34: =stage4_de!T13*1000/assumptions!$B$7+stage4_de!T14*10
A35: DE | B35: EEG-Umlage (E1, full) | C35: E1 | D35: =stage4_de!D21*10 | E35: =stage4_de!E21*10 | F35: =stage4_de!F21*10 | G35: =stage4_de!G21*10 | H35: =stage4_de!H21*10 | I35: =stage4_de!I21*10 | J35: =stage4_de!J21*10 | K35: =stage4_de!K21*10 | ... T35: =stage4_de!T21*10 | U35: 2022 = year-avg (est=Y); 0 from 2023 (budget, incidence iii).
A36: DE | B36: KWKG (E1: Kat-B/B′ blend to 2016; full non-priv from 2017 — structural break) | C36: E1 | D36: =(0.1*stage4_de!D22+499.9*stage4_de!D23)/500*10 | E36: =(0.1*stage4_de!E22+499.9*stage4_de!E23)/500*10 | F36: =(0.1*stage4_de!F22+499.9*stage4_de!F23)/500*10 | G36: =(0.1*stage4_de!G22+499.9*stage4_de!G23)/500*10 | H36: =(0.1*stage4_de!H22+499.9*stage4_de!H23)/500*10 | I36: =(0.1*stage4_de!I22+499.9*stage4_de!I23)/500*10 | J36: =(1*stage4_de!J22+499*stage4_de!J23)/500*10 | K36: =stage4_de!K22*10 | L36: =stage4_de!L22*10 | M36: =stage4_de!M22*10 | N36: =stage4_de!N22*10 | O36: =stage4_de!O22*10 | P36: =stage4_de!P22*10 | Q36: =stage4_de!Q22*10 | R36: =stage4_de!R22*10 | ... T36: =stage4_de!T22*10 | U36: 2010–15: Kat A first 100 MWh, Kat B above; 2016: A′ first 1 GWh, B′ above. Break 2017 marked.
A37: DE | B37: §19-Umlage (E1: A′ first 1 GWh + B′ above; from 2012) | C37: E1 | F37: =(1*stage4_de!F25+499*stage4_de!F26)/500*10 | G37: =(1*stage4_de!G25+499*stage4_de!G26)/500*10 | H37: =(1*stage4_de!H25+499*stage4_de!H26)/500*10 | I37: =(1*stage4_de!I25+499*stage4_de!I26)/500*10 | J37: =(1*stage4_de!J25+499*stage4_de!J26)/500*10 | K37: =(1*stage4_de!K25+499*stage4_de!K26)/500*10 | L37: =(1*stage4_de!L25+499*stage4_de!L26)/500*10 | M37: =(1*stage4_de!M25+499*stage4_de!M26)/500*10 | ... T37: =(1*stage4_de!T25+499*stage4_de!T26)/500*10
A38: DE | B38: Offshore-Umlage (E1: A/B blend 2013–18; full non-priv 2019+ — break) | C38: E1 | G38: =(1*stage4_de!G28+499*stage4_de!G29)/500*10 | H38: =(1*stage4_de!H28+499*stage4_de!H29)/500*10 | I38: =(1*stage4_de!I28+499*stage4_de!I29)/500*10 | J38: =(1*stage4_de!J28+499*stage4_de!J29)/500*10 | K38: =(1*stage4_de!K28+499*stage4_de!K29)/500*10 | L38: =(1*stage4_de!L28+499*stage4_de!L29)/500*10 | M38: =stage4_de!M28*10 | N38: =stage4_de!N28*10 | O38: =stage4_de!O28*10 | P38: =stage4_de!P28*10 | Q38: =stage4_de!Q28*10 | R38: =stage4_de!R28*10 | S38: =stage4_de!S28*10 | T38: =stage4_de!T28*10
A39: DE | B39: AbLaV-Umlage | C39: E1+E2 | H39: =stage4_de!H31*10 | I39: =stage4_de!I31*10 | J39: =stage4_de!J31*10 | K39: =stage4_de!K31*10 | L39: =stage4_de!L31*10 | M39: =stage4_de!M31*10 | N39: =stage4_de!N31*10 | O39: =stage4_de!O31*10 | ... T39: =stage4_de!T31*10 | U39: Ends 2022.
A40: DE | B40: Stromsteuer (full §3) + Konzessionsabgabe (0 via Grenzpreis) | C40: E1 | D40: =stage4_de!D34+stage4_de!D36*10 | E40: =stage4_de!E34+stage4_de!E36*10 | F40: =stage4_de!F34+stage4_de!F36*10 | G40: =stage4_de!G34+stage4_de!G36*10 | H40: =stage4_de!H34+stage4_de!H36*10 | I40: =stage4_de!I34+stage4_de!I36*10 | J40: =stage4_de!J34+stage4_de!J36*10 | K40: =stage4_de!K34+stage4_de!K36*10 | ... T40: =stage4_de!T34+stage4_de!T36*10
A41: DE | B41: E1 TOTAL (blank 2010/2026 — wholesale gap) | C41: E1 | D41: =IF(ISNUMBER(D32),D32+D33+D35+D36+SUM(D37)+SUM(D38)+SUM(D39)+D40,"") | E41: =IF(ISNUMBER(E32),E32+E33+E35+E36+SUM(E37)+SUM(E38)+SUM(E39)+E40,"") | F41: =IF(ISNUMBER(F32),F32+F33+F35+F36+SUM(F37)+SUM(F38)+SUM(F39)+F40,"") | G41: =IF(ISNUMBER(G32),G32+G33+G35+G36+SUM(G37)+SUM(G38)+SUM(G39)+G40,"") | H41: =IF(ISNUMBER(H32),H32+H33+H35+H36+SUM(H37)+SUM(H38)+SUM(H39)+H40,"") | I41: =IF(ISNUMBER(I32),I32+I33+I35+I36+SUM(I37)+SUM(I38)+SUM(I39)+I40,"") | J41: =IF(ISNUMBER(J32),J32+J33+J35+J36+SUM(J37)+SUM(J38)+SUM(J39)+J40,"") | K41: =IF(ISNUMBER(K32),K32+K33+K35+K36+SUM(K37)+SUM(K38)+SUM(K39)+K40,"") | ... T41: =IF(ISNUMBER(T32),T32+T33+T35+T36+SUM(T37)+SUM(T38)+SUM(T39)+T40,"") | U41: MODELLED.
A42: DE | B42: E2 network: 2011 = 0 (§19(2) S.2 exemption, approvals eff. 01.01.2011); 2012–13 = 10% floor (8,000h; §32(7) retroactive, D32); 2014+ = Netz × (1−0.76), D8 | C42: E2 | E42: 0 | F42: =F33*0.1 | G42: =G33*0.1 | H42: =H33*(1-0.76) | I42: =I33*(1-0.76) | J42: =J33*(1-0.76) | K42: =K33*(1-0.76) | L42: =L33*(1-0.76) | M42: =M33*(1-0.76) | N42: =N33*(1-0.76) | O42: =O33*(1-0.76) | ... T42: =T33*(1-0.76) | U42: AgNes 68-HS-site avg Bandlast rebate. estimated=Y. NEVER delete the band (rows below).
A43: DE | B43: E2 network band LOW = 10% statutory floor (§19(2) S.2 Nr.3, ≥8,000h) | C43: E2 band | H43: =H33*0.1 | I43: =I33*0.1 | J43: =J33*0.1 | K43: =K33*0.1 | L43: =L33*0.1 | M43: =M33*0.1 | N43: =N33*0.1 | O43: =O33*0.1 | ... T43: =T33*0.1
A44: DE | B44: E2 network band HIGH = full published tariff | C44: E2 band | H44: =H33 | I44: =I33 | J44: =J33 | K44: =K33 | L44: =L33 | M44: =M33 | N44: =N33 | O44: =O33 | ... T44: =T33
A45: DE | B45: E2 EEG (BesAR: 0.05 ct floor era-central 2012–2021; band-high = uncapped 15% formula; 2022 H1 pro-rata; 2010–11 GAP) | C45: E2 | D45: 0.5 | E45: 0.5 | F45: 0.5 | G45: 0.5 | H45: 0.5 | I45: 0.5 | J45: 0.5 | K45: 0.5 | L45: 0.5 | M45: 0.5 | N45: 0.5 | O45: 0.5 | P45: 0.25 | Q45: 0 | R45: 0 | S45: 0 | T45: 0 | U45: REGIME SPLIT (Q90, 2026-07-24). 2010–2012 = EEG 2009 §§40–44 + §6 AusglMechV: flat 0.05 ct/kWh cap on the privileged volume, with a 10% SELBSTBEHALT at the full Umlage UNLESS the site clears BOTH ≥100 GWh AND ≥20% Stromkosten/Bruttowertschöpfung (§41(3) S.1 — the limbs are joined by "oder", so failing either brings the Selbstbehalt back). The large archetype (500 GWh) is modelled vollbegünstigt, so 0.05 ct/kWh across the whole volume = 0.5 €/MWh, unchanged 2010–2012. 2013+ = EEG 2012 §41(3) tranche ladder (≤1 GWh full / 1–10 GWh 10% / 10–100 GWh 1% / >100 GWh 0.05 ct), then EEG 2014/2017/2021 §64 floors 0.05 (cap assumed binding — typical large EII; est=Y). CRITICAL TIMING: the EEG 2012 ladder FIRST APPLIES TO BENEFIT YEAR 2013, not 2012 — §43(1) makes applications due 30 June effective 1 January of the FOLLOWING year, and §66(13) EEG 2012 applies §41 to applications made IN 2012. Benefit year 2012 ran on applications filed 30.06.2011 under EEG 2009. Empirical confirmation: privileged undertakings 734 (2012) → 1,691 (2013) when the 1 GWh threshold bit. S189/S191. High-band 2013+: =(1+0.15×499)/500×Umlage.
A46: DE | B46: E2 EEG band HIGH (no cap: 1 GWh full + 15% above) | C46: E2 band | D46: =(0.1*stage4_de!D21+0.9*0.05)*10 | E46: =(0.1*stage4_de!E21+0.9*0.05)*10 | F46: =(1*stage4_de!F21+499*0.15*stage4_de!F21)/500*10 | G46: =(1*stage4_de!G21+499*0.15*stage4_de!G21)/500*10 | H46: =(1*stage4_de!H21+499*0.15*stage4_de!H21)/500*10 | I46: =(1*stage4_de!I21+499*0.15*stage4_de!I21)/500*10 | J46: =(1*stage4_de!J21+499*0.15*stage4_de!J21)/500*10 | K46: =(1*stage4_de!K21+499*0.15*stage4_de!K21)/500*10 | L46: =(1*stage4_de!L21+499*0.15*stage4_de!L21)/500*10 | M46: =(1*stage4_de!M21+499*0.15*stage4_de!M21)/500*10 | ... T46: =(1*stage4_de!T21+499*0.15*stage4_de!T21)/500*10 | U46: 2010–2012 band HIGH = the TEILBEGÜNSTIGT outcome, i.e. a large site that clears 15% but not 20% Stromkosten/BWS and therefore keeps the 10% Selbstbehalt: 0.1×Umlage + 0.9×0.05 ct. This is the correct EEG 2009 upper case and replaces the EEG-2012 tranche formula, which did not apply before benefit year 2013. Q90 / S189.
A47: DE | B47: E2 KWKG (2016 C′ blend; other years = E1, flagged — D25 overstates E2) | C47: E2 | D47: =D36 | E47: =E36 | F47: =F36 | G47: =G36 | H47: =H36 | I47: =I36 | J47: =(1*stage4_de!J22+499*stage4_de!J24)/500*10 | K47: =K36 | L47: =L36 | M47: =M36 | N47: =N36 | O47: =O36 | P47: =P36 | Q47: =Q36 | R47: =R36 | ... T47: =T36 | U47: Kat C 2010–15 GAP; privileged rates company-specific 2017+ (D25).
A48: DE | B48: E2 §19-Umlage (C′ stromintensiv blend) | C48: E2 | F48: =(1*stage4_de!F25+499*stage4_de!F27)/500*10 | G48: =(1*stage4_de!G25+499*stage4_de!G27)/500*10 | H48: =(1*stage4_de!H25+499*stage4_de!H27)/500*10 | I48: =(1*stage4_de!I25+499*stage4_de!I27)/500*10 | J48: =(1*stage4_de!J25+499*stage4_de!J27)/500*10 | K48: =(1*stage4_de!K25+499*stage4_de!K27)/500*10 | L48: =(1*stage4_de!L25+499*stage4_de!L27)/500*10 | M48: =(1*stage4_de!M25+499*stage4_de!M27)/500*10 | ... T48: =(1*stage4_de!T25+499*stage4_de!T27)/500*10
A49: DE | B49: E2 Offshore (Kat C blend 2013–18; = E1 2019+, D25) | C49: E2 | G49: =(1*stage4_de!G28+499*stage4_de!G30)/500*10 | H49: =(1*stage4_de!H28+499*stage4_de!H30)/500*10 | I49: =(1*stage4_de!I28+499*stage4_de!I30)/500*10 | J49: =(1*stage4_de!J28+499*stage4_de!J30)/500*10 | K49: =(1*stage4_de!K28+499*stage4_de!K30)/500*10 | L49: =(1*stage4_de!L28+499*stage4_de!L30)/500*10 | M49: =M38 | N49: =N38 | O49: =O38 | P49: =P38 | Q49: =Q38 | R49: =R38 | S49: =S38 | T49: =T38
A50: DE | B50: E2 Stromsteuer (2010 §9(3) 12.30; §9b 2011+; §10 Spitzenausgleich NOT modelled — overstates E2) | C50: E2 | D50: =stage4_de!D35 | E50: =stage4_de!E35 | F50: =stage4_de!F35 | G50: =stage4_de!G35 | H50: =stage4_de!H35 | I50: =stage4_de!I35 | J50: =stage4_de!J35 | K50: =stage4_de!K35 | ... T50: =stage4_de!T35
A51: DE | B51: E2 TOTAL central (2014–2025; SPK not netted — wholesale carbon relief unmodelled, qc) | C51: E2 | D51: =IF(AND(ISNUMBER(D32),ISNUMBER(D42),ISNUMBER(D45)),D32+D42+D45+D47+SUM(D48)+SUM(D49)+SUM(D39)+D50,"") | E51: =IF(AND(ISNUMBER(E32),ISNUMBER(E42),ISNUMBER(E45)),E32+E42+E45+E47+SUM(E48)+SUM(E49)+SUM(E39)+E50,"") | F51: =IF(AND(ISNUMBER(F32),ISNUMBER(F42),ISNUMBER(F45)),F32+F42+F45+F47+SUM(F48)+SUM(F49)+SUM(F39)+F50,"") | G51: =IF(AND(ISNUMBER(G32),ISNUMBER(G42),ISNUMBER(G45)),G32+G42+G45+G47+SUM(G48)+SUM(G49)+SUM(G39)+G50,"") | H51: =IF(AND(ISNUMBER(H32),ISNUMBER(H42),ISNUMBER(H45)),H32+H42+H45+H47+SUM(H48)+SUM(H49)+SUM(H39)+H50,"") | I51: =IF(AND(ISNUMBER(I32),ISNUMBER(I42),ISNUMBER(I45)),I32+I42+I45+I47+SUM(I48)+SUM(I49)+SUM(I39)+I50,"") | J51: =IF(AND(ISNUMBER(J32),ISNUMBER(J42),ISNUMBER(J45)),J32+J42+J45+J47+SUM(J48)+SUM(J49)+SUM(J39)+J50,"") | K51: =IF(AND(ISNUMBER(K32),ISNUMBER(K42),ISNUMBER(K45)),K32+K42+K45+K47+SUM(K48)+SUM(K49)+SUM(K39)+K50,"") | ... T51: =IF(AND(ISNUMBER(T32),ISNUMBER(T42),ISNUMBER(T45)),T32+T42+T45+T47+SUM(T48)+SUM(T49)+SUM(T39)+T50,"") | U51: MODELLED. Band = swap network central for low/high rows.
A52: DE | B52: E2 TOTAL band LOW (network at 10% floor) | C52: E2 band | D52: =IF(ISNUMBER(D51),D51-D42+D43,"") | E52: =IF(ISNUMBER(E51),E51-E42+E43,"") | F52: =IF(ISNUMBER(F51),F51-F42+F43,"") | G52: =IF(ISNUMBER(G51),G51-G42+G43,"") | H52: =IF(ISNUMBER(H51),H51-H42+H43,"") | I52: =IF(ISNUMBER(I51),I51-I42+I43,"") | J52: =IF(ISNUMBER(J51),J51-J42+J43,"") | K52: =IF(ISNUMBER(K51),K51-K42+K43,"") | ... T52: =IF(ISNUMBER(T51),T51-T42+T43,"")
A53: DE | B53: E2 TOTAL band HIGH (network full + EEG high-band) | C53: E2 band | D53: =IF(ISNUMBER(D51),D51-D42+D44-D45+SUM(D46),"") | E53: =IF(ISNUMBER(E51),E51-E42+E44-E45+SUM(E46),"") | F53: =IF(ISNUMBER(F51),F51-F42+F44-F45+SUM(F46),"") | G53: =IF(ISNUMBER(G51),G51-G42+G44-G45+SUM(G46),"") | H53: =IF(ISNUMBER(H51),H51-H42+H44-H45+SUM(H46),"") | I53: =IF(ISNUMBER(I51),I51-I42+I44-I45+SUM(I46),"") | J53: =IF(ISNUMBER(J51),J51-J42+J44-J45+SUM(J46),"") | K53: =IF(ISNUMBER(K51),K51-K42+K44-K45+SUM(K46),"") | ... T53: =IF(ISNUMBER(T51),T51-T42+T44-T45+SUM(T46),"")
A54: DE | B54: OBSERVED: Eurostat IF (70–150 GWh) annual (validation); IG (≥150 GWh) from 2020 below | C54: obs | D54: =stage4_de!D42*1000 | E54: =stage4_de!E42*1000 | F54: =stage4_de!F42*1000 | G54: =stage4_de!G42*1000 | H54: =stage4_de!H42*1000 | I54: =stage4_de!I42*1000 | J54: =stage4_de!J42*1000 | K54: =stage4_de!K42*1000 | ... S54: =stage4_de!S42*1000 | U54: Semester avg, est=Y (D7).
A55: DE | B55: OBSERVED: Eurostat IG annual (2020+) | C55: obs | N55: =stage4_de!N45*1000 | O55: =stage4_de!O45*1000 | P55: =stage4_de!P45*1000 | Q55: =stage4_de!Q45*1000 | R55: =stage4_de!R45*1000 | S55: =stage4_de!S45*1000 | U55: Q21: IG usable 2019-S2+.
A56: DE — MEDIUM archetype (20 GWh, 5,000h, Mittelspannung, Westnetz). Nominal €/MWh.
A57: DE | B57: Wholesale (as large) | C57: E1+E2 | E57: =SUM(E32) | F57: =SUM(F32) | G57: =SUM(G32) | H57: =SUM(H32) | I57: =SUM(I32) | J57: =SUM(J32) | K57: =SUM(K32) | L57: =SUM(L32) | ... T57: =SUM(T32)
A58: DE | B58: Netzentgelte MS (Westnetz 2013+; MB national-avg bridge 2010–12, 6,000h case — flagged, D20) | C58: E1=E2 network | D58: =stage4_de!D17*10 | E58: =stage4_de!E17*10 | F58: =stage4_de!F17*10 | G58: =stage4_de!G15*1000/assumptions!$C$7+stage4_de!G16*10 | H58: =stage4_de!H15*1000/assumptions!$C$7+stage4_de!H16*10 | I58: =stage4_de!I15*1000/assumptions!$C$7+stage4_de!I16*10 | J58: =stage4_de!J15*1000/assumptions!$C$7+stage4_de!J16*10 | K58: =stage4_de!K15*1000/assumptions!$C$7+stage4_de!K16*10 | L58: =stage4_de!L15*1000/assumptions!$C$7+stage4_de!L16*10 | M58: =stage4_de!M15*1000/assumptions!$C$7+stage4_de!M16*10 | N58: =stage4_de!N15*1000/assumptions!$C$7+stage4_de!N16*10 | ... T58: =stage4_de!T15*1000/assumptions!$C$7+stage4_de!T16*10 | U58: No §19 relief at 5,000h (fails Satz 2). Bridge era methodology break marked.
A59: DE | B59: Umlagen E1 (EEG full + KWKG/§19/Offshore blends at 20 GWh + AbLaV) | C59: E1 | D59: =stage4_de!D21*10+(0.1*stage4_de!D22+19.9*stage4_de!D23)/20*10 | E59: =stage4_de!E21*10+(0.1*stage4_de!E22+19.9*stage4_de!E23)/20*10 | F59: =stage4_de!F21*10+(0.1*stage4_de!F22+19.9*stage4_de!F23)/20*10+(1*stage4_de!F25+19*stage4_de!F26)/20*10 | G59: =stage4_de!G21*10+(0.1*stage4_de!G22+19.9*stage4_de!G23)/20*10+(1*stage4_de!G25+19*stage4_de!G26)/20*10+(1*stage4_de!G28+19*stage4_de!G29)/20*10 | H59: =stage4_de!H21*10+(0.1*stage4_de!H22+19.9*stage4_de!H23)/20*10+(1*stage4_de!H25+19*stage4_de!H26)/20*10+(1*stage4_de!H28+19*stage4_de!H29)/20*10+stage4_de!H31*10 | I59: =stage4_de!I21*10+(0.1*stage4_de!I22+19.9*stage4_de!I23)/20*10+(1*stage4_de!I25+19*stage4_de!I26)/20*10+(1*stage4_de!I28+19*stage4_de!I29)/20*10+stage4_de!I31*10 | J59: =stage4_de!J21*10+(1*stage4_de!J22+19*stage4_de!J23)/20*10+(1*stage4_de!J25+19*stage4_de!J26)/20*10+(1*stage4_de!J28+19*stage4_de!J29)/20*10+stage4_de!J31*10 | K59: =stage4_de!K21*10+stage4_de!K22*10+(1*stage4_de!K25+19*stage4_de!K26)/20*10+(1*stage4_de!K28+19*stage4_de!K29)/20*10+stage4_de!K31*10 | L59: =stage4_de!L21*10+stage4_de!L22*10+(1*stage4_de!L25+19*stage4_de!L26)/20*10+(1*stage4_de!L28+19*stage4_de!L29)/20*10+stage4_de!L31*10 | M59: =stage4_de!M21*10+stage4_de!M22*10+(1*stage4_de!M25+19*stage4_de!M26)/20*10+stage4_de!M28*10+stage4_de!M31*10 | N59: =stage4_de!N21*10+stage4_de!N22*10+(1*stage4_de!N25+19*stage4_de!N26)/20*10+stage4_de!N28*10+stage4_de!N31*10 | O59: =stage4_de!O21*10+stage4_de!O22*10+(1*stage4_de!O25+19*stage4_de!O26)/20*10+stage4_de!O28*10+stage4_de!O31*10 | P59: =stage4_de!P21*10+stage4_de!P22*10+(1*stage4_de!P25+19*stage4_de!P26)/20*10+stage4_de!P28*10+stage4_de!P31*10 | Q59: =stage4_de!Q21*10+stage4_de!Q22*10+(1*stage4_de!Q25+19*stage4_de!Q26)/20*10+stage4_de!Q28*10+stage4_de!Q31*10 | R59: =stage4_de!R21*10+stage4_de!R22*10+(1*stage4_de!R25+19*stage4_de!R26)/20*10+stage4_de!R28*10+stage4_de!R31*10 | S59: =stage4_de!S21*10+stage4_de!S22*10+(1*stage4_de!S25+19*stage4_de!S26)/20*10+stage4_de!S28*10+stage4_de!S31*10 | T59: =stage4_de!T21*10+stage4_de!T22*10+(1*stage4_de!T25+19*stage4_de!T26)/20*10+stage4_de!T28*10+stage4_de!T31*10 | U59: Same era structure as large; tranche blends at 20 GWh.
A60: DE | B60: Stromsteuer + KA (E1) | C60: E1 | D60: =stage4_de!D34+stage4_de!D36*10 | E60: =stage4_de!E34+stage4_de!E36*10 | F60: =stage4_de!F34+stage4_de!F36*10 | G60: =stage4_de!G34+stage4_de!G36*10 | H60: =stage4_de!H34+stage4_de!H36*10 | I60: =stage4_de!I34+stage4_de!I36*10 | J60: =stage4_de!J34+stage4_de!J36*10 | K60: =stage4_de!K34+stage4_de!K36*10 | ... T60: =stage4_de!T34+stage4_de!T36*10
A61: DE | B61: E1 TOTAL medium | C61: E1 | D61: =IF(ISNUMBER(D57),D57+D58+D59+D60,"") | E61: =IF(ISNUMBER(E57),E57+E58+E59+E60,"") | F61: =IF(ISNUMBER(F57),F57+F58+F59+F60,"") | G61: =IF(ISNUMBER(G57),G57+G58+G59+G60,"") | H61: =IF(ISNUMBER(H57),H57+H58+H59+H60,"") | I61: =IF(ISNUMBER(I57),I57+I58+I59+I60,"") | J61: =IF(ISNUMBER(J57),J57+J58+J59+J60,"") | K61: =IF(ISNUMBER(K57),K57+K58+K59+K60,"") | ... T61: =IF(ISNUMBER(T57),T57+T58+T59+T60,"") | U61: MODELLED.
A62: DE | B62: E2 EEG medium (BesAR per D24: 2012–13 sliding ≈10%×U; 2014–21 central = (1+19×0.15)/20×U uncapped; band-low = 0.1 ct floor) | C62: E2 | D62: =(0.1*stage4_de!D21+0.9*0.05)*10 | E62: =(0.1*stage4_de!E21+0.9*0.05)*10 | F62: =(0.1*stage4_de!F21+0.9*0.05)*10 | G62: =0.1*stage4_de!G21*10 | H62: =(1*stage4_de!H21+19*0.15*stage4_de!H21)/20*10 | I62: =(1*stage4_de!I21+19*0.15*stage4_de!I21)/20*10 | J62: =(1*stage4_de!J21+19*0.15*stage4_de!J21)/20*10 | K62: =(1*stage4_de!K21+19*0.15*stage4_de!K21)/20*10 | L62: =(1*stage4_de!L21+19*0.15*stage4_de!L21)/20*10 | M62: =(1*stage4_de!M21+19*0.15*stage4_de!M21)/20*10 | N62: =(1*stage4_de!N21+19*0.15*stage4_de!N21)/20*10 | O62: =(1*stage4_de!O21+19*0.15*stage4_de!O21)/20*10 | ... T62: =(1*stage4_de!T21+19*0.15*stage4_de!T21)/20*10 | U62: MEDIUM (20 GWh) is ALWAYS teilbegünstigt — §41(3) EEG 2009 exempts only sites clearing BOTH ≥100 GWh AND ≥20% Stromkosten/BWS, and 20 GWh can never clear the first limb. 2010–2012 (EEG 2009 regime): 0.1×Umlage + 0.9×0.05 ct/kWh → 0.2497 / 0.398 / 0.4042 ct/kWh. Eligibility met: >10 GWh and >15% BWS assumed per D24. 2013+ (EEG 2012 §41(3) ladder): at EXACTLY 20 GWh the ladder collapses to 10% of the Umlage — (1×U + 9×0.1U + 10×0.01U)/20 = 2U/20 = 0.1U — so the existing 0.1×U formula is EXACTLY right for 2013 and must not be "corrected". 2014+ EEG 2014/2017/2021 §64: (1 + 19×0.15)/20 × U, cap (BWS) unknowable for the archetype → central = no-cap (conservative-high). Q90 / S189/S190. est=Y.
A63: DE | B63: E2 Umlagen other (KWKG =E1 exc 2016 C′; §19 C′; Offshore C/=E1; AbLaV) | C63: E2 | D63: =(0.1*stage4_de!D22+19.9*stage4_de!D23)/20*10 | E63: =(0.1*stage4_de!E22+19.9*stage4_de!E23)/20*10 | F63: =(0.1*stage4_de!F22+19.9*stage4_de!F23)/20*10+(1*stage4_de!F25+19*stage4_de!F27)/20*10 | G63: =(0.1*stage4_de!G22+19.9*stage4_de!G23)/20*10+(1*stage4_de!G25+19*stage4_de!G27)/20*10+(1*stage4_de!G28+19*stage4_de!G30)/20*10 | H63: =(0.1*stage4_de!H22+19.9*stage4_de!H23)/20*10+(1*stage4_de!H25+19*stage4_de!H27)/20*10+(1*stage4_de!H28+19*stage4_de!H30)/20*10+stage4_de!H31*10 | I63: =(0.1*stage4_de!I22+19.9*stage4_de!I23)/20*10+(1*stage4_de!I25+19*stage4_de!I27)/20*10+(1*stage4_de!I28+19*stage4_de!I30)/20*10+stage4_de!I31*10 | J63: =(1*stage4_de!J22+19*stage4_de!J24)/20*10+(1*stage4_de!J25+19*stage4_de!J27)/20*10+(1*stage4_de!J28+19*stage4_de!J30)/20*10+stage4_de!J31*10 | K63: =stage4_de!K22*10+(1*stage4_de!K25+19*stage4_de!K27)/20*10+(1*stage4_de!K28+19*stage4_de!K30)/20*10+stage4_de!K31*10 | L63: =stage4_de!L22*10+(1*stage4_de!L25+19*stage4_de!L27)/20*10+(1*stage4_de!L28+19*stage4_de!L30)/20*10+stage4_de!L31*10 | M63: =stage4_de!M22*10+(1*stage4_de!M25+19*stage4_de!M27)/20*10+stage4_de!M28*10+stage4_de!M31*10 | N63: =stage4_de!N22*10+(1*stage4_de!N25+19*stage4_de!N27)/20*10+stage4_de!N28*10+stage4_de!N31*10 | O63: =stage4_de!O22*10+(1*stage4_de!O25+19*stage4_de!O27)/20*10+stage4_de!O28*10+stage4_de!O31*10 | P63: =stage4_de!P22*10+(1*stage4_de!P25+19*stage4_de!P27)/20*10+stage4_de!P28*10+stage4_de!P31*10 | Q63: =stage4_de!Q22*10+(1*stage4_de!Q25+19*stage4_de!Q27)/20*10+stage4_de!Q28*10+stage4_de!Q31*10 | R63: =stage4_de!R22*10+(1*stage4_de!R25+19*stage4_de!R27)/20*10+stage4_de!R28*10+stage4_de!R31*10 | S63: =stage4_de!S22*10+(1*stage4_de!S25+19*stage4_de!S27)/20*10+stage4_de!S28*10+stage4_de!S31*10 | T63: =stage4_de!T22*10+(1*stage4_de!T25+19*stage4_de!T27)/20*10+stage4_de!T28*10+stage4_de!T31*10 | U63: D25 where privileged rate unpublished (2017+/2019+) — overstates E2, flagged.
A64: DE | B64: E2 TOTAL medium (2012+; EII status assumed, D24) | C64: E2 | D64: =IF(ISNUMBER(D57),D57+D58+D62+D63+stage4_de!D35,"") | E64: =IF(ISNUMBER(E57),E57+E58+E62+E63+stage4_de!E35,"") | F64: =IF(ISNUMBER(F57),F57+F58+F62+F63+stage4_de!F35,"") | G64: =IF(ISNUMBER(G57),G57+G58+G62+G63+stage4_de!G35,"") | H64: =IF(ISNUMBER(H57),H57+H58+H62+H63+stage4_de!H35,"") | I64: =IF(ISNUMBER(I57),I57+I58+I62+I63+stage4_de!I35,"") | J64: =IF(ISNUMBER(J57),J57+J58+J62+J63+stage4_de!J35,"") | K64: =IF(ISNUMBER(K57),K57+K58+K62+K63+stage4_de!K35,"") | ... T64: =IF(ISNUMBER(T57),T57+T58+T62+T63+stage4_de!T35,"") | U64: Network = E1 (no §19 at 5,000h).
A65: DE | B65: OBSERVED: Eurostat ID (2–20 GWh) annual | C65: obs | D65: =stage4_de!D39*1000 | E65: =stage4_de!E39*1000 | F65: =stage4_de!F39*1000 | G65: =stage4_de!G39*1000 | H65: =stage4_de!H39*1000 | I65: =stage4_de!I39*1000 | J65: =stage4_de!J39*1000 | K65: =stage4_de!K39*1000 | ... S65: =stage4_de!S39*1000 | U65: GN3 (BDEW 17.6 ct 2025) is the second anchor.
A66: CN — provincial basket (renormalised, D23; coverage row shown). Nominal 元/MWh. E1 = E2 (no formal exemption regime).
A67: CN | B67: LARGE: catalogue basket 2012–21 (2020 incl. COVID rebate; 2021 Jan–Sep) → market basket 2022+ (JS/GD/HN) | C67: E1=E2 | F67: =stage4_cn!F58 | G67: =stage4_cn!G58 | H67: =stage4_cn!H58 | I67: =stage4_cn!I58 | J67: =stage4_cn!J58 | K67: =stage4_cn!K58 | L67: =stage4_cn!L58 | M67: =stage4_cn!M58 | N67: =stage4_cn!N58+stage4_cn!N63 | O67: =stage4_cn!O58 | P67: =stage4_cn!P88 | Q67: =stage4_cn!Q88 | R67: =stage4_cn!R88 | S67: =stage4_cn!S88 | T67: =stage4_cn!T88 | U67: Breaks 2021-10 & 2026 marked; never a continuous line. 系统运行 proxy flags (stage4_cn).
A68: CN | B68: LARGE excl Inner Mongolia (swing constituent; catalogue era only — IM absent from market basket anyway) | C68: E1=E2 variant | F68: =stage4_cn!F59 | G68: =stage4_cn!G59 | H68: =stage4_cn!H59 | I68: =stage4_cn!I59 | J68: =stage4_cn!J59 | K68: =stage4_cn!K59 | L68: =stage4_cn!L59 | M68: =stage4_cn!M59 | ... O68: =stage4_cn!O59
A69: CN | B69: LARGE basket coverage (Set-C weight share) | C69: note | F69: =stage4_cn!F62 | G69: =stage4_cn!G62 | H69: =stage4_cn!H62 | I69: =stage4_cn!I62 | J69: =stage4_cn!J62 | K69: =stage4_cn!K62 | L69: =stage4_cn!L62 | M69: =stage4_cn!M62 | ... O69: =stage4_cn!O62 | P69: =stage4_cn!P89 | Q69: =stage4_cn!Q89 | R69: =stage4_cn!R89 | S69: =stage4_cn!S89 | T69: =stage4_cn!T89 | U69: Report on every chart.
A70: CN | B70: MEDIUM: catalogue basket 2012–21 (2020 incl. COVID) → JS 代理购电 build 2022+ (coverage 17.7%) | C70: E1=E2 | F70: =stage4_cn!F60 | G70: =stage4_cn!G60 | H70: =stage4_cn!H60 | I70: =stage4_cn!I60 | J70: =stage4_cn!J60 | K70: =stage4_cn!K60 | L70: =stage4_cn!L60 | M70: =stage4_cn!M60 | N70: =stage4_cn!N60*(1-0.05*11/12) | O70: =stage4_cn!O60 | P70: =stage4_cn!P93 | Q70: =stage4_cn!Q93 | R70: =stage4_cn!R93 | S70: =stage4_cn!S93 | T70: =stage4_cn!T93 | U70: GD/SD/HN full-bill snapshots kept as anchors (stage4_cn). 需量-basis two-part throughout.
A71: CN | B71: MEDIUM excl Inner Mongolia (catalogue era) | C71: E1=E2 variant | F71: =stage4_cn!F61 | G71: =stage4_cn!G61 | H71: =stage4_cn!H61 | I71: =stage4_cn!I61 | J71: =stage4_cn!J61 | K71: =stage4_cn!K61 | L71: =stage4_cn!L61 | M71: =stage4_cn!M61 | ... O71: =stage4_cn!O61
A72: CN | B72: No validation overlay exists for CN (no band-average survey) — owned in text; NEA 通报 anchors on qc list | C72: note
A73: REAL 2025 USD/MWh (Fed H.10 annual-avg FX × CPI-U deflator; fx_deflator helper cols I–M). NO 2026 conversion (D6). Footnote: "Real 2025 USD/MWh. Converted at annual-average market FX. Excludes VAT." CN series: 含税 as published (Q84; de-VAT memo stage6 r189–191).
A74: UK | B74: UK LARGE E1 — real 2025 USD/MWh | C74: USD | D74: =IF(ISNUMBER(D15),D15*fx_deflator!$I$5*fx_deflator!$M$5,"") | E74: =IF(ISNUMBER(E15),E15*fx_deflator!$I$6*fx_deflator!$M$6,"") | F74: =IF(ISNUMBER(F15),F15*fx_deflator!$I$7*fx_deflator!$M$7,"") | G74: =IF(ISNUMBER(G15),G15*fx_deflator!$I$8*fx_deflator!$M$8,"") | H74: =IF(ISNUMBER(H15),H15*fx_deflator!$I$9*fx_deflator!$M$9,"") | I74: =IF(ISNUMBER(I15),I15*fx_deflator!$I$10*fx_deflator!$M$10,"") | J74: =IF(ISNUMBER(J15),J15*fx_deflator!$I$11*fx_deflator!$M$11,"") | K74: =IF(ISNUMBER(K15),K15*fx_deflator!$I$12*fx_deflator!$M$12,"") | L74: =IF(ISNUMBER(L15),L15*fx_deflator!$I$13*fx_deflator!$M$13,"") | M74: =IF(ISNUMBER(M15),M15*fx_deflator!$I$14*fx_deflator!$M$14,"") | N74: =IF(ISNUMBER(N15),N15*fx_deflator!$I$15*fx_deflator!$M$15,"") | O74: =IF(ISNUMBER(O15),O15*fx_deflator!$I$16*fx_deflator!$M$16,"") | P74: =IF(ISNUMBER(P15),P15*fx_deflator!$I$17*fx_deflator!$M$17,"") | Q74: =IF(ISNUMBER(Q15),Q15*fx_deflator!$I$18*fx_deflator!$M$18,"") | R74: =IF(ISNUMBER(R15),R15*fx_deflator!$I$19*fx_deflator!$M$19,"") | S74: =IF(ISNUMBER(S15),S15*fx_deflator!$I$20*fx_deflator!$M$20,"")
A75: UK | B75: UK LARGE E2 — real 2025 USD/MWh | C75: USD | D75: =IF(ISNUMBER(D19),D19*fx_deflator!$I$5*fx_deflator!$M$5,"") | E75: =IF(ISNUMBER(E19),E19*fx_deflator!$I$6*fx_deflator!$M$6,"") | F75: =IF(ISNUMBER(F19),F19*fx_deflator!$I$7*fx_deflator!$M$7,"") | G75: =IF(ISNUMBER(G19),G19*fx_deflator!$I$8*fx_deflator!$M$8,"") | H75: =IF(ISNUMBER(H19),H19*fx_deflator!$I$9*fx_deflator!$M$9,"") | I75: =IF(ISNUMBER(I19),I19*fx_deflator!$I$10*fx_deflator!$M$10,"") | J75: =IF(ISNUMBER(J19),J19*fx_deflator!$I$11*fx_deflator!$M$11,"") | K75: =IF(ISNUMBER(K19),K19*fx_deflator!$I$12*fx_deflator!$M$12,"") | L75: =IF(ISNUMBER(L19),L19*fx_deflator!$I$13*fx_deflator!$M$13,"") | M75: =IF(ISNUMBER(M19),M19*fx_deflator!$I$14*fx_deflator!$M$14,"") | N75: =IF(ISNUMBER(N19),N19*fx_deflator!$I$15*fx_deflator!$M$15,"") | O75: =IF(ISNUMBER(O19),O19*fx_deflator!$I$16*fx_deflator!$M$16,"") | P75: =IF(ISNUMBER(P19),P19*fx_deflator!$I$17*fx_deflator!$M$17,"") | Q75: =IF(ISNUMBER(Q19),Q19*fx_deflator!$I$18*fx_deflator!$M$18,"") | R75: =IF(ISNUMBER(R19),R19*fx_deflator!$I$19*fx_deflator!$M$19,"") | S75: =IF(ISNUMBER(S19),S19*fx_deflator!$I$20*fx_deflator!$M$20,"")
A76: UK | B76: UK MEDIUM E1 — real 2025 USD/MWh | C76: USD | D76: =IF(ISNUMBER(D28),D28*fx_deflator!$I$5*fx_deflator!$M$5,"") | E76: =IF(ISNUMBER(E28),E28*fx_deflator!$I$6*fx_deflator!$M$6,"") | F76: =IF(ISNUMBER(F28),F28*fx_deflator!$I$7*fx_deflator!$M$7,"") | G76: =IF(ISNUMBER(G28),G28*fx_deflator!$I$8*fx_deflator!$M$8,"") | H76: =IF(ISNUMBER(H28),H28*fx_deflator!$I$9*fx_deflator!$M$9,"") | I76: =IF(ISNUMBER(I28),I28*fx_deflator!$I$10*fx_deflator!$M$10,"") | J76: =IF(ISNUMBER(J28),J28*fx_deflator!$I$11*fx_deflator!$M$11,"") | K76: =IF(ISNUMBER(K28),K28*fx_deflator!$I$12*fx_deflator!$M$12,"") | L76: =IF(ISNUMBER(L28),L28*fx_deflator!$I$13*fx_deflator!$M$13,"") | M76: =IF(ISNUMBER(M28),M28*fx_deflator!$I$14*fx_deflator!$M$14,"") | N76: =IF(ISNUMBER(N28),N28*fx_deflator!$I$15*fx_deflator!$M$15,"") | O76: =IF(ISNUMBER(O28),O28*fx_deflator!$I$16*fx_deflator!$M$16,"") | P76: =IF(ISNUMBER(P28),P28*fx_deflator!$I$17*fx_deflator!$M$17,"") | Q76: =IF(ISNUMBER(Q28),Q28*fx_deflator!$I$18*fx_deflator!$M$18,"") | R76: =IF(ISNUMBER(R28),R28*fx_deflator!$I$19*fx_deflator!$M$19,"") | S76: =IF(ISNUMBER(S28),S28*fx_deflator!$I$20*fx_deflator!$M$20,"")
A77: UK | B77: UK MEDIUM E2 — real 2025 USD/MWh | C77: USD | D77: =IF(ISNUMBER(D29),D29*fx_deflator!$I$5*fx_deflator!$M$5,"") | E77: =IF(ISNUMBER(E29),E29*fx_deflator!$I$6*fx_deflator!$M$6,"") | F77: =IF(ISNUMBER(F29),F29*fx_deflator!$I$7*fx_deflator!$M$7,"") | G77: =IF(ISNUMBER(G29),G29*fx_deflator!$I$8*fx_deflator!$M$8,"") | H77: =IF(ISNUMBER(H29),H29*fx_deflator!$I$9*fx_deflator!$M$9,"") | I77: =IF(ISNUMBER(I29),I29*fx_deflator!$I$10*fx_deflator!$M$10,"") | J77: =IF(ISNUMBER(J29),J29*fx_deflator!$I$11*fx_deflator!$M$11,"") | K77: =IF(ISNUMBER(K29),K29*fx_deflator!$I$12*fx_deflator!$M$12,"") | L77: =IF(ISNUMBER(L29),L29*fx_deflator!$I$13*fx_deflator!$M$13,"") | M77: =IF(ISNUMBER(M29),M29*fx_deflator!$I$14*fx_deflator!$M$14,"") | N77: =IF(ISNUMBER(N29),N29*fx_deflator!$I$15*fx_deflator!$M$15,"") | O77: =IF(ISNUMBER(O29),O29*fx_deflator!$I$16*fx_deflator!$M$16,"") | P77: =IF(ISNUMBER(P29),P29*fx_deflator!$I$17*fx_deflator!$M$17,"") | Q77: =IF(ISNUMBER(Q29),Q29*fx_deflator!$I$18*fx_deflator!$M$18,"") | R77: =IF(ISNUMBER(R29),R29*fx_deflator!$I$19*fx_deflator!$M$19,"") | S77: =IF(ISNUMBER(S29),S29*fx_deflator!$I$20*fx_deflator!$M$20,"")
A78: UK | B78: UK OBSERVED QEP Extra Large (incl CCL, D71) — real 2025 USD/MWh | C78: USD | D78: =IF(ISNUMBER(D20),D20*fx_deflator!$I$5*fx_deflator!$M$5,"") | E78: =IF(ISNUMBER(E20),E20*fx_deflator!$I$6*fx_deflator!$M$6,"") | F78: =IF(ISNUMBER(F20),F20*fx_deflator!$I$7*fx_deflator!$M$7,"") | G78: =IF(ISNUMBER(G20),G20*fx_deflator!$I$8*fx_deflator!$M$8,"") | H78: =IF(ISNUMBER(H20),H20*fx_deflator!$I$9*fx_deflator!$M$9,"") | I78: =IF(ISNUMBER(I20),I20*fx_deflator!$I$10*fx_deflator!$M$10,"") | J78: =IF(ISNUMBER(J20),J20*fx_deflator!$I$11*fx_deflator!$M$11,"") | K78: =IF(ISNUMBER(K20),K20*fx_deflator!$I$12*fx_deflator!$M$12,"") | L78: =IF(ISNUMBER(L20),L20*fx_deflator!$I$13*fx_deflator!$M$13,"") | M78: =IF(ISNUMBER(M20),M20*fx_deflator!$I$14*fx_deflator!$M$14,"") | N78: =IF(ISNUMBER(N20),N20*fx_deflator!$I$15*fx_deflator!$M$15,"") | O78: =IF(ISNUMBER(O20),O20*fx_deflator!$I$16*fx_deflator!$M$16,"") | P78: =IF(ISNUMBER(P20),P20*fx_deflator!$I$17*fx_deflator!$M$17,"") | Q78: =IF(ISNUMBER(Q20),Q20*fx_deflator!$I$18*fx_deflator!$M$18,"") | R78: =IF(ISNUMBER(R20),R20*fx_deflator!$I$19*fx_deflator!$M$19,"") | S78: =IF(ISNUMBER(S20),S20*fx_deflator!$I$20*fx_deflator!$M$20,"")
A79: UK | B79: UK OBSERVED QEP Large (incl CCL, D71) — real 2025 USD/MWh | C79: USD | D79: =IF(ISNUMBER(D30),D30*fx_deflator!$I$5*fx_deflator!$M$5,"") | E79: =IF(ISNUMBER(E30),E30*fx_deflator!$I$6*fx_deflator!$M$6,"") | F79: =IF(ISNUMBER(F30),F30*fx_deflator!$I$7*fx_deflator!$M$7,"") | G79: =IF(ISNUMBER(G30),G30*fx_deflator!$I$8*fx_deflator!$M$8,"") | H79: =IF(ISNUMBER(H30),H30*fx_deflator!$I$9*fx_deflator!$M$9,"") | I79: =IF(ISNUMBER(I30),I30*fx_deflator!$I$10*fx_deflator!$M$10,"") | J79: =IF(ISNUMBER(J30),J30*fx_deflator!$I$11*fx_deflator!$M$11,"") | K79: =IF(ISNUMBER(K30),K30*fx_deflator!$I$12*fx_deflator!$M$12,"") | L79: =IF(ISNUMBER(L30),L30*fx_deflator!$I$13*fx_deflator!$M$13,"") | M79: =IF(ISNUMBER(M30),M30*fx_deflator!$I$14*fx_deflator!$M$14,"") | N79: =IF(ISNUMBER(N30),N30*fx_deflator!$I$15*fx_deflator!$M$15,"") | O79: =IF(ISNUMBER(O30),O30*fx_deflator!$I$16*fx_deflator!$M$16,"") | P79: =IF(ISNUMBER(P30),P30*fx_deflator!$I$17*fx_deflator!$M$17,"") | Q79: =IF(ISNUMBER(Q30),Q30*fx_deflator!$I$18*fx_deflator!$M$18,"") | R79: =IF(ISNUMBER(R30),R30*fx_deflator!$I$19*fx_deflator!$M$19,"") | S79: =IF(ISNUMBER(S30),S30*fx_deflator!$I$20*fx_deflator!$M$20,"")
A80: DE | B80: DE LARGE E1 — real 2025 USD/MWh | C80: USD | D80: =IF(ISNUMBER(D41),D41*fx_deflator!$J$5*fx_deflator!$M$5,"") | E80: =IF(ISNUMBER(E41),E41*fx_deflator!$J$6*fx_deflator!$M$6,"") | F80: =IF(ISNUMBER(F41),F41*fx_deflator!$J$7*fx_deflator!$M$7,"") | G80: =IF(ISNUMBER(G41),G41*fx_deflator!$J$8*fx_deflator!$M$8,"") | H80: =IF(ISNUMBER(H41),H41*fx_deflator!$J$9*fx_deflator!$M$9,"") | I80: =IF(ISNUMBER(I41),I41*fx_deflator!$J$10*fx_deflator!$M$10,"") | J80: =IF(ISNUMBER(J41),J41*fx_deflator!$J$11*fx_deflator!$M$11,"") | K80: =IF(ISNUMBER(K41),K41*fx_deflator!$J$12*fx_deflator!$M$12,"") | L80: =IF(ISNUMBER(L41),L41*fx_deflator!$J$13*fx_deflator!$M$13,"") | M80: =IF(ISNUMBER(M41),M41*fx_deflator!$J$14*fx_deflator!$M$14,"") | N80: =IF(ISNUMBER(N41),N41*fx_deflator!$J$15*fx_deflator!$M$15,"") | O80: =IF(ISNUMBER(O41),O41*fx_deflator!$J$16*fx_deflator!$M$16,"") | P80: =IF(ISNUMBER(P41),P41*fx_deflator!$J$17*fx_deflator!$M$17,"") | Q80: =IF(ISNUMBER(Q41),Q41*fx_deflator!$J$18*fx_deflator!$M$18,"") | R80: =IF(ISNUMBER(R41),R41*fx_deflator!$J$19*fx_deflator!$M$19,"") | S80: =IF(ISNUMBER(S41),S41*fx_deflator!$J$20*fx_deflator!$M$20,"")
A81: DE | B81: DE LARGE E2 central — real 2025 USD/MWh | C81: USD | D81: =IF(ISNUMBER(D51),D51*fx_deflator!$J$5*fx_deflator!$M$5,"") | E81: =IF(ISNUMBER(E51),E51*fx_deflator!$J$6*fx_deflator!$M$6,"") | F81: =IF(ISNUMBER(F51),F51*fx_deflator!$J$7*fx_deflator!$M$7,"") | G81: =IF(ISNUMBER(G51),G51*fx_deflator!$J$8*fx_deflator!$M$8,"") | H81: =IF(ISNUMBER(H51),H51*fx_deflator!$J$9*fx_deflator!$M$9,"") | I81: =IF(ISNUMBER(I51),I51*fx_deflator!$J$10*fx_deflator!$M$10,"") | J81: =IF(ISNUMBER(J51),J51*fx_deflator!$J$11*fx_deflator!$M$11,"") | K81: =IF(ISNUMBER(K51),K51*fx_deflator!$J$12*fx_deflator!$M$12,"") | L81: =IF(ISNUMBER(L51),L51*fx_deflator!$J$13*fx_deflator!$M$13,"") | M81: =IF(ISNUMBER(M51),M51*fx_deflator!$J$14*fx_deflator!$M$14,"") | N81: =IF(ISNUMBER(N51),N51*fx_deflator!$J$15*fx_deflator!$M$15,"") | O81: =IF(ISNUMBER(O51),O51*fx_deflator!$J$16*fx_deflator!$M$16,"") | P81: =IF(ISNUMBER(P51),P51*fx_deflator!$J$17*fx_deflator!$M$17,"") | Q81: =IF(ISNUMBER(Q51),Q51*fx_deflator!$J$18*fx_deflator!$M$18,"") | R81: =IF(ISNUMBER(R51),R51*fx_deflator!$J$19*fx_deflator!$M$19,"") | S81: =IF(ISNUMBER(S51),S51*fx_deflator!$J$20*fx_deflator!$M$20,"")
A82: DE | B82: DE LARGE E2 band low — real 2025 USD/MWh | C82: USD | D82: =IF(ISNUMBER(D52),D52*fx_deflator!$J$5*fx_deflator!$M$5,"") | E82: =IF(ISNUMBER(E52),E52*fx_deflator!$J$6*fx_deflator!$M$6,"") | F82: =IF(ISNUMBER(F52),F52*fx_deflator!$J$7*fx_deflator!$M$7,"") | G82: =IF(ISNUMBER(G52),G52*fx_deflator!$J$8*fx_deflator!$M$8,"") | H82: =IF(ISNUMBER(H52),H52*fx_deflator!$J$9*fx_deflator!$M$9,"") | I82: =IF(ISNUMBER(I52),I52*fx_deflator!$J$10*fx_deflator!$M$10,"") | J82: =IF(ISNUMBER(J52),J52*fx_deflator!$J$11*fx_deflator!$M$11,"") | K82: =IF(ISNUMBER(K52),K52*fx_deflator!$J$12*fx_deflator!$M$12,"") | L82: =IF(ISNUMBER(L52),L52*fx_deflator!$J$13*fx_deflator!$M$13,"") | M82: =IF(ISNUMBER(M52),M52*fx_deflator!$J$14*fx_deflator!$M$14,"") | N82: =IF(ISNUMBER(N52),N52*fx_deflator!$J$15*fx_deflator!$M$15,"") | O82: =IF(ISNUMBER(O52),O52*fx_deflator!$J$16*fx_deflator!$M$16,"") | P82: =IF(ISNUMBER(P52),P52*fx_deflator!$J$17*fx_deflator!$M$17,"") | Q82: =IF(ISNUMBER(Q52),Q52*fx_deflator!$J$18*fx_deflator!$M$18,"") | R82: =IF(ISNUMBER(R52),R52*fx_deflator!$J$19*fx_deflator!$M$19,"") | S82: =IF(ISNUMBER(S52),S52*fx_deflator!$J$20*fx_deflator!$M$20,"")
A83: DE | B83: DE LARGE E2 band high — real 2025 USD/MWh | C83: USD | D83: =IF(ISNUMBER(D53),D53*fx_deflator!$J$5*fx_deflator!$M$5,"") | E83: =IF(ISNUMBER(E53),E53*fx_deflator!$J$6*fx_deflator!$M$6,"") | F83: =IF(ISNUMBER(F53),F53*fx_deflator!$J$7*fx_deflator!$M$7,"") | G83: =IF(ISNUMBER(G53),G53*fx_deflator!$J$8*fx_deflator!$M$8,"") | H83: =IF(ISNUMBER(H53),H53*fx_deflator!$J$9*fx_deflator!$M$9,"") | I83: =IF(ISNUMBER(I53),I53*fx_deflator!$J$10*fx_deflator!$M$10,"") | J83: =IF(ISNUMBER(J53),J53*fx_deflator!$J$11*fx_deflator!$M$11,"") | K83: =IF(ISNUMBER(K53),K53*fx_deflator!$J$12*fx_deflator!$M$12,"") | L83: =IF(ISNUMBER(L53),L53*fx_deflator!$J$13*fx_deflator!$M$13,"") | M83: =IF(ISNUMBER(M53),M53*fx_deflator!$J$14*fx_deflator!$M$14,"") | N83: =IF(ISNUMBER(N53),N53*fx_deflator!$J$15*fx_deflator!$M$15,"") | O83: =IF(ISNUMBER(O53),O53*fx_deflator!$J$16*fx_deflator!$M$16,"") | P83: =IF(ISNUMBER(P53),P53*fx_deflator!$J$17*fx_deflator!$M$17,"") | Q83: =IF(ISNUMBER(Q53),Q53*fx_deflator!$J$18*fx_deflator!$M$18,"") | R83: =IF(ISNUMBER(R53),R53*fx_deflator!$J$19*fx_deflator!$M$19,"") | S83: =IF(ISNUMBER(S53),S53*fx_deflator!$J$20*fx_deflator!$M$20,"")
A84: DE | B84: DE MEDIUM E1 — real 2025 USD/MWh | C84: USD | D84: =IF(ISNUMBER(D61),D61*fx_deflator!$J$5*fx_deflator!$M$5,"") | E84: =IF(ISNUMBER(E61),E61*fx_deflator!$J$6*fx_deflator!$M$6,"") | F84: =IF(ISNUMBER(F61),F61*fx_deflator!$J$7*fx_deflator!$M$7,"") | G84: =IF(ISNUMBER(G61),G61*fx_deflator!$J$8*fx_deflator!$M$8,"") | H84: =IF(ISNUMBER(H61),H61*fx_deflator!$J$9*fx_deflator!$M$9,"") | I84: =IF(ISNUMBER(I61),I61*fx_deflator!$J$10*fx_deflator!$M$10,"") | J84: =IF(ISNUMBER(J61),J61*fx_deflator!$J$11*fx_deflator!$M$11,"") | K84: =IF(ISNUMBER(K61),K61*fx_deflator!$J$12*fx_deflator!$M$12,"") | L84: =IF(ISNUMBER(L61),L61*fx_deflator!$J$13*fx_deflator!$M$13,"") | M84: =IF(ISNUMBER(M61),M61*fx_deflator!$J$14*fx_deflator!$M$14,"") | N84: =IF(ISNUMBER(N61),N61*fx_deflator!$J$15*fx_deflator!$M$15,"") | O84: =IF(ISNUMBER(O61),O61*fx_deflator!$J$16*fx_deflator!$M$16,"") | P84: =IF(ISNUMBER(P61),P61*fx_deflator!$J$17*fx_deflator!$M$17,"") | Q84: =IF(ISNUMBER(Q61),Q61*fx_deflator!$J$18*fx_deflator!$M$18,"") | R84: =IF(ISNUMBER(R61),R61*fx_deflator!$J$19*fx_deflator!$M$19,"") | S84: =IF(ISNUMBER(S61),S61*fx_deflator!$J$20*fx_deflator!$M$20,"")
A85: DE | B85: DE MEDIUM E2 — real 2025 USD/MWh | C85: USD | D85: =IF(ISNUMBER(D64),D64*fx_deflator!$J$5*fx_deflator!$M$5,"") | E85: =IF(ISNUMBER(E64),E64*fx_deflator!$J$6*fx_deflator!$M$6,"") | F85: =IF(ISNUMBER(F64),F64*fx_deflator!$J$7*fx_deflator!$M$7,"") | G85: =IF(ISNUMBER(G64),G64*fx_deflator!$J$8*fx_deflator!$M$8,"") | H85: =IF(ISNUMBER(H64),H64*fx_deflator!$J$9*fx_deflator!$M$9,"") | I85: =IF(ISNUMBER(I64),I64*fx_deflator!$J$10*fx_deflator!$M$10,"") | J85: =IF(ISNUMBER(J64),J64*fx_deflator!$J$11*fx_deflator!$M$11,"") | K85: =IF(ISNUMBER(K64),K64*fx_deflator!$J$12*fx_deflator!$M$12,"") | L85: =IF(ISNUMBER(L64),L64*fx_deflator!$J$13*fx_deflator!$M$13,"") | M85: =IF(ISNUMBER(M64),M64*fx_deflator!$J$14*fx_deflator!$M$14,"") | N85: =IF(ISNUMBER(N64),N64*fx_deflator!$J$15*fx_deflator!$M$15,"") | O85: =IF(ISNUMBER(O64),O64*fx_deflator!$J$16*fx_deflator!$M$16,"") | P85: =IF(ISNUMBER(P64),P64*fx_deflator!$J$17*fx_deflator!$M$17,"") | Q85: =IF(ISNUMBER(Q64),Q64*fx_deflator!$J$18*fx_deflator!$M$18,"") | R85: =IF(ISNUMBER(R64),R64*fx_deflator!$J$19*fx_deflator!$M$19,"") | S85: =IF(ISNUMBER(S64),S64*fx_deflator!$J$20*fx_deflator!$M$20,"")
A86: DE | B86: DE OBSERVED Eurostat IF — real 2025 USD/MWh | C86: USD | D86: =IF(ISNUMBER(D54),D54*fx_deflator!$J$5*fx_deflator!$M$5,"") | E86: =IF(ISNUMBER(E54),E54*fx_deflator!$J$6*fx_deflator!$M$6,"") | F86: =IF(ISNUMBER(F54),F54*fx_deflator!$J$7*fx_deflator!$M$7,"") | G86: =IF(ISNUMBER(G54),G54*fx_deflator!$J$8*fx_deflator!$M$8,"") | H86: =IF(ISNUMBER(H54),H54*fx_deflator!$J$9*fx_deflator!$M$9,"") | I86: =IF(ISNUMBER(I54),I54*fx_deflator!$J$10*fx_deflator!$M$10,"") | J86: =IF(ISNUMBER(J54),J54*fx_deflator!$J$11*fx_deflator!$M$11,"") | K86: =IF(ISNUMBER(K54),K54*fx_deflator!$J$12*fx_deflator!$M$12,"") | L86: =IF(ISNUMBER(L54),L54*fx_deflator!$J$13*fx_deflator!$M$13,"") | M86: =IF(ISNUMBER(M54),M54*fx_deflator!$J$14*fx_deflator!$M$14,"") | N86: =IF(ISNUMBER(N54),N54*fx_deflator!$J$15*fx_deflator!$M$15,"") | O86: =IF(ISNUMBER(O54),O54*fx_deflator!$J$16*fx_deflator!$M$16,"") | P86: =IF(ISNUMBER(P54),P54*fx_deflator!$J$17*fx_deflator!$M$17,"") | Q86: =IF(ISNUMBER(Q54),Q54*fx_deflator!$J$18*fx_deflator!$M$18,"") | R86: =IF(ISNUMBER(R54),R54*fx_deflator!$J$19*fx_deflator!$M$19,"") | S86: =IF(ISNUMBER(S54),S54*fx_deflator!$J$20*fx_deflator!$M$20,"")
A87: DE | B87: DE OBSERVED Eurostat IG — real 2025 USD/MWh | C87: USD | D87: =IF(ISNUMBER(D55),D55*fx_deflator!$J$5*fx_deflator!$M$5,"") | E87: =IF(ISNUMBER(E55),E55*fx_deflator!$J$6*fx_deflator!$M$6,"") | F87: =IF(ISNUMBER(F55),F55*fx_deflator!$J$7*fx_deflator!$M$7,"") | G87: =IF(ISNUMBER(G55),G55*fx_deflator!$J$8*fx_deflator!$M$8,"") | H87: =IF(ISNUMBER(H55),H55*fx_deflator!$J$9*fx_deflator!$M$9,"") | I87: =IF(ISNUMBER(I55),I55*fx_deflator!$J$10*fx_deflator!$M$10,"") | J87: =IF(ISNUMBER(J55),J55*fx_deflator!$J$11*fx_deflator!$M$11,"") | K87: =IF(ISNUMBER(K55),K55*fx_deflator!$J$12*fx_deflator!$M$12,"") | L87: =IF(ISNUMBER(L55),L55*fx_deflator!$J$13*fx_deflator!$M$13,"") | M87: =IF(ISNUMBER(M55),M55*fx_deflator!$J$14*fx_deflator!$M$14,"") | N87: =IF(ISNUMBER(N55),N55*fx_deflator!$J$15*fx_deflator!$M$15,"") | O87: =IF(ISNUMBER(O55),O55*fx_deflator!$J$16*fx_deflator!$M$16,"") | P87: =IF(ISNUMBER(P55),P55*fx_deflator!$J$17*fx_deflator!$M$17,"") | Q87: =IF(ISNUMBER(Q55),Q55*fx_deflator!$J$18*fx_deflator!$M$18,"") | R87: =IF(ISNUMBER(R55),R55*fx_deflator!$J$19*fx_deflator!$M$19,"") | S87: =IF(ISNUMBER(S55),S55*fx_deflator!$J$20*fx_deflator!$M$20,"")
A88: DE | B88: DE OBSERVED Eurostat ID — real 2025 USD/MWh | C88: USD | D88: =IF(ISNUMBER(D65),D65*fx_deflator!$J$5*fx_deflator!$M$5,"") | E88: =IF(ISNUMBER(E65),E65*fx_deflator!$J$6*fx_deflator!$M$6,"") | F88: =IF(ISNUMBER(F65),F65*fx_deflator!$J$7*fx_deflator!$M$7,"") | G88: =IF(ISNUMBER(G65),G65*fx_deflator!$J$8*fx_deflator!$M$8,"") | H88: =IF(ISNUMBER(H65),H65*fx_deflator!$J$9*fx_deflator!$M$9,"") | I88: =IF(ISNUMBER(I65),I65*fx_deflator!$J$10*fx_deflator!$M$10,"") | J88: =IF(ISNUMBER(J65),J65*fx_deflator!$J$11*fx_deflator!$M$11,"") | K88: =IF(ISNUMBER(K65),K65*fx_deflator!$J$12*fx_deflator!$M$12,"") | L88: =IF(ISNUMBER(L65),L65*fx_deflator!$J$13*fx_deflator!$M$13,"") | M88: =IF(ISNUMBER(M65),M65*fx_deflator!$J$14*fx_deflator!$M$14,"") | N88: =IF(ISNUMBER(N65),N65*fx_deflator!$J$15*fx_deflator!$M$15,"") | O88: =IF(ISNUMBER(O65),O65*fx_deflator!$J$16*fx_deflator!$M$16,"") | P88: =IF(ISNUMBER(P65),P65*fx_deflator!$J$17*fx_deflator!$M$17,"") | Q88: =IF(ISNUMBER(Q65),Q65*fx_deflator!$J$18*fx_deflator!$M$18,"") | R88: =IF(ISNUMBER(R65),R65*fx_deflator!$J$19*fx_deflator!$M$19,"") | S88: =IF(ISNUMBER(S65),S65*fx_deflator!$J$20*fx_deflator!$M$20,"")
A89: CN | B89: CN LARGE (E1=E2) — real 2025 USD/MWh (incl VAT as published — Q84) | C89: USD | D89: =IF(ISNUMBER(D67),D67/fx_deflator!$K$5*fx_deflator!$M$5,"") | E89: =IF(ISNUMBER(E67),E67/fx_deflator!$K$6*fx_deflator!$M$6,"") | F89: =IF(ISNUMBER(F67),F67/fx_deflator!$K$7*fx_deflator!$M$7,"") | G89: =IF(ISNUMBER(G67),G67/fx_deflator!$K$8*fx_deflator!$M$8,"") | H89: =IF(ISNUMBER(H67),H67/fx_deflator!$K$9*fx_deflator!$M$9,"") | I89: =IF(ISNUMBER(I67),I67/fx_deflator!$K$10*fx_deflator!$M$10,"") | J89: =IF(ISNUMBER(J67),J67/fx_deflator!$K$11*fx_deflator!$M$11,"") | K89: =IF(ISNUMBER(K67),K67/fx_deflator!$K$12*fx_deflator!$M$12,"") | L89: =IF(ISNUMBER(L67),L67/fx_deflator!$K$13*fx_deflator!$M$13,"") | M89: =IF(ISNUMBER(M67),M67/fx_deflator!$K$14*fx_deflator!$M$14,"") | N89: =IF(ISNUMBER(N67),N67/fx_deflator!$K$15*fx_deflator!$M$15,"") | O89: =IF(ISNUMBER(O67),O67/fx_deflator!$K$16*fx_deflator!$M$16,"") | P89: =IF(ISNUMBER(P67),P67/fx_deflator!$K$17*fx_deflator!$M$17,"") | Q89: =IF(ISNUMBER(Q67),Q67/fx_deflator!$K$18*fx_deflator!$M$18,"") | R89: =IF(ISNUMBER(R67),R67/fx_deflator!$K$19*fx_deflator!$M$19,"") | S89: =IF(ISNUMBER(S67),S67/fx_deflator!$K$20*fx_deflator!$M$20,"")
A90: CN | B90: CN MEDIUM (E1=E2) — real 2025 USD/MWh (incl VAT as published — Q84) | C90: USD | D90: =IF(ISNUMBER(D70),D70/fx_deflator!$K$5*fx_deflator!$M$5,"") | E90: =IF(ISNUMBER(E70),E70/fx_deflator!$K$6*fx_deflator!$M$6,"") | F90: =IF(ISNUMBER(F70),F70/fx_deflator!$K$7*fx_deflator!$M$7,"") | G90: =IF(ISNUMBER(G70),G70/fx_deflator!$K$8*fx_deflator!$M$8,"") | H90: =IF(ISNUMBER(H70),H70/fx_deflator!$K$9*fx_deflator!$M$9,"") | I90: =IF(ISNUMBER(I70),I70/fx_deflator!$K$10*fx_deflator!$M$10,"") | J90: =IF(ISNUMBER(J70),J70/fx_deflator!$K$11*fx_deflator!$M$11,"") | K90: =IF(ISNUMBER(K70),K70/fx_deflator!$K$12*fx_deflator!$M$12,"") | L90: =IF(ISNUMBER(L70),L70/fx_deflator!$K$13*fx_deflator!$M$13,"") | M90: =IF(ISNUMBER(M70),M70/fx_deflator!$K$14*fx_deflator!$M$14,"") | N90: =IF(ISNUMBER(N70),N70/fx_deflator!$K$15*fx_deflator!$M$15,"") | O90: =IF(ISNUMBER(O70),O70/fx_deflator!$K$16*fx_deflator!$M$16,"") | P90: =IF(ISNUMBER(P70),P70/fx_deflator!$K$17*fx_deflator!$M$17,"") | Q90: =IF(ISNUMBER(Q70),Q70/fx_deflator!$K$18*fx_deflator!$M$18,"") | R90: =IF(ISNUMBER(R70),R70/fx_deflator!$K$19*fx_deflator!$M$19,"") | S90: =IF(ISNUMBER(S70),S70/fx_deflator!$K$20*fx_deflator!$M$20,"")
A91: VALIDATION GATE (house rule 3): observed band average must fall between E2 and E1. Run in nominal local currency; UK compared EXCL CCL (QEP 3.4.1 basis). Build-up excludes supply margin → observed near/above E1 flags margin+gaps, not archetype failure — investigate, never tune (results → qc).
A92: UK | B92: GATE UK large: QEP XL ∈ [E2, E1] (provisional pre-2024: E1 understated by FiT/CM/BSUoS gaps) [D71: both sides now incl CCL; E2 carries none] | C92: gate | D92: =IF(OR(NOT(ISNUMBER(D20)),NOT(ISNUMBER(D15)),NOT(ISNUMBER(D19))),"n/a",IF(AND(D20>=D19,D20<=D15),"PASS","FAIL")) | E92: =IF(OR(NOT(ISNUMBER(E20)),NOT(ISNUMBER(E15)),NOT(ISNUMBER(E19))),"n/a",IF(AND(E20>=E19,E20<=E15),"PASS","FAIL")) | F92: =IF(OR(NOT(ISNUMBER(F20)),NOT(ISNUMBER(F15)),NOT(ISNUMBER(F19))),"n/a",IF(AND(F20>=F19,F20<=F15),"PASS","FAIL")) | G92: =IF(OR(NOT(ISNUMBER(G20)),NOT(ISNUMBER(G15)),NOT(ISNUMBER(G19))),"n/a",IF(AND(G20>=G19,G20<=G15),"PASS","FAIL")) | H92: =IF(OR(NOT(ISNUMBER(H20)),NOT(ISNUMBER(H15)),NOT(ISNUMBER(H19))),"n/a",IF(AND(H20>=H19,H20<=H15),"PASS","FAIL")) | I92: =IF(OR(NOT(ISNUMBER(I20)),NOT(ISNUMBER(I15)),NOT(ISNUMBER(I19))),"n/a",IF(AND(I20>=I19,I20<=I15),"PASS","FAIL")) | J92: =IF(OR(NOT(ISNUMBER(J20)),NOT(ISNUMBER(J15)),NOT(ISNUMBER(J19))),"n/a",IF(AND(J20>=J19,J20<=J15),"PASS","FAIL")) | K92: =IF(OR(NOT(ISNUMBER(K20)),NOT(ISNUMBER(K15)),NOT(ISNUMBER(K19))),"n/a",IF(AND(K20>=K19,K20<=K15),"PASS","FAIL")) | ... S92: =IF(OR(NOT(ISNUMBER(S20)),NOT(ISNUMBER(S15)),NOT(ISNUMBER(S19))),"n/a",IF(AND(S20>=S19,S20<=S15),"PASS","FAIL"))
A93: UK | B93: GATE UK medium: QEP Large ∈ [E2, E1] (2017+) [D71: both sides now incl CCL; E2 carries none] | C93: gate | D93: =IF(OR(NOT(ISNUMBER(D30)),NOT(ISNUMBER(D28)),NOT(ISNUMBER(D29))),"n/a",IF(AND(D30>=D29,D30<=D28),"PASS","FAIL")) | E93: =IF(OR(NOT(ISNUMBER(E30)),NOT(ISNUMBER(E28)),NOT(ISNUMBER(E29))),"n/a",IF(AND(E30>=E29,E30<=E28),"PASS","FAIL")) | F93: =IF(OR(NOT(ISNUMBER(F30)),NOT(ISNUMBER(F28)),NOT(ISNUMBER(F29))),"n/a",IF(AND(F30>=F29,F30<=F28),"PASS","FAIL")) | G93: =IF(OR(NOT(ISNUMBER(G30)),NOT(ISNUMBER(G28)),NOT(ISNUMBER(G29))),"n/a",IF(AND(G30>=G29,G30<=G28),"PASS","FAIL")) | H93: =IF(OR(NOT(ISNUMBER(H30)),NOT(ISNUMBER(H28)),NOT(ISNUMBER(H29))),"n/a",IF(AND(H30>=H29,H30<=H28),"PASS","FAIL")) | I93: =IF(OR(NOT(ISNUMBER(I30)),NOT(ISNUMBER(I28)),NOT(ISNUMBER(I29))),"n/a",IF(AND(I30>=I29,I30<=I28),"PASS","FAIL")) | J93: =IF(OR(NOT(ISNUMBER(J30)),NOT(ISNUMBER(J28)),NOT(ISNUMBER(J29))),"n/a",IF(AND(J30>=J29,J30<=J28),"PASS","FAIL")) | K93: =IF(OR(NOT(ISNUMBER(K30)),NOT(ISNUMBER(K28)),NOT(ISNUMBER(K29))),"n/a",IF(AND(K30>=K29,K30<=K28),"PASS","FAIL")) | ... S93: =IF(OR(NOT(ISNUMBER(S30)),NOT(ISNUMBER(S28)),NOT(ISNUMBER(S29))),"n/a",IF(AND(S30>=S29,S30<=S28),"PASS","FAIL"))
A94: DE | B94: GATE DE large: Eurostat IF ∈ [E2 central, E1] | C94: gate | D94: =IF(OR(NOT(ISNUMBER(D54)),NOT(ISNUMBER(D41)),NOT(ISNUMBER(D51))),"n/a",IF(AND(D54>=(D51),D54<=(D41)),"PASS","FAIL")) | E94: =IF(OR(NOT(ISNUMBER(E54)),NOT(ISNUMBER(E41)),NOT(ISNUMBER(E51))),"n/a",IF(AND(E54>=(E51),E54<=(E41)),"PASS","FAIL")) | F94: =IF(OR(NOT(ISNUMBER(F54)),NOT(ISNUMBER(F41)),NOT(ISNUMBER(F51))),"n/a",IF(AND(F54>=(F51),F54<=(F41)),"PASS","FAIL")) | G94: =IF(OR(NOT(ISNUMBER(G54)),NOT(ISNUMBER(G41)),NOT(ISNUMBER(G51))),"n/a",IF(AND(G54>=(G51),G54<=(G41)),"PASS","FAIL")) | H94: =IF(OR(NOT(ISNUMBER(H54)),NOT(ISNUMBER(H41)),NOT(ISNUMBER(H51))),"n/a",IF(AND(H54>=(H51),H54<=(H41)),"PASS","FAIL")) | I94: =IF(OR(NOT(ISNUMBER(I54)),NOT(ISNUMBER(I41)),NOT(ISNUMBER(I51))),"n/a",IF(AND(I54>=(I51),I54<=(I41)),"PASS","FAIL")) | J94: =IF(OR(NOT(ISNUMBER(J54)),NOT(ISNUMBER(J41)),NOT(ISNUMBER(J51))),"n/a",IF(AND(J54>=(J51),J54<=(J41)),"PASS","FAIL")) | K94: =IF(OR(NOT(ISNUMBER(K54)),NOT(ISNUMBER(K41)),NOT(ISNUMBER(K51))),"n/a",IF(AND(K54>=(K51),K54<=(K41)),"PASS","FAIL")) | ... S94: =IF(OR(NOT(ISNUMBER(S54)),NOT(ISNUMBER(S41)),NOT(ISNUMBER(S51))),"n/a",IF(AND(S54>=(S51),S54<=(S41)),"PASS","FAIL"))
A95: DE | B95: GATE DE medium: Eurostat ID ∈ [E2, E1] | C95: gate | D95: =IF(OR(NOT(ISNUMBER(D65)),NOT(ISNUMBER(D61)),NOT(ISNUMBER(D64))),"n/a",IF(AND(D65>=(D64),D65<=(D61)),"PASS","FAIL")) | E95: =IF(OR(NOT(ISNUMBER(E65)),NOT(ISNUMBER(E61)),NOT(ISNUMBER(E64))),"n/a",IF(AND(E65>=(E64),E65<=(E61)),"PASS","FAIL")) | F95: =IF(OR(NOT(ISNUMBER(F65)),NOT(ISNUMBER(F61)),NOT(ISNUMBER(F64))),"n/a",IF(AND(F65>=(F64),F65<=(F61)),"PASS","FAIL")) | G95: =IF(OR(NOT(ISNUMBER(G65)),NOT(ISNUMBER(G61)),NOT(ISNUMBER(G64))),"n/a",IF(AND(G65>=(G64),G65<=(G61)),"PASS","FAIL")) | H95: =IF(OR(NOT(ISNUMBER(H65)),NOT(ISNUMBER(H61)),NOT(ISNUMBER(H64))),"n/a",IF(AND(H65>=(H64),H65<=(H61)),"PASS","FAIL")) | I95: =IF(OR(NOT(ISNUMBER(I65)),NOT(ISNUMBER(I61)),NOT(ISNUMBER(I64))),"n/a",IF(AND(I65>=(I64),I65<=(I61)),"PASS","FAIL")) | J95: =IF(OR(NOT(ISNUMBER(J65)),NOT(ISNUMBER(J61)),NOT(ISNUMBER(J64))),"n/a",IF(AND(J65>=(J64),J65<=(J61)),"PASS","FAIL")) | K95: =IF(OR(NOT(ISNUMBER(K65)),NOT(ISNUMBER(K61)),NOT(ISNUMBER(K64))),"n/a",IF(AND(K65>=(K64),K65<=(K61)),"PASS","FAIL")) | ... S95: =IF(OR(NOT(ISNUMBER(S65)),NOT(ISNUMBER(S61)),NOT(ISNUMBER(S64))),"n/a",IF(AND(S65>=(S64),S65<=(S61)),"PASS","FAIL"))
A96: SENSITIVITIES (mandatory) — large archetype. (1) Load factor at assumptions!B56 = 6,500h: below the German 7,000h §19 threshold → DE E2 network = FULL tariff (the threshold is the exhibit). (2) Hedging: day-ahead-indexed vs rolling year-ahead. CN market annual averages have no hedging analogue (noted).
A97: UK | B97: UK LARGE E1 @6,500h (triad-era TNUoS re-scaled; TCR residual per-site unchanged) | C97: sens | D97: =D15+stage4_uk!D25*1000*(1/assumptions!$B$56-1/assumptions!$B$7) | E97: =E15+stage4_uk!E25*1000*(1/assumptions!$B$56-1/assumptions!$B$7) | F97: =F15+stage4_uk!F25*1000*(1/assumptions!$B$56-1/assumptions!$B$7) | G97: =G15+stage4_uk!G25*1000*(1/assumptions!$B$56-1/assumptions!$B$7) | H97: =H15+stage4_uk!H25*1000*(1/assumptions!$B$56-1/assumptions!$B$7) | I97: =I15+stage4_uk!I25*1000*(1/assumptions!$B$56-1/assumptions!$B$7) | J97: =J15+stage4_uk!J25*1000*(1/assumptions!$B$56-1/assumptions!$B$7) | K97: =K15+stage4_uk!K25*1000*(1/assumptions!$B$56-1/assumptions!$B$7) | ... P97: =P15+stage4_uk!P25*1000*(1/assumptions!$B$56-1/assumptions!$B$7) | Q97: =Q15 | R97: =R15 | S97: =S15 | T97: =T15 | U97: TCR-era: fixed per-site residual → per-MWh unchanged at constant consumption (say so in ch.3).
A98: DE | B98: DE LARGE E1 @6,500h | C98: sens | D98: =IF(ISNUMBER(D41),D41+stage4_de!D11*1000*(1/assumptions!$B$56-1/assumptions!$B$7),"") | E98: =IF(ISNUMBER(E41),E41+stage4_de!E11*1000*(1/assumptions!$B$56-1/assumptions!$B$7),"") | F98: =IF(ISNUMBER(F41),F41+stage4_de!F11*1000*(1/assumptions!$B$56-1/assumptions!$B$7),"") | G98: =IF(ISNUMBER(G41),G41+stage4_de!G11*1000*(1/assumptions!$B$56-1/assumptions!$B$7),"") | H98: =IF(ISNUMBER(H41),H41+stage4_de!H11*1000*(1/assumptions!$B$56-1/assumptions!$B$7),"") | I98: =IF(ISNUMBER(I41),I41+stage4_de!I11*1000*(1/assumptions!$B$56-1/assumptions!$B$7),"") | J98: =IF(ISNUMBER(J41),J41+stage4_de!J11*1000*(1/assumptions!$B$56-1/assumptions!$B$7),"") | K98: =IF(ISNUMBER(K41),K41+stage4_de!K11*1000*(1/assumptions!$B$56-1/assumptions!$B$7),"") | ... T98: =IF(ISNUMBER(T41),T41+stage4_de!T11*1000*(1/assumptions!$B$56-1/assumptions!$B$7),"")
A99: DE | B99: DE LARGE E2 @6,500h — LOSES §19 (below 7,000h): network at full tariff | C99: sens | D99: =IF(ISNUMBER(D51),D51-D42+(stage4_de!D11*1000/assumptions!$B$56+stage4_de!D12*10),"") | E99: =IF(ISNUMBER(E51),E51-E42+(stage4_de!E11*1000/assumptions!$B$56+stage4_de!E12*10),"") | F99: =IF(ISNUMBER(F51),F51-F42+(stage4_de!F11*1000/assumptions!$B$56+stage4_de!F12*10),"") | G99: =IF(ISNUMBER(G51),G51-G42+(stage4_de!G11*1000/assumptions!$B$56+stage4_de!G12*10),"") | H99: =IF(ISNUMBER(H51),H51-H42+(stage4_de!H11*1000/assumptions!$B$56+stage4_de!H12*10),"") | I99: =IF(ISNUMBER(I51),I51-I42+(stage4_de!I11*1000/assumptions!$B$56+stage4_de!I12*10),"") | J99: =IF(ISNUMBER(J51),J51-J42+(stage4_de!J11*1000/assumptions!$B$56+stage4_de!J12*10),"") | K99: =IF(ISNUMBER(K51),K51-K42+(stage4_de!K11*1000/assumptions!$B$56+stage4_de!K12*10),"") | ... T99: =IF(ISNUMBER(T51),T51-T42+(stage4_de!T11*1000/assumptions!$B$56+stage4_de!T12*10),"") | U99: The 7,000h eligibility cliff, charted explicitly (project instructions).
A100: CN | B100: CN LARGE @6,500h (demand-charge terms re-scaled; renormalisation identical) | C100: sens | F100: =stage4_cn!F100 | G100: =stage4_cn!G100 | H100: =stage4_cn!H100 | I100: =stage4_cn!I100 | J100: =stage4_cn!J100 | K100: =stage4_cn!K100 | L100: =stage4_cn!L100 | M100: =stage4_cn!M100 | ... O100: =stage4_cn!O100 | P100: =stage4_cn!P101 | Q100: =stage4_cn!Q101 | R100: =stage4_cn!R101 | S100: =stage4_cn!S101 | T100: =stage4_cn!T101 | U100: 2020 COVID rebate not re-scaled (2nd-order).
A101: UK | B101: UK LARGE E1, day-ahead-indexed (hedging sensitivity; identical to headline pre-2022 by construction of D22 proxy) | C101: sens | D101: =D15-D6+stage4_uk!D7+(stage4_uk!D7-D6)*(assumptions!$B$79*(1+assumptions!$B$78)-1) | E101: =E15-E6+stage4_uk!E7+(stage4_uk!E7-E6)*(assumptions!$B$79*(1+assumptions!$B$78)-1) | F101: =F15-F6+stage4_uk!F7+(stage4_uk!F7-F6)*(assumptions!$B$79*(1+assumptions!$B$78)-1) | G101: =G15-G6+stage4_uk!G7+(stage4_uk!G7-G6)*(assumptions!$B$79*(1+assumptions!$B$78)-1) | H101: =H15-H6+stage4_uk!H7+(stage4_uk!H7-H6)*(assumptions!$B$79*(1+assumptions!$B$78)-1) | I101: =I15-I6+stage4_uk!I7+(stage4_uk!I7-I6)*(assumptions!$B$79*(1+assumptions!$B$78)-1) | J101: =J15-J6+stage4_uk!J7+(stage4_uk!J7-J6)*(assumptions!$B$79*(1+assumptions!$B$78)-1) | K101: =K15-K6+stage4_uk!K7+(stage4_uk!K7-K6)*(assumptions!$B$79*(1+assumptions!$B$78)-1) | ... T101: =T15-T6+stage4_uk!T7+(stage4_uk!T7-T6)*(assumptions!$B$79*(1+assumptions!$B$78)-1)
...

Sheet data_lineitems
A1: country | B1: year | C1: archetype | D1: exemption_case (E1/E2/observed) | E1: source_line_item | F1: economic_function (1 Commodity / 2 Gen capital via subsidy-capacity / 3 Network / 4 System services / 5 Taxes-levies / 6 Supply margin) | G1: institutional_bucket (wholesale/network/levies&taxes/supply) | H1: cost_incidence (i own bill / ii other users / iii taxpayer / iv unfunded) | I1: USD_per_MWh_real2025 | J1: source_ref | K1: table_page | L1: retrieval_date | M1: estimated_YN | N1: nominal_local_per_MWh | O1: local_unit | P1: notes
A2: Populated at stage 6 (2026-07-16). Rows 3-1567. Panel 2010-2025 (2026 excluded, D39/D6). MEMO/HATCH rows are excluded from bucket sums (function string prefix).
A3: UK | B3: 2010 | C3: large | D3: E1 | E3: Wholesale (rolling year-ahead baseload; DA proxy <=2021) | F3: 1 Commodity | G3: wholesale market | H3: i | I3: =IF(ISNUMBER(N3),N3*fx_deflator!$I$5*fx_deflator!$M$5,"") | J3: Ofgem data portal — DA baseload monthly avg (proxy <=2021, D22); Forward Delivery Contracts (D21) | K3: stage4_uk r7-9 | L3: 2026-07-15 | M3: Y | N3: =IF(ISNUMBER(timeseries!D6),timeseries!D6,"") | O3: GBP/MWh nominal | P3: identical E1/E2; embedded carbon memo inside this item
A4: UK | B4: 2010 | C4: large | D4: E1 | E4: TNUoS demand (zone 5; TCR banded residual from 2023) | F4: 3 Network | G4: transmission network charge | H4: i | I4: =IF(ISNUMBER(N4),N4*fx_deflator!$I$5*fx_deflator!$M$5,"") | J4: NESO TNUoS tariff documents (compendium doc 50736; Final TNUoS 2023/24-2026/27 Table 10) | K4: stage4_uk r25-27 | L4: 2026-07-15 | M4: Y | N4: =IF(ISNUMBER(timeseries!D7),timeseries!D7,"") | O4: GBP/MWh nominal
A5: UK | B5: 2010 | C5: large | D5: E1 | E5: BSUoS (demand-only from 04/2023) | F5: 4 System services & balancing | G5: balancing charge | H5: i | I5: =IF(ISNUMBER(N5),N5*fx_deflator!$I$5*fx_deflator!$M$5,"") | J5: NESO bsuos-fixed-tariffs + HH RF settlement files (own annual avg 2010-22) | K5: stage4_uk r28-30 | L5: 2026-07-15 | M5: Y | N5: =IF(ISNUMBER(timeseries!D8),timeseries!D8,"") | O5: GBP/MWh nominal
A6: UK | B6: 2010 | C6: large | D6: E1 | E6: AAHEDC | F6: 3 Network | G6: network levy (hydro benefit) | H6: ii (pays cross-subsidy to N Scotland consumers) | I6: =IF(ISNUMBER(N6),N6*fx_deflator!$I$5*fx_deflator!$M$5,"") | J6: NG/ESO AAHEDC charging statements & final tariff letters | K6: stage4_uk r31 | L6: 2026-07-15 | M6: N | N6: =IF(ISNUMBER(timeseries!D9),timeseries!D9,"") | O6: GBP/MWh nominal | P6: not in NCC base (conservative, unverified)
A7: UK | B7: 2010 | C7: large | D7: E1 | E7: RO (buy-out x obligation) | F7: 2 Gen capital recovery | G7: renewables levy | H7: i | I7: =IF(ISNUMBER(N7),N7*fx_deflator!$I$5*fx_deflator!$M$5,"") | J7: Ofgem RO guidance OFG1164 Table 1.1 (buy-out x obligation) | K7: stage4_uk r12-14 | L7: 2026-07-15 | M7: Y | N7: =IF(ISNUMBER(timeseries!D10),timeseries!D10,"") | O7: GBP/MWh nominal
A8: UK | B8: 2010 | C8: large | D8: E1 | E8: FiT levelisation | F8: 2 Gen capital recovery | G8: renewables levy | H8: i | I8: =IF(ISNUMBER(N8),N8*fx_deflator!$I$5*fx_deflator!$M$5,"") | J8: Ofgem FIT Annual Reports SY1-SY15; D27 for 2010-14 | K8: stage4_uk r20 | L8: 2026-07-15 | M8: Y | N8: =IF(ISNUMBER(timeseries!D12),timeseries!D12,"") | O8: GBP/MWh nominal | P8: 2025 unpublished (Q32) — row absent, gap stated
A9: UK | B9: 2010 | C9: large | D9: E1 | E9: CCL (main rate; CCA discount not modelled) | F9: 5 General taxation & levies | G9: climate levy (tax) | H9: i | I9: =IF(ISNUMBER(N9),N9*fx_deflator!$I$5*fx_deflator!$M$5,"") | J9: HMRC Environmental Taxes Bulletin, historical rates Table 1 | K9: stage4_uk r22 | L9: 2026-07-15 | M9: N | N9: =IF(ISNUMBER(timeseries!D14),timeseries!D14,"") | O9: GBP/MWh nominal
A10: UK | B10: 2011 | C10: large | D10: E1 | E10: Wholesale (rolling year-ahead baseload; DA proxy <=2021) | F10: 1 Commodity | G10: wholesale market | H10: i | I10: =IF(ISNUMBER(N10),N10*fx_deflator!$I$6*fx_deflator!$M$6,"") | J10: Ofgem data portal — DA baseload monthly avg (proxy <=2021, D22); Forward Delivery Contracts (D21) | K10: stage4_uk r7-9 | L10: 2026-07-15 | M10: Y | N10: =IF(ISNUMBER(timeseries!E6),timeseries!E6,"") | O10: GBP/MWh nominal | P10: identical E1/E2; embedded carbon memo inside this item
A11: UK | B11: 2011 | C11: large | D11: E1 | E11: TNUoS demand (zone 5; TCR banded residual from 2023) | F11: 3 Network | G11: transmission network charge | H11: i | I11: =IF(ISNUMBER(N11),N11*fx_deflator!$I$6*fx_deflator!$M$6,"") | J11: NESO TNUoS tariff documents (compendium doc 50736; Final TNUoS 2023/24-2026/27 Table 10) | K11: stage4_uk r25-27 | L11: 2026-07-15 | M11: Y | N11: =IF(ISNUMBER(timeseries!E7),timeseries!E7,"") | O11: GBP/MWh nominal
A12: UK | B12: 2011 | C12: large | D12: E1 | E12: BSUoS (demand-only from 04/2023) | F12: 4 System services & balancing | G12: balancing charge | H12: i | I12: =IF(ISNUMBER(N12),N12*fx_deflator!$I$6*fx_deflator!$M$6,"") | J12: NESO bsuos-fixed-tariffs + HH RF settlement files (own annual avg 2010-22) | K12: stage4_uk r28-30 | L12: 2026-07-15 | M12: Y | N12: =IF(ISNUMBER(timeseries!E8),timeseries!E8,"") | O12: GBP/MWh nominal
A13: UK | B13: 2011 | C13: large | D13: E1 | E13: AAHEDC | F13: 3 Network | G13: network levy (hydro benefit) | H13: ii (pays cross-subsidy to N Scotland consumers) | I13: =IF(ISNUMBER(N13),N13*fx_deflator!$I$6*fx_deflator!$M$6,"") | J13: NG/ESO AAHEDC charging statements & final tariff letters | K13: stage4_uk r31 | L13: 2026-07-15 | M13: N | N13: =IF(ISNUMBER(timeseries!E9),timeseries!E9,"") | O13: GBP/MWh nominal | P13: not in NCC base (conservative, unverified)
A14: UK | B14: 2011 | C14: large | D14: E1 | E14: RO (buy-out x obligation) | F14: 2 Gen capital recovery | G14: renewables levy | H14: i | I14: =IF(ISNUMBER(N14),N14*fx_deflator!$I$6*fx_deflator!$M$6,"") | J14: Ofgem RO guidance OFG1164 Table 1.1 (buy-out x obligation) | K14: stage4_uk r12-14 | L14: 2026-07-15 | M14: Y | N14: =IF(ISNUMBER(timeseries!E10),timeseries!E10,"") | O14: GBP/MWh nominal
A15: UK | B15: 2011 | C15: large | D15: E1 | E15: FiT levelisation | F15: 2 Gen capital recovery | G15: renewables levy | H15: i | I15: =IF(ISNUMBER(N15),N15*fx_deflator!$I$6*fx_deflator!$M$6,"") | J15: Ofgem FIT Annual Reports SY1-SY15; D27 for 2010-14 | K15: stage4_uk r20 | L15: 2026-07-15 | M15: Y | N15: =IF(ISNUMBER(timeseries!E12),timeseries!E12,"") | O15: GBP/MWh nominal | P15: 2025 unpublished (Q32) — row absent, gap stated
A16: UK | B16: 2011 | C16: large | D16: E1 | E16: CCL (main rate; CCA discount not modelled) | F16: 5 General taxation & levies | G16: climate levy (tax) | H16: i | I16: =IF(ISNUMBER(N16),N16*fx_deflator!$I$6*fx_deflator!$M$6,"") | J16: HMRC Environmental Taxes Bulletin, historical rates Table 1 | K16: stage4_uk r22 | L16: 2026-07-15 | M16: N | N16: =IF(ISNUMBER(timeseries!E14),timeseries!E14,"") | O16: GBP/MWh nominal
A17: UK | B17: 2012 | C17: large | D17: E1 | E17: Wholesale (rolling year-ahead baseload; DA proxy <=2021) | F17: 1 Commodity | G17: wholesale market | H17: i | I17: =IF(ISNUMBER(N17),N17*fx_deflator!$I$7*fx_deflator!$M$7,"") | J17: Ofgem data portal — DA baseload monthly avg (proxy <=2021, D22); Forward Delivery Contracts (D21) | K17: stage4_uk r7-9 | L17: 2026-07-15 | M17: Y | N17: =IF(ISNUMBER(timeseries!F6),timeseries!F6,"") | O17: GBP/MWh nominal | P17: identical E1/E2; embedded carbon memo inside this item
A18: UK | B18: 2012 | C18: large | D18: E1 | E18: TNUoS demand (zone 5; TCR banded residual from 2023) | F18: 3 Network | G18: transmission network charge | H18: i | I18: =IF(ISNUMBER(N18),N18*fx_deflator!$I$7*fx_deflator!$M$7,"") | J18: NESO TNUoS tariff documents (compendium doc 50736; Final TNUoS 2023/24-2026/27 Table 10) | K18: stage4_uk r25-27 | L18: 2026-07-15 | M18: Y | N18: =IF(ISNUMBER(timeseries!F7),timeseries!F7,"") | O18: GBP/MWh nominal
A19: UK | B19: 2012 | C19: large | D19: E1 | E19: BSUoS (demand-only from 04/2023) | F19: 4 System services & balancing | G19: balancing charge | H19: i | I19: =IF(ISNUMBER(N19),N19*fx_deflator!$I$7*fx_deflator!$M$7,"") | J19: NESO bsuos-fixed-tariffs + HH RF settlement files (own annual avg 2010-22) | K19: stage4_uk r28-30 | L19: 2026-07-15 | M19: Y | N19: =IF(ISNUMBER(timeseries!F8),timeseries!F8,"") | O19: GBP/MWh nominal
A20: UK | B20: 2012 | C20: large | D20: E1 | E20: AAHEDC | F20: 3 Network | G20: network levy (hydro benefit) | H20: ii (pays cross-subsidy to N Scotland consumers) | I20: =IF(ISNUMBER(N20),N20*fx_deflator!$I$7*fx_deflator!$M$7,"") | J20: NG/ESO AAHEDC charging statements & final tariff letters | K20: stage4_uk r31 | L20: 2026-07-15 | M20: N | N20: =IF(ISNUMBER(timeseries!F9),timeseries!F9,"") | O20: GBP/MWh nominal | P20: not in NCC base (conservative, unverified)
A21: UK | B21: 2012 | C21: large | D21: E1 | E21: RO (buy-out x obligation) | F21: 2 Gen capital recovery | G21: renewables levy | H21: i | I21: =IF(ISNUMBER(N21),N21*fx_deflator!$I$7*fx_deflator!$M$7,"") | J21: Ofgem RO guidance OFG1164 Table 1.1 (buy-out x obligation) | K21: stage4_uk r12-14 | L21: 2026-07-15 | M21: Y | N21: =IF(ISNUMBER(timeseries!F10),timeseries!F10,"") | O21: GBP/MWh nominal
A22: UK | B22: 2012 | C22: large | D22: E1 | E22: FiT levelisation | F22: 2 Gen capital recovery | G22: renewables levy | H22: i | I22: =IF(ISNUMBER(N22),N22*fx_deflator!$I$7*fx_deflator!$M$7,"") | J22: Ofgem FIT Annual Reports SY1-SY15; D27 for 2010-14 | K22: stage4_uk r20 | L22: 2026-07-15 | M22: Y | N22: =IF(ISNUMBER(timeseries!F12),timeseries!F12,"") | O22: GBP/MWh nominal | P22: 2025 unpublished (Q32) — row absent, gap stated
A23: UK | B23: 2012 | C23: large | D23: E1 | E23: CCL (main rate; CCA discount not modelled) | F23: 5 General taxation & levies | G23: climate levy (tax) | H23: i | I23: =IF(ISNUMBER(N23),N23*fx_deflator!$I$7*fx_deflator!$M$7,"") | J23: HMRC Environmental Taxes Bulletin, historical rates Table 1 | K23: stage4_uk r22 | L23: 2026-07-15 | M23: N | N23: =IF(ISNUMBER(timeseries!F14),timeseries!F14,"") | O23: GBP/MWh nominal
A24: UK | B24: 2013 | C24: large | D24: E1 | E24: Wholesale (rolling year-ahead baseload; DA proxy <=2021) | F24: 1 Commodity | G24: wholesale market | H24: i | I24: =IF(ISNUMBER(N24),N24*fx_deflator!$I$8*fx_deflator!$M$8,"") | J24: Ofgem data portal — DA baseload monthly avg (proxy <=2021, D22); Forward Delivery Contracts (D21) | K24: stage4_uk r7-9 | L24: 2026-07-15 | M24: Y | N24: =IF(ISNUMBER(timeseries!G6),timeseries!G6,"") | O24: GBP/MWh nominal | P24: identical E1/E2; embedded carbon memo inside this item
A25: UK | B25: 2013 | C25: large | D25: E1 | E25: TNUoS demand (zone 5; TCR banded residual from 2023) | F25: 3 Network | G25: transmission network charge | H25: i | I25: =IF(ISNUMBER(N25),N25*fx_deflator!$I$8*fx_deflator!$M$8,"") | J25: NESO TNUoS tariff documents (compendium doc 50736; Final TNUoS 2023/24-2026/27 Table 10) | K25: stage4_uk r25-27 | L25: 2026-07-15 | M25: Y | N25: =IF(ISNUMBER(timeseries!G7),timeseries!G7,"") | O25: GBP/MWh nominal
A26: UK | B26: 2013 | C26: large | D26: E1 | E26: BSUoS (demand-only from 04/2023) | F26: 4 System services & balancing | G26: balancing charge | H26: i | I26: =IF(ISNUMBER(N26),N26*fx_deflator!$I$8*fx_deflator!$M$8,"") | J26: NESO bsuos-fixed-tariffs + HH RF settlement files (own annual avg 2010-22) | K26: stage4_uk r28-30 | L26: 2026-07-15 | M26: Y | N26: =IF(ISNUMBER(timeseries!G8),timeseries!G8,"") | O26: GBP/MWh nominal
A27: UK | B27: 2013 | C27: large | D27: E1 | E27: AAHEDC | F27: 3 Network | G27: network levy (hydro benefit) | H27: ii (pays cross-subsidy to N Scotland consumers) | I27: =IF(ISNUMBER(N27),N27*fx_deflator!$I$8*fx_deflator!$M$8,"") | J27: NG/ESO AAHEDC charging statements & final tariff letters | K27: stage4_uk r31 | L27: 2026-07-15 | M27: N | N27: =IF(ISNUMBER(timeseries!G9),timeseries!G9,"") | O27: GBP/MWh nominal | P27: not in NCC base (conservative, unverified)
A28: UK | B28: 2013 | C28: large | D28: E1 | E28: RO (buy-out x obligation) | F28: 2 Gen capital recovery | G28: renewables levy | H28: i | I28: =IF(ISNUMBER(N28),N28*fx_deflator!$I$8*fx_deflator!$M$8,"") | J28: Ofgem RO guidance OFG1164 Table 1.1 (buy-out x obligation) | K28: stage4_uk r12-14 | L28: 2026-07-15 | M28: Y | N28: =IF(ISNUMBER(timeseries!G10),timeseries!G10,"") | O28: GBP/MWh nominal
A29: UK | B29: 2013 | C29: large | D29: E1 | E29: FiT levelisation | F29: 2 Gen capital recovery | G29: renewables levy | H29: i | I29: =IF(ISNUMBER(N29),N29*fx_deflator!$I$8*fx_deflator!$M$8,"") | J29: Ofgem FIT Annual Reports SY1-SY15; D27 for 2010-14 | K29: stage4_uk r20 | L29: 2026-07-15 | M29: Y | N29: =IF(ISNUMBER(timeseries!G12),timeseries!G12,"") | O29: GBP/MWh nominal | P29: 2025 unpublished (Q32) — row absent, gap stated
A30: UK | B30: 2013 | C30: large | D30: E1 | E30: CCL (main rate; CCA discount not modelled) | F30: 5 General taxation & levies | G30: climate levy (tax) | H30: i | I30: =IF(ISNUMBER(N30),N30*fx_deflator!$I$8*fx_deflator!$M$8,"") | J30: HMRC Environmental Taxes Bulletin, historical rates Table 1 | K30: stage4_uk r22 | L30: 2026-07-15 | M30: N | N30: =IF(ISNUMBER(timeseries!G14),timeseries!G14,"") | O30: GBP/MWh nominal
A31: UK | B31: 2014 | C31: large | D31: E1 | E31: Wholesale (rolling year-ahead baseload; DA proxy <=2021) | F31: 1 Commodity | G31: wholesale market | H31: i | I31: =IF(ISNUMBER(N31),N31*fx_deflator!$I$9*fx_deflator!$M$9,"") | J31: Ofgem data portal — DA baseload monthly avg (proxy <=2021, D22); Forward Delivery Contracts (D21) | K31: stage4_uk r7-9 | L31: 2026-07-15 | M31: Y | N31: =IF(ISNUMBER(timeseries!H6),timeseries!H6,"") | O31: GBP/MWh nominal | P31: identical E1/E2; embedded carbon memo inside this item
A32: UK | B32: 2014 | C32: large | D32: E1 | E32: TNUoS demand (zone 5; TCR banded residual from 2023) | F32: 3 Network | G32: transmission network charge | H32: i | I32: =IF(ISNUMBER(N32),N32*fx_deflator!$I$9*fx_deflator!$M$9,"") | J32: NESO TNUoS tariff documents (compendium doc 50736; Final TNUoS 2023/24-2026/27 Table 10) | K32: stage4_uk r25-27 | L32: 2026-07-15 | M32: Y | N32: =IF(ISNUMBER(timeseries!H7),timeseries!H7,"") | O32: GBP/MWh nominal
A33: UK | B33: 2014 | C33: large | D33: E1 | E33: BSUoS (demand-only from 04/2023) | F33: 4 System services & balancing | G33: balancing charge | H33: i | I33: =IF(ISNUMBER(N33),N33*fx_deflator!$I$9*fx_deflator!$M$9,"") | J33: NESO bsuos-fixed-tariffs + HH RF settlement files (own annual avg 2010-22) | K33: stage4_uk r28-30 | L33: 2026-07-15 | M33: Y | N33: =IF(ISNUMBER(timeseries!H8),timeseries!H8,"") | O33: GBP/MWh nominal
A34: UK | B34: 2014 | C34: large | D34: E1 | E34: AAHEDC | F34: 3 Network | G34: network levy (hydro benefit) | H34: ii (pays cross-subsidy to N Scotland consumers) | I34: =IF(ISNUMBER(N34),N34*fx_deflator!$I$9*fx_deflator!$M$9,"") | J34: NG/ESO AAHEDC charging statements & final tariff letters | K34: stage4_uk r31 | L34: 2026-07-15 | M34: N | N34: =IF(ISNUMBER(timeseries!H9),timeseries!H9,"") | O34: GBP/MWh nominal | P34: not in NCC base (conservative, unverified)
A35: UK | B35: 2014 | C35: large | D35: E1 | E35: RO (buy-out x obligation) | F35: 2 Gen capital recovery | G35: renewables levy | H35: i | I35: =IF(ISNUMBER(N35),N35*fx_deflator!$I$9*fx_deflator!$M$9,"") | J35: Ofgem RO guidance OFG1164 Table 1.1 (buy-out x obligation) | K35: stage4_uk r12-14 | L35: 2026-07-15 | M35: Y | N35: =IF(ISNUMBER(timeseries!H10),timeseries!H10,"") | O35: GBP/MWh nominal
A36: UK | B36: 2014 | C36: large | D36: E1 | E36: FiT levelisation | F36: 2 Gen capital recovery | G36: renewables levy | H36: i | I36: =IF(ISNUMBER(N36),N36*fx_deflator!$I$9*fx_deflator!$M$9,"") | J36: Ofgem FIT Annual Reports SY1-SY15; D27 for 2010-14 | K36: stage4_uk r20 | L36: 2026-07-15 | M36: Y | N36: =IF(ISNUMBER(timeseries!H12),timeseries!H12,"") | O36: GBP/MWh nominal | P36: 2025 unpublished (Q32) — row absent, gap stated
A37: UK | B37: 2014 | C37: large | D37: E1 | E37: CCL (main rate; CCA discount not modelled) | F37: 5 General taxation & levies | G37: climate levy (tax) | H37: i | I37: =IF(ISNUMBER(N37),N37*fx_deflator!$I$9*fx_deflator!$M$9,"") | J37: HMRC Environmental Taxes Bulletin, historical rates Table 1 | K37: stage4_uk r22 | L37: 2026-07-15 | M37: N | N37: =IF(ISNUMBER(timeseries!H14),timeseries!H14,"") | O37: GBP/MWh nominal
A38: UK | B38: 2015 | C38: large | D38: E1 | E38: Wholesale (rolling year-ahead baseload; DA proxy <=2021) | F38: 1 Commodity | G38: wholesale market | H38: i | I38: =IF(ISNUMBER(N38),N38*fx_deflator!$I$10*fx_deflator!$M$10,"") | J38: Ofgem data portal — DA baseload monthly avg (proxy <=2021, D22); Forward Delivery Contracts (D21) | K38: stage4_uk r7-9 | L38: 2026-07-15 | M38: Y | N38: =IF(ISNUMBER(timeseries!I6),timeseries!I6,"") | O38: GBP/MWh nominal | P38: identical E1/E2; embedded carbon memo inside this item
A39: UK | B39: 2015 | C39: large | D39: E1 | E39: TNUoS demand (zone 5; TCR banded residual from 2023) | F39: 3 Network | G39: transmission network charge | H39: i | I39: =IF(ISNUMBER(N39),N39*fx_deflator!$I$10*fx_deflator!$M$10,"") | J39: NESO TNUoS tariff documents (compendium doc 50736; Final TNUoS 2023/24-2026/27 Table 10) | K39: stage4_uk r25-27 | L39: 2026-07-15 | M39: Y | N39: =IF(ISNUMBER(timeseries!I7),timeseries!I7,"") | O39: GBP/MWh nominal
A40: UK | B40: 2015 | C40: large | D40: E1 | E40: BSUoS (demand-only from 04/2023) | F40: 4 System services & balancing | G40: balancing charge | H40: i | I40: =IF(ISNUMBER(N40),N40*fx_deflator!$I$10*fx_deflator!$M$10,"") | J40: NESO bsuos-fixed-tariffs + HH RF settlement files (own annual avg 2010-22) | K40: stage4_uk r28-30 | L40: 2026-07-15 | M40: Y | N40: =IF(ISNUMBER(timeseries!I8),timeseries!I8,"") | O40: GBP/MWh nominal
A41: UK | B41: 2015 | C41: large | D41: E1 | E41: AAHEDC | F41: 3 Network | G41: network levy (hydro benefit) | H41: ii (pays cross-subsidy to N Scotland consumers) | I41: =IF(ISNUMBER(N41),N41*fx_deflator!$I$10*fx_deflator!$M$10,"") | J41: NG/ESO AAHEDC charging statements & final tariff letters | K41: stage4_uk r31 | L41: 2026-07-15 | M41: N | N41: =IF(ISNUMBER(timeseries!I9),timeseries!I9,"") | O41: GBP/MWh nominal | P41: not in NCC base (conservative, unverified)
A42: UK | B42: 2015 | C42: large | D42: E1 | E42: RO (buy-out x obligation) | F42: 2 Gen capital recovery | G42: renewables levy | H42: i | I42: =IF(ISNUMBER(N42),N42*fx_deflator!$I$10*fx_deflator!$M$10,"") | J42: Ofgem RO guidance OFG1164 Table 1.1 (buy-out x obligation) | K42: stage4_uk r12-14 | L42: 2026-07-15 | M42: Y | N42: =IF(ISNUMBER(timeseries!I10),timeseries!I10,"") | O42: GBP/MWh nominal
A43: UK | B43: 2015 | C43: large | D43: E1 | E43: FiT levelisation | F43: 2 Gen capital recovery | G43: renewables levy | H43: i | I43: =IF(ISNUMBER(N43),N43*fx_deflator!$I$10*fx_deflator!$M$10,"") | J43: Ofgem FIT Annual Reports SY1-SY15; D27 for 2010-14 | K43: stage4_uk r20 | L43: 2026-07-15 | M43: Y | N43: =IF(ISNUMBER(timeseries!I12),timeseries!I12,"") | O43: GBP/MWh nominal | P43: 2025 unpublished (Q32) — row absent, gap stated
A44: UK | B44: 2015 | C44: large | D44: E1 | E44: CCL (main rate; CCA discount not modelled) | F44: 5 General taxation & levies | G44: climate levy (tax) | H44: i | I44: =IF(ISNUMBER(N44),N44*fx_deflator!$I$10*fx_deflator!$M$10,"") | J44: HMRC Environmental Taxes Bulletin, historical rates Table 1 | K44: stage4_uk r22 | L44: 2026-07-15 | M44: N | N44: =IF(ISNUMBER(timeseries!I14),timeseries!I14,"") | O44: GBP/MWh nominal
A45: UK | B45: 2016 | C45: large | D45: E1 | E45: Wholesale (rolling year-ahead baseload; DA proxy <=2021) | F45: 1 Commodity | G45: wholesale market | H45: i | I45: =IF(ISNUMBER(N45),N45*fx_deflator!$I$11*fx_deflator!$M$11,"") | J45: Ofgem data portal — DA baseload monthly avg (proxy <=2021, D22); Forward Delivery Contracts (D21) | K45: stage4_uk r7-9 | L45: 2026-07-15 | M45: Y | N45: =IF(ISNUMBER(timeseries!J6),timeseries!J6,"") | O45: GBP/MWh nominal | P45: identical E1/E2; embedded carbon memo inside this item
A46: UK | B46: 2016 | C46: large | D46: E1 | E46: TNUoS demand (zone 5; TCR banded residual from 2023) | F46: 3 Network | G46: transmission network charge | H46: i | I46: =IF(ISNUMBER(N46),N46*fx_deflator!$I$11*fx_deflator!$M$11,"") | J46: NESO TNUoS tariff documents (compendium doc 50736; Final TNUoS 2023/24-2026/27 Table 10) | K46: stage4_uk r25-27 | L46: 2026-07-15 | M46: Y | N46: =IF(ISNUMBER(timeseries!J7),timeseries!J7,"") | O46: GBP/MWh nominal
A47: UK | B47: 2016 | C47: large | D47: E1 | E47: BSUoS (demand-only from 04/2023) | F47: 4 System services & balancing | G47: balancing charge | H47: i | I47: =IF(ISNUMBER(N47),N47*fx_deflator!$I$11*fx_deflator!$M$11,"") | J47: NESO bsuos-fixed-tariffs + HH RF settlement files (own annual avg 2010-22) | K47: stage4_uk r28-30 | L47: 2026-07-15 | M47: Y | N47: =IF(ISNUMBER(timeseries!J8),timeseries!J8,"") | O47: GBP/MWh nominal
A48: UK | B48: 2016 | C48: large | D48: E1 | E48: AAHEDC | F48: 3 Network | G48: network levy (hydro benefit) | H48: ii (pays cross-subsidy to N Scotland consumers) | I48: =IF(ISNUMBER(N48),N48*fx_deflator!$I$11*fx_deflator!$M$11,"") | J48: NG/ESO AAHEDC charging statements & final tariff letters | K48: stage4_uk r31 | L48: 2026-07-15 | M48: N | N48: =IF(ISNUMBER(timeseries!J9),timeseries!J9,"") | O48: GBP/MWh nominal | P48: not in NCC base (conservative, unverified)
A49: UK | B49: 2016 | C49: large | D49: E1 | E49: RO (buy-out x obligation) | F49: 2 Gen capital recovery | G49: renewables levy | H49: i | I49: =IF(ISNUMBER(N49),N49*fx_deflator!$I$11*fx_deflator!$M$11,"") | J49: Ofgem RO guidance OFG1164 Table 1.1 (buy-out x obligation) | K49: stage4_uk r12-14 | L49: 2026-07-15 | M49: Y | N49: =IF(ISNUMBER(timeseries!J10),timeseries!J10,"") | O49: GBP/MWh nominal
A50: UK | B50: 2016 | C50: large | D50: E1 | E50: CfD Interim Levy Rate (annual avg) | F50: 2 Gen capital recovery | G50: renewables levy | H50: i | I50: =IF(ISNUMBER(N50),N50*fx_deflator!$I$11*fx_deflator!$M$11,"") | J50: LCCC Actual ILR Income dataset (quarterly avg) | K50: stage4_uk r15-19 | L50: 2026-07-15 | M50: Y | N50: =IF(ISNUMBER(timeseries!J11),timeseries!J11,"") | O50: GBP/MWh nominal
A51: UK | B51: 2016 | C51: large | D51: E1 | E51: FiT levelisation | F51: 2 Gen capital recovery | G51: renewables levy | H51: i | I51: =IF(ISNUMBER(N51),N51*fx_deflator!$I$11*fx_deflator!$M$11,"") | J51: Ofgem FIT Annual Reports SY1-SY15; D27 for 2010-14 | K51: stage4_uk r20 | L51: 2026-07-15 | M51: Y | N51: =IF(ISNUMBER(timeseries!J12),timeseries!J12,"") | O51: GBP/MWh nominal | P51: 2025 unpublished (Q32) — row absent, gap stated
A52: UK | B52: 2016 | C52: large | D52: E1 | E52: CCL (main rate; CCA discount not modelled) | F52: 5 General taxation & levies | G52: climate levy (tax) | H52: i | I52: =IF(ISNUMBER(N52),N52*fx_deflator!$I$11*fx_deflator!$M$11,"") | J52: HMRC Environmental Taxes Bulletin, historical rates Table 1 | K52: stage4_uk r22 | L52: 2026-07-15 | M52: N | N52: =IF(ISNUMBER(timeseries!J14),timeseries!J14,"") | O52: GBP/MWh nominal
A53: UK | B53: 2017 | C53: large | D53: E1 | E53: Wholesale (rolling year-ahead baseload; DA proxy <=2021) | F53: 1 Commodity | G53: wholesale market | H53: i | I53: =IF(ISNUMBER(N53),N53*fx_deflator!$I$12*fx_deflator!$M$12,"") | J53: Ofgem data portal — DA baseload monthly avg (proxy <=2021, D22); Forward Delivery Contracts (D21) | K53: stage4_uk r7-9 | L53: 2026-07-15 | M53: Y | N53: =IF(ISNUMBER(timeseries!K6),timeseries!K6,"") | O53: GBP/MWh nominal | P53: identical E1/E2; embedded carbon memo inside this item
A54: UK | B54: 2017 | C54: large | D54: E1 | E54: TNUoS demand (zone 5; TCR banded residual from 2023) | F54: 3 Network | G54: transmission network charge | H54: i | I54: =IF(ISNUMBER(N54),N54*fx_deflator!$I$12*fx_deflator!$M$12,"") | J54: NESO TNUoS tariff documents (compendium doc 50736; Final TNUoS 2023/24-2026/27 Table 10) | K54: stage4_uk r25-27 | L54: 2026-07-15 | M54: Y | N54: =IF(ISNUMBER(timeseries!K7),timeseries!K7,"") | O54: GBP/MWh nominal
A55: UK | B55: 2017 | C55: large | D55: E1 | E55: BSUoS (demand-only from 04/2023) | F55: 4 System services & balancing | G55: balancing charge | H55: i | I55: =IF(ISNUMBER(N55),N55*fx_deflator!$I$12*fx_deflator!$M$12,"") | J55: NESO bsuos-fixed-tariffs + HH RF settlement files (own annual avg 2010-22) | K55: stage4_uk r28-30 | L55: 2026-07-15 | M55: Y | N55: =IF(ISNUMBER(timeseries!K8),timeseries!K8,"") | O55: GBP/MWh nominal
A56: UK | B56: 2017 | C56: large | D56: E1 | E56: AAHEDC | F56: 3 Network | G56: network levy (hydro benefit) | H56: ii (pays cross-subsidy to N Scotland consumers) | I56: =IF(ISNUMBER(N56),N56*fx_deflator!$I$12*fx_deflator!$M$12,"") | J56: NG/ESO AAHEDC charging statements & final tariff letters | K56: stage4_uk r31 | L56: 2026-07-15 | M56: N | N56: =IF(ISNUMBER(timeseries!K9),timeseries!K9,"") | O56: GBP/MWh nominal | P56: not in NCC base (conservative, unverified)
A57: UK | B57: 2017 | C57: large | D57: E1 | E57: RO (buy-out x obligation) | F57: 2 Gen capital recovery | G57: renewables levy | H57: i | I57: =IF(ISNUMBER(N57),N57*fx_deflator!$I$12*fx_deflator!$M$12,"") | J57: Ofgem RO guidance OFG1164 Table 1.1 (buy-out x obligation) | K57: stage4_uk r12-14 | L57: 2026-07-15 | M57: Y | N57: =IF(ISNUMBER(timeseries!K10),timeseries!K10,"") | O57: GBP/MWh nominal
A58: UK | B58: 2017 | C58: large | D58: E1 | E58: CfD Interim Levy Rate (annual avg) | F58: 2 Gen capital recovery | G58: renewables levy | H58: i | I58: =IF(ISNUMBER(N58),N58*fx_deflator!$I$12*fx_deflator!$M$12,"") | J58: LCCC Actual ILR Income dataset (quarterly avg) | K58: stage4_uk r15-19 | L58: 2026-07-15 | M58: Y | N58: =IF(ISNUMBER(timeseries!K11),timeseries!K11,"") | O58: GBP/MWh nominal
A59: UK | B59: 2017 | C59: large | D59: E1 | E59: FiT levelisation | F59: 2 Gen capital recovery | G59: renewables levy | H59: i | I59: =IF(ISNUMBER(N59),N59*fx_deflator!$I$12*fx_deflator!$M$12,"") | J59: Ofgem FIT Annual Reports SY1-SY15; D27 for 2010-14 | K59: stage4_uk r20 | L59: 2026-07-15 | M59: Y | N59: =IF(ISNUMBER(timeseries!K12),timeseries!K12,"") | O59: GBP/MWh nominal | P59: 2025 unpublished (Q32) — row absent, gap stated
A60: UK | B60: 2017 | C60: large | D60: E1 | E60: Capacity Market (derived per-MWh) | F60: 2 Gen capital recovery | G60: capacity market levy | H60: i | I60: =IF(ISNUMBER(N60),N60*fx_deflator!$I$12*fx_deflator!$M$12,"") | J60: EMRS Key Figures for Payments (derived per-MWh, D30) | K60: stage4_uk r21 | L60: 2026-07-15 | M60: Y | N60: =IF(ISNUMBER(timeseries!K13),timeseries!K13,"") | O60: GBP/MWh nominal | P60: function 2 per D9
A61: UK | B61: 2017 | C61: large | D61: E1 | E61: CCL (main rate; CCA discount not modelled) | F61: 5 General taxation & levies | G61: climate levy (tax) | H61: i | I61: =IF(ISNUMBER(N61),N61*fx_deflator!$I$12*fx_deflator!$M$12,"") | J61: HMRC Environmental Taxes Bulletin, historical rates Table 1 | K61: stage4_uk r22 | L61: 2026-07-15 | M61: N | N61: =IF(ISNUMBER(timeseries!K14),timeseries!K14,"") | O61: GBP/MWh nominal
A62: UK | B62: 2018 | C62: large | D62: E1 | E62: Wholesale (rolling year-ahead baseload; DA proxy <=2021) | F62: 1 Commodity | G62: wholesale market | H62: i | I62: =IF(ISNUMBER(N62),N62*fx_deflator!$I$13*fx_deflator!$M$13,"") | J62: Ofgem data portal — DA baseload monthly avg (proxy <=2021, D22); Forward Delivery Contracts (D21) | K62: stage4_uk r7-9 | L62: 2026-07-15 | M62: Y | N62: =IF(ISNUMBER(timeseries!L6),timeseries!L6,"") | O62: GBP/MWh nominal | P62: identical E1/E2; embedded carbon memo inside this item
A63: UK | B63: 2018 | C63: large | D63: E1 | E63: TNUoS demand (zone 5; TCR banded residual from 2023) | F63: 3 Network | G63: transmission network charge | H63: i | I63: =IF(ISNUMBER(N63),N63*fx_deflator!$I$13*fx_deflator!$M$13,"") | J63: NESO TNUoS tariff documents (compendium doc 50736; Final TNUoS 2023/24-2026/27 Table 10) | K63: stage4_uk r25-27 | L63: 2026-07-15 | M63: Y | N63: =IF(ISNUMBER(timeseries!L7),timeseries!L7,"") | O63: GBP/MWh nominal
A64: UK | B64: 2018 | C64: large | D64: E1 | E64: BSUoS (demand-only from 04/2023) | F64: 4 System services & balancing | G64: balancing charge | H64: i | I64: =IF(ISNUMBER(N64),N64*fx_deflator!$I$13*fx_deflator!$M$13,"") | J64: NESO bsuos-fixed-tariffs + HH RF settlement files (own annual avg 2010-22) | K64: stage4_uk r28-30 | L64: 2026-07-15 | M64: Y | N64: =IF(ISNUMBER(timeseries!L8),timeseries!L8,"") | O64: GBP/MWh nominal
A65: UK | B65: 2018 | C65: large | D65: E1 | E65: AAHEDC | F65: 3 Network | G65: network levy (hydro benefit) | H65: ii (pays cross-subsidy to N Scotland consumers) | I65: =IF(ISNUMBER(N65),N65*fx_deflator!$I$13*fx_deflator!$M$13,"") | J65: NG/ESO AAHEDC charging statements & final tariff letters | K65: stage4_uk r31 | L65: 2026-07-15 | M65: N | N65: =IF(ISNUMBER(timeseries!L9),timeseries!L9,"") | O65: GBP/MWh nominal | P65: not in NCC base (conservative, unverified)
A66: UK | B66: 2018 | C66: large | D66: E1 | E66: RO (buy-out x obligation) | F66: 2 Gen capital recovery | G66: renewables levy | H66: i | I66: =IF(ISNUMBER(N66),N66*fx_deflator!$I$13*fx_deflator!$M$13,"") | J66: Ofgem RO guidance OFG1164 Table 1.1 (buy-out x obligation) | K66: stage4_uk r12-14 | L66: 2026-07-15 | M66: Y | N66: =IF(ISNUMBER(timeseries!L10),timeseries!L10,"") | O66: GBP/MWh nominal
A67: UK | B67: 2018 | C67: large | D67: E1 | E67: CfD Interim Levy Rate (annual avg) | F67: 2 Gen capital recovery | G67: renewables levy | H67: i | I67: =IF(ISNUMBER(N67),N67*fx_deflator!$I$13*fx_deflator!$M$13,"") | J67: LCCC Actual ILR Income dataset (quarterly avg) | K67: stage4_uk r15-19 | L67: 2026-07-15 | M67: Y | N67: =IF(ISNUMBER(timeseries!L11),timeseries!L11,"") | O67: GBP/MWh nominal
A68: UK | B68: 2018 | C68: large | D68: E1 | E68: FiT levelisation | F68: 2 Gen capital recovery | G68: renewables levy | H68: i | I68: =IF(ISNUMBER(N68),N68*fx_deflator!$I$13*fx_deflator!$M$13,"") | J68: Ofgem FIT Annual Reports SY1-SY15; D27 for 2010-14 | K68: stage4_uk r20 | L68: 2026-07-15 | M68: Y | N68: =IF(ISNUMBER(timeseries!L12),timeseries!L12,"") | O68: GBP/MWh nominal | P68: 2025 unpublished (Q32) — row absent, gap stated
A69: UK | B69: 2018 | C69: large | D69: E1 | E69: Capacity Market (derived per-MWh) | F69: 2 Gen capital recovery | G69: capacity market levy | H69: i | I69: =IF(ISNUMBER(N69),N69*fx_deflator!$I$13*fx_deflator!$M$13,"") | J69: EMRS Key Figures for Payments (derived per-MWh, D30) | K69: stage4_uk r21 | L69: 2026-07-15 | M69: Y | N69: =IF(ISNUMBER(timeseries!L13),timeseries!L13,"") | O69: GBP/MWh nominal | P69: function 2 per D9
A70: UK | B70: 2018 | C70: large | D70: E1 | E70: CCL (main rate; CCA discount not modelled) | F70: 5 General taxation & levies | G70: climate levy (tax) | H70: i | I70: =IF(ISNUMBER(N70),N70*fx_deflator!$I$13*fx_deflator!$M$13,"") | J70: HMRC Environmental Taxes Bulletin, historical rates Table 1 | K70: stage4_uk r22 | L70: 2026-07-15 | M70: N | N70: =IF(ISNUMBER(timeseries!L14),timeseries!L14,"") | O70: GBP/MWh nominal
A71: UK | B71: 2019 | C71: large | D71: E1 | E71: Wholesale (rolling year-ahead baseload; DA proxy <=2021) | F71: 1 Commodity | G71: wholesale market | H71: i | I71: =IF(ISNUMBER(N71),N71*fx_deflator!$I$14*fx_deflator!$M$14,"") | J71: Ofgem data portal — DA baseload monthly avg (proxy <=2021, D22); Forward Delivery Contracts (D21) | K71: stage4_uk r7-9 | L71: 2026-07-15 | M71: Y | N71: =IF(ISNUMBER(timeseries!M6),timeseries!M6,"") | O71: GBP/MWh nominal | P71: identical E1/E2; embedded carbon memo inside this item
A72: UK | B72: 2019 | C72: large | D72: E1 | E72: TNUoS demand (zone 5; TCR banded residual from 2023) | F72: 3 Network | G72: transmission network charge | H72: i | I72: =IF(ISNUMBER(N72),N72*fx_deflator!$I$14*fx_deflator!$M$14,"") | J72: NESO TNUoS tariff documents (compendium doc 50736; Final TNUoS 2023/24-2026/27 Table 10) | K72: stage4_uk r25-27 | L72: 2026-07-15 | M72: Y | N72: =IF(ISNUMBER(timeseries!M7),timeseries!M7,"") | O72: GBP/MWh nominal
A73: UK | B73: 2019 | C73: large | D73: E1 | E73: BSUoS (demand-only from 04/2023) | F73: 4 System services & balancing | G73: balancing charge | H73: i | I73: =IF(ISNUMBER(N73),N73*fx_deflator!$I$14*fx_deflator!$M$14,"") | J73: NESO bsuos-fixed-tariffs + HH RF settlement files (own annual avg 2010-22) | K73: stage4_uk r28-30 | L73: 2026-07-15 | M73: Y | N73: =IF(ISNUMBER(timeseries!M8),timeseries!M8,"") | O73: GBP/MWh nominal
A74: UK | B74: 2019 | C74: large | D74: E1 | E74: AAHEDC | F74: 3 Network | G74: network levy (hydro benefit) | H74: ii (pays cross-subsidy to N Scotland consumers) | I74: =IF(ISNUMBER(N74),N74*fx_deflator!$I$14*fx_deflator!$M$14,"") | J74: NG/ESO AAHEDC charging statements & final tariff letters | K74: stage4_uk r31 | L74: 2026-07-15 | M74: N | N74: =IF(ISNUMBER(timeseries!M9),timeseries!M9,"") | O74: GBP/MWh nominal | P74: not in NCC base (conservative, unverified)
A75: UK | B75: 2019 | C75: large | D75: E1 | E75: RO (buy-out x obligation) | F75: 2 Gen capital recovery | G75: renewables levy | H75: i | I75: =IF(ISNUMBER(N75),N75*fx_deflator!$I$14*fx_deflator!$M$14,"") | J75: Ofgem RO guidance OFG1164 Table 1.1 (buy-out x obligation) | K75: stage4_uk r12-14 | L75: 2026-07-15 | M75: Y | N75: =IF(ISNUMBER(timeseries!M10),timeseries!M10,"") | O75: GBP/MWh nominal
A76: UK | B76: 2019 | C76: large | D76: E1 | E76: CfD Interim Levy Rate (annual avg) | F76: 2 Gen capital recovery | G76: renewables levy | H76: i | I76: =IF(ISNUMBER(N76),N76*fx_deflator!$I$14*fx_deflator!$M$14,"") | J76: LCCC Actual ILR Income dataset (quarterly avg) | K76: stage4_uk r15-19 | L76: 2026-07-15 | M76: Y | N76: =IF(ISNUMBER(timeseries!M11),timeseries!M11,"") | O76: GBP/MWh nominal
A77: UK | B77: 2019 | C77: large | D77: E1 | E77: FiT levelisation | F77: 2 Gen capital recovery | G77: renewables levy | H77: i | I77: =IF(ISNUMBER(N77),N77*fx_deflator!$I$14*fx_deflator!$M$14,"") | J77: Ofgem FIT Annual Reports SY1-SY15; D27 for 2010-14 | K77: stage4_uk r20 | L77: 2026-07-15 | M77: Y | N77: =IF(ISNUMBER(timeseries!M12),timeseries!M12,"") | O77: GBP/MWh nominal | P77: 2025 unpublished (Q32) — row absent, gap stated
A78: UK | B78: 2019 | C78: large | D78: E1 | E78: Capacity Market (derived per-MWh) | F78: 2 Gen capital recovery | G78: capacity market levy | H78: i | I78: =IF(ISNUMBER(N78),N78*fx_deflator!$I$14*fx_deflator!$M$14,"") | J78: EMRS Key Figures for Payments (derived per-MWh, D30) | K78: stage4_uk r21 | L78: 2026-07-15 | M78: Y | N78: =IF(ISNUMBER(timeseries!M13),timeseries!M13,"") | O78: GBP/MWh nominal | P78: function 2 per D9
A79: UK | B79: 2019 | C79: large | D79: E1 | E79: CCL (main rate; CCA discount not modelled) | F79: 5 General taxation & levies | G79: climate levy (tax) | H79: i | I79: =IF(ISNUMBER(N79),N79*fx_deflator!$I$14*fx_deflator!$M$14,"") | J79: HMRC Environmental Taxes Bulletin, historical rates Table 1 | K79: stage4_uk r22 | L79: 2026-07-15 | M79: N | N79: =IF(ISNUMBER(timeseries!M14),timeseries!M14,"") | O79: GBP/MWh nominal
A80: UK | B80: 2020 | C80: large | D80: E1 | E80: Wholesale (rolling year-ahead baseload; DA proxy <=2021) | F80: 1 Commodity | G80: wholesale market | H80: i | I80: =IF(ISNUMBER(N80),N80*fx_deflator!$I$15*fx_deflator!$M$15,"") | J80: Ofgem data portal — DA baseload monthly avg (proxy <=2021, D22); Forward Delivery Contracts (D21) | K80: stage4_uk r7-9 | L80: 2026-07-15 | M80: Y | N80: =IF(ISNUMBER(timeseries!N6),timeseries!N6,"") | O80: GBP/MWh nominal | P80: identical E1/E2; embedded carbon memo inside this item
A81: UK | B81: 2020 | C81: large | D81: E1 | E81: TNUoS demand (zone 5; TCR banded residual from 2023) | F81: 3 Network | G81: transmission network charge | H81: i | I81: =IF(ISNUMBER(N81),N81*fx_deflator!$I$15*fx_deflator!$M$15,"") | J81: NESO TNUoS tariff documents (compendium doc 50736; Final TNUoS 2023/24-2026/27 Table 10) | K81: stage4_uk r25-27 | L81: 2026-07-15 | M81: Y | N81: =IF(ISNUMBER(timeseries!N7),timeseries!N7,"") | O81: GBP/MWh nominal
A82: UK | B82: 2020 | C82: large | D82: E1 | E82: BSUoS (demand-only from 04/2023) | F82: 4 System services & balancing | G82: balancing charge | H82: i | I82: =IF(ISNUMBER(N82),N82*fx_deflator!$I$15*fx_deflator!$M$15,"") | J82: NESO bsuos-fixed-tariffs + HH RF settlement files (own annual avg 2010-22) | K82: stage4_uk r28-30 | L82: 2026-07-15 | M82: Y | N82: =IF(ISNUMBER(timeseries!N8),timeseries!N8,"") | O82: GBP/MWh nominal
A83: UK | B83: 2020 | C83: large | D83: E1 | E83: AAHEDC | F83: 3 Network | G83: network levy (hydro benefit) | H83: ii (pays cross-subsidy to N Scotland consumers) | I83: =IF(ISNUMBER(N83),N83*fx_deflator!$I$15*fx_deflator!$M$15,"") | J83: NG/ESO AAHEDC charging statements & final tariff letters | K83: stage4_uk r31 | L83: 2026-07-15 | M83: N | N83: =IF(ISNUMBER(timeseries!N9),timeseries!N9,"") | O83: GBP/MWh nominal | P83: not in NCC base (conservative, unverified)
A84: UK | B84: 2020 | C84: large | D84: E1 | E84: RO (buy-out x obligation) | F84: 2 Gen capital recovery | G84: renewables levy | H84: i | I84: =IF(ISNUMBER(N84),N84*fx_deflator!$I$15*fx_deflator!$M$15,"") | J84: Ofgem RO guidance OFG1164 Table 1.1 (buy-out x obligation) | K84: stage4_uk r12-14 | L84: 2026-07-15 | M84: Y | N84: =IF(ISNUMBER(timeseries!N10),timeseries!N10,"") | O84: GBP/MWh nominal
A85: UK | B85: 2020 | C85: large | D85: E1 | E85: CfD Interim Levy Rate (annual avg) | F85: 2 Gen capital recovery | G85: renewables levy | H85: i | I85: =IF(ISNUMBER(N85),N85*fx_deflator!$I$15*fx_deflator!$M$15,"") | J85: LCCC Actual ILR Income dataset (quarterly avg) | K85: stage4_uk r15-19 | L85: 2026-07-15 | M85: Y | N85: =IF(ISNUMBER(timeseries!N11),timeseries!N11,"") | O85: GBP/MWh nominal
A86: UK | B86: 2020 | C86: large | D86: E1 | E86: FiT levelisation | F86: 2 Gen capital recovery | G86: renewables levy | H86: i | I86: =IF(ISNUMBER(N86),N86*fx_deflator!$I$15*fx_deflator!$M$15,"") | J86: Ofgem FIT Annual Reports SY1-SY15; D27 for 2010-14 | K86: stage4_uk r20 | L86: 2026-07-15 | M86: Y | N86: =IF(ISNUMBER(timeseries!N12),timeseries!N12,"") | O86: GBP/MWh nominal | P86: 2025 unpublished (Q32) — row absent, gap stated
A87: UK | B87: 2020 | C87: large | D87: E1 | E87: Capacity Market (derived per-MWh) | F87: 2 Gen capital recovery | G87: capacity market levy | H87: i | I87: =IF(ISNUMBER(N87),N87*fx_deflator!$I$15*fx_deflator!$M$15,"") | J87: EMRS Key Figures for Payments (derived per-MWh, D30) | K87: stage4_uk r21 | L87: 2026-07-15 | M87: Y | N87: =IF(ISNUMBER(timeseries!N13),timeseries!N13,"") | O87: GBP/MWh nominal | P87: function 2 per D9
A88: UK | B88: 2020 | C88: large | D88: E1 | E88: CCL (main rate; CCA discount not modelled) | F88: 5 General taxation & levies | G88: climate levy (tax) | H88: i | I88: =IF(ISNUMBER(N88),N88*fx_deflator!$I$15*fx_deflator!$M$15,"") | J88: HMRC Environmental Taxes Bulletin, historical rates Table 1 | K88: stage4_uk r22 | L88: 2026-07-15 | M88: N | N88: =IF(ISNUMBER(timeseries!N14),timeseries!N14,"") | O88: GBP/MWh nominal
A89: UK | B89: 2021 | C89: large | D89: E1 | E89: Wholesale (rolling year-ahead baseload; DA proxy <=2021) | F89: 1 Commodity | G89: wholesale market | H89: i | I89: =IF(ISNUMBER(N89),N89*fx_deflator!$I$16*fx_deflator!$M$16,"") | J89: Ofgem data portal — DA baseload monthly avg (proxy <=2021, D22); Forward Delivery Contracts (D21) | K89: stage4_uk r7-9 | L89: 2026-07-15 | M89: Y | N89: =IF(ISNUMBER(timeseries!O6),timeseries!O6,"") | O89: GBP/MWh nominal | P89: identical E1/E2; embedded carbon memo inside this item
A90: UK | B90: 2021 | C90: large | D90: E1 | E90: TNUoS demand (zone 5; TCR banded residual from 2023) | F90: 3 Network | G90: transmission network charge | H90: i | I90: =IF(ISNUMBER(N90),N90*fx_deflator!$I$16*fx_deflator!$M$16,"") | J90: NESO TNUoS tariff documents (compendium doc 50736; Final TNUoS 2023/24-2026/27 Table 10) | K90: stage4_uk r25-27 | L90: 2026-07-15 | M90: Y | N90: =IF(ISNUMBER(timeseries!O7),timeseries!O7,"") | O90: GBP/MWh nominal
A91: UK | B91: 2021 | C91: large | D91: E1 | E91: BSUoS (demand-only from 04/2023) | F91: 4 System services & balancing | G91: balancing charge | H91: i | I91: =IF(ISNUMBER(N91),N91*fx_deflator!$I$16*fx_deflator!$M$16,"") | J91: NESO bsuos-fixed-tariffs + HH RF settlement files (own annual avg 2010-22) | K91: stage4_uk r28-30 | L91: 2026-07-15 | M91: Y | N91: =IF(ISNUMBER(timeseries!O8),timeseries!O8,"") | O91: GBP/MWh nominal
A92: UK | B92: 2021 | C92: large | D92: E1 | E92: AAHEDC | F92: 3 Network | G92: network levy (hydro benefit) | H92: ii (pays cross-subsidy to N Scotland consumers) | I92: =IF(ISNUMBER(N92),N92*fx_deflator!$I$16*fx_deflator!$M$16,"") | J92: NG/ESO AAHEDC charging statements & final tariff letters | K92: stage4_uk r31 | L92: 2026-07-15 | M92: N | N92: =IF(ISNUMBER(timeseries!O9),timeseries!O9,"") | O92: GBP/MWh nominal | P92: not in NCC base (conservative, unverified)
A93: UK | B93: 2021 | C93: large | D93: E1 | E93: RO (buy-out x obligation) | F93: 2 Gen capital recovery | G93: renewables levy | H93: i | I93: =IF(ISNUMBER(N93),N93*fx_deflator!$I$16*fx_deflator!$M$16,"") | J93: Ofgem RO guidance OFG1164 Table 1.1 (buy-out x obligation) | K93: stage4_uk r12-14 | L93: 2026-07-15 | M93: Y | N93: =IF(ISNUMBER(timeseries!O10),timeseries!O10,"") | O93: GBP/MWh nominal
A94: UK | B94: 2021 | C94: large | D94: E1 | E94: CfD Interim Levy Rate (annual avg) | F94: 2 Gen capital recovery | G94: renewables levy | H94: i | I94: =IF(ISNUMBER(N94),N94*fx_deflator!$I$16*fx_deflator!$M$16,"") | J94: LCCC Actual ILR Income dataset (quarterly avg) | K94: stage4_uk r15-19 | L94: 2026-07-15 | M94: Y | N94: =IF(ISNUMBER(timeseries!O11),timeseries!O11,"") | O94: GBP/MWh nominal
A95: UK | B95: 2021 | C95: large | D95: E1 | E95: FiT levelisation | F95: 2 Gen capital recovery | G95: renewables levy | H95: i | I95: =IF(ISNUMBER(N95),N95*fx_deflator!$I$16*fx_deflator!$M$16,"") | J95: Ofgem FIT Annual Reports SY1-SY15; D27 for 2010-14 | K95: stage4_uk r20 | L95: 2026-07-15 | M95: Y | N95: =IF(ISNUMBER(timeseries!O12),timeseries!O12,"") | O95: GBP/MWh nominal | P95: 2025 unpublished (Q32) — row absent, gap stated
A96: UK | B96: 2021 | C96: large | D96: E1 | E96: Capacity Market (derived per-MWh) | F96: 2 Gen capital recovery | G96: capacity market levy | H96: i | I96: =IF(ISNUMBER(N96),N96*fx_deflator!$I$16*fx_deflator!$M$16,"") | J96: EMRS Key Figures for Payments (derived per-MWh, D30) | K96: stage4_uk r21 | L96: 2026-07-15 | M96: Y | N96: =IF(ISNUMBER(timeseries!O13),timeseries!O13,"") | O96: GBP/MWh nominal | P96: function 2 per D9
A97: UK | B97: 2021 | C97: large | D97: E1 | E97: CCL (main rate; CCA discount not modelled) | F97: 5 General taxation & levies | G97: climate levy (tax) | H97: i | I97: =IF(ISNUMBER(N97),N97*fx_deflator!$I$16*fx_deflator!$M$16,"") | J97: HMRC Environmental Taxes Bulletin, historical rates Table 1 | K97: stage4_uk r22 | L97: 2026-07-15 | M97: N | N97: =IF(ISNUMBER(timeseries!O14),timeseries!O14,"") | O97: GBP/MWh nominal
A98: UK | B98: 2022 | C98: large | D98: E1 | E98: Wholesale (rolling year-ahead baseload; DA proxy <=2021) | F98: 1 Commodity | G98: wholesale market | H98: i | I98: =IF(ISNUMBER(N98),N98*fx_deflator!$I$17*fx_deflator!$M$17,"") | J98: Ofgem data portal — DA baseload monthly avg (proxy <=2021, D22); Forward Delivery Contracts (D21) | K98: stage4_uk r7-9 | L98: 2026-07-15 | M98: Y | N98: =IF(ISNUMBER(timeseries!P6),timeseries!P6,"") | O98: GBP/MWh nominal | P98: identical E1/E2; embedded carbon memo inside this item
A99: UK | B99: 2022 | C99: large | D99: E1 | E99: TNUoS demand (zone 5; TCR banded residual from 2023) | F99: 3 Network | G99: transmission network charge | H99: i | I99: =IF(ISNUMBER(N99),N99*fx_deflator!$I$17*fx_deflator!$M$17,"") | J99: NESO TNUoS tariff documents (compendium doc 50736; Final TNUoS 2023/24-2026/27 Table 10) | K99: stage4_uk r25-27 | L99: 2026-07-15 | M99: Y | N99: =IF(ISNUMBER(timeseries!P7),timeseries!P7,"") | O99: GBP/MWh nominal
A100: UK | B100: 2022 | C100: large | D100: E1 | E100: BSUoS (demand-only from 04/2023) | F100: 4 System services & balancing | G100: balancing charge | H100: i | I100: =IF(ISNUMBER(N100),N100*fx_deflator!$I$17*fx_deflator!$M$17,"") | J100: NESO bsuos-fixed-tariffs + HH RF settlement files (own annual avg 2010-22) | K100: stage4_uk r28-30 | L100: 2026-07-15 | M100: Y | N100: =IF(ISNUMBER(timeseries!P8),timeseries!P8,"") | O100: GBP/MWh nominal
...

Sheet sources
A1: SOURCES — every source with tier and retrieval date
A3: ID | B3: Source | C3: Tier | D3: URL | E3: Retrieved | F3: Used for
A4: S1 | B4: NESO, Final TNUoS Tariffs 2025/26 v1.0, Jan 2025 (report + tables wb) | C4: 1 | D4: https://www.neso.energy/document/353086/download ; tables https://www.neso.energy/document/353061/download | E4: 2026-07-14 | F4: Zone 5, zero floor, T-Demand4 £12,796.715359/site/day, thresholds, App. H map (GN2)
A5: S2 | B5: NESO, Final TNUoS Tariffs 2026/27 v1.0, Jan 2026 (report + tables wb) | C5: 1 | D5: https://www.neso.energy/document/376336/download ; tables https://www.neso.energy/document/376341/download | E5: 2026-07-14 | F5: 2026/27 T-Demand4 £20,829.236682/site/day; re-set thresholds (>163,880 MWh)
A6: S3 | B6: NESO, Transmission Connected Sites Residual Charging Bands (23.05.2025) | C6: 1 | D6: https://www.neso.energy/document/361646/download | E6: 2026-07-14 | F6: Per-site band allocations TRN1–TRN4
A7: S4 | B7: DESNZ, QEP tables 3.4.1/3.4.2 (table_341.xlsx, pub. 30.06.2026) | C7: 1 | D7: https://assets.publishing.service.gov.uk/media/6942bd3536f089d38be1f246/table_341.xlsx | E7: 2026-07-14 | F7: GN1: Extra Large 2024 = 21.697864840 p/kWh excl CCL; 22.146381945 incl CCL
A8: S5 | B8: DBT, NCC uplift consultation response (upd. 31.10.2025) | C8: 1 | D8: https://www.gov.uk/government/consultations/network-charging-compensation-scheme-uplift-for-energy-intensive-industries/outcome/proposed-uplift-to-the-network-charging-compensation-scheme-for-energy-intensive-industries-eiis-government-consultation-response | E8: 2026-07-14 | F8: BIS: 100% CfD/RO/FiT (04/2024), 100% CM (10/2024), NCC 60%→90% from 01.04.2026; ESL recovery
A9: S6 | B9: UK legislation: SI 2024/409; SI 2026/243; Electricity Act 1989 ss.4, 64 | C9: 1 | D9: https://www.legislation.gov.uk/ | E9: 2026-07-14 | F9: EII regs; 132kV transmission/distribution split
A10: S7 | B10: National Grid, Grimsby-Walpole 'Need for project'; Northern Powergrid about-us | C10: 1 | D10: https://www.nationalgrid.com/electricity-transmission/network-and-infrastructure/infrastructure-projects/grimsby-to-walpole/need-for-project ; https://www.northernpowergrid.com/about-us | E10: 2026-07-14 | F10: DNO attribution: both Humber banks = Northern Powergrid
A11: S8 | B11: StromNEV consolidated text (gesetze-im-internet.de): §3, §14a–d, §19 | C11: 1 | D11: https://www.gesetze-im-internet.de/stromnev/ | E11: 2026-07-14 | F11: Harmonised ÜNB charges since 01.01.2023; §19(2) floors 20/15/10% verbatim
A12: S9 | B12: BNetzA GBK, AgNes Orientierungspunkte Industrienetzentgelte, 22.04.2026 (GBK-25-01-1#3) | C12: 1 | D12: https://www.bundesnetzagentur.de/DE/Beschlusskammern/1_GZ/GBK-GZ/2025/GBK-25-01-1x3_AgNes/Downloads/Orientierungspunkte_Industr_NetzE.pdf | E12: 2026-07-14 | F12: §19 reform path (StromNEV expiry end-2028; Bandlast transition to 2031); 555 sites; 68 HS sites avg rebate ≈76% (€242m of €317.36m)
A13: S10 | B13: §24c EnWG; Bundesregierung 'Niedrigere Stromkosten' 22.12.2025 | C13: 1 | D13: https://www.gesetze-im-internet.de/enwg_2005/__24c.html ; https://www.bundesregierung.de/breg-de/aktuelles/niedrigere-netzentgelte-2382396 | E13: 2026-07-14 | F13: €6.5bn 2026 transmission subsidy (KTF), 10× €650m instalments, 2026 only
A14: S11 | B14: netztransparenz.de: Aufschlag besondere Netznutzung 2025/2026 + Datenbasis; KWKG-, Offshore-Umlage 2025/2026; ÜNB-Preisblatt 2026 (05.12.2025) | C14: 1 | D14: https://www.netztransparenz.de/ | E14: 2026-07-14 | F14: Levy values (A' 1.558/1.559; B' 0.050; C' 0.025 ct/kWh); §19 foregone revenue by limb (2026: atypical €379.48m; Bandlast €905.10m); NO privileged volumes published
A15: S12 | B15: StromStG §3, §9b (as amended by BGBl. 2025 I Nr. 340); KAV §2 | C15: 1 | D15: https://www.gesetze-im-internet.de/stromstg/ ; https://www.gesetze-im-internet.de/kav/ | E15: 2026-07-14 | F15: Stromsteuer 20.50 €/MWh, manufacturing relief 20 €/MWh → effective 0.50 (permanent from 2026); Konzessionsabgabe max 0.11 ct/kWh, Grenzpreis rule
... A21: S18 | B21: NDRC 发改价格〔2023〕1501号 (煤电容量电价) + 发改价格〔2026〕114号 | C21: 1 | D21: https://www.ndrc.gov.cn/xxgk/zcfb/tz/202311/t20231110_1361897.html ; https://www.ndrc.gov.cn/xxgk/zcfb/tz/202601/t20260130_1403524.html | E21: 2026-07-14 | F21: 容量电价 330 元/kW·yr benchmark; recovery ≥50% from 2026
A22: S19 | B22: Provincial 2024 consumption sources (7): GD bulletin PDF; SD stats bureau; NEA Henan; jiangsu.gov.cn (SGCC CSR); 新华网/国网浙江; 内蒙古太阳能行业协会; Sichuan Energy Bureau director article | C22: 1/2 mixed | D22: see assumptions tab C-section notes | E22: 2026-07-14 | F22: Basket weights — category flags per province in assumptions tab
A23: S20 | B23: FRED/Fed H.10-G.5A (DEXUSUK, DEXUSEU, DEXCHUS); G.5A release 05.01.2026 | C23: 1 | D23: https://www.federalreserve.gov/releases/g5a/current/ ; https://fred.stlouisfed.org/ | E23: 2026-07-14 | F23: FX annual averages 2020–2025
A24: S21 | B24: BLS Public Data API v2, CUUR0000SA0 M13 | C24: 1 | D24: https://api.bls.gov/publicAPI/v2/timeseries/data/ | E24: 2026-07-14 | F24: CPI-U annual averages 2020–2025 (2025 = 321.943, final)
A25: S22 | B25: NDRC 发改价格规〔2025〕1490号 (4th-period pricing methods, 27.11.2025) | C25: 1 | D25: https://www.ndrc.gov.cn/xxgk/zcfb/ghxwj/202511/t20251127_1401964.html | E25: 2026-07-14 | F25: 4th regulatory period preparation — context for qc item Q1
A26: S23 | B26: 163.com/预见能源 report on 发改价格〔2026〕1077号 (4th-period T&D prices, reported 10.07.2026) | C26: 3 | D26: https://www.163.com/dy/article/L1NFPL6D05118O92.html | E26: 2026-07-14 | F26: TIER 3 — locator only. NO figure enters any chart/table from this source. Third period retained per decision D13.
A27: S24 | B27: 广东统计年鉴2025, 表7-6 分行业能源消费总量和原煤、电力消费量 (2024年) | C27: 1 | D27: http://stats.gd.gov.cn/gdtjnj/content/post_4810393.html (ZIP: .../615394/4810393.zip) | E27: 2026-07-14 | F27: GD 2024: 消费总量 9121.03; 工业合计 5217.39; 建筑业 102.68 (NBS energy classification). Confirms no 第二产业 aggregate published.
A28: S25 | B28: 国网浙江省电力 via 新华网浙江 (2025-01-20); NEA Henan 12月通报 表2; Shandong stats bureau note (2025-01-22) | C28: 1 | D28: http://zj.news.cn/20250120/eafe98e109de4e9f9f6d5af0ccafb248/c.html ; https://henb.nea.gov.cn/dtyw/sjfd/202501/t20250120_275548.html ; http://tjj.shandong.gov.cn/art/2025/1/22/art_6227_10316253.html | E28: 2026-07-14 | F28: Set C 第二产业 2024: ZJ 4515.5; HN 2330.71 (row sum check ✓); SD 6071.1
A29: S26 | B29: 川投能源 2024年年度报告摘要 via 上海证券报 (2025-04-12) | C29: 2 | D29: https://paper.cnstock.com/html/2025-04/12/content_2048342.htm | E29: 2026-07-14 | F29: SC 2024 全社会用电量 3999.69 亿千瓦时 (+7.77%) — Tier 2, corroborates official rounded 4000 (Sichuan Energy Bureau director article)
A30: S27 | B30: DESNZ, Electricity Generation Costs 2023 (Nov 2023) + Annex A 2023 | C30: 1 | D30: https://www.gov.uk/government/publications/electricity-generation-costs-2023 | E30: 2026-07-14 | F30: UK LCOE 2025 commissioning, real 2021 £ (Table 10 p.24; Annex A assumptions incl. hurdle rates 5.0–7.5%) — headline UK leg per decision D16
A31: S28 | B31: DESNZ, Electricity Generation Costs 2025 (14.01.2026, upd. 18.03.2026) + Annexes A/B; CEPA hurdle-rate study (06.10.2025) | C31: 1 | D31: https://www.gov.uk/government/publications/electricity-generation-costs-2025 ; https://assets.publishing.service.gov.uk/media/68cd1d818c44a661b4995d9f/cepa-desnz-hurdle-rates-electricity.pdf | E31: 2026-07-14 | F31: Newer edition: starts 2030 commissioning, real 2024 £; no coal, no nuclear (commercially sensitive); new carbon methodology — NOT headline (D16), cited as context
A32: S29 | B32: Fraunhofer ISE, Stromgestehungskosten Erneuerbare Energien, Juli 2024 | C32: 1 | D32: https://www.ise.fraunhofer.de/content/dam/ise/de/documents/publications/studies/DE2024_ISE_Studie_Stromgestehungskosten_Erneuerbare_Energien.pdf | E32: 2026-07-14 | F32: DE LCOE bands, real 2024 EUR, all 7 techs incl. new-build coal & nuclear (excl. back-end); tech-specific real WACC 3.2–7.8% (Tab. 2); no 2025/26 edition exists
A33: S30 | B33: IEA, World Energy Outlook 2025 (12.11.2025), Annex B Tables B.4a–c | C33: 1 | D33: https://iea.blob.core.windows.net/assets/9753df19-0a71-422a-b725-012c555763b3/WorldEnergyOutlook2025.pdf | E33: 2026-07-14 | F33: CN LCOE 2024 (2024 USD): coal 65 / CCGT 100 / nuclear 70 / PV 45 / onshore 40 / offshore 60; WACC 8–9% thermal-nuclear, 4–7% PV/onshore, 5–8% offshore (p.453–455)
A34: S31 | B34: IEA/NEA, Projected Costs of Generating Electricity 2020 (9th ed.; latest as of 2026-07-14) | C34: 1 | D34: https://www.oecd-nea.org/upload/docs/application/pdf/2020-12/egc-2020_2020-12-09_18-26-46_781.pdf | E34: 2026-07-14 | F34: Published harmonised @3/7/10% real, 2018 USD; CN full set (coal 74.66 / CCGT 84.00 / nuclear 66.01 @7%); DE hydro only; UK absent; CN data Secretariat-compiled
... A43: S40 | B43: Ofgem data portal wholesale charts (everviz embeds): 'Electricity Prices: Forward Delivery Contracts – Weekly Average (GB)' (0eDBSsofl, weekly, from 01.02.2021) and 'Day Ahead Baseload Contracts – Monthly Average (GB)' (n9WSDfgxc, monthly, from 06/2010) | C43: 1 | D43: https://cloud.highcharts.com/embed/0eDBSsofl ; https://cloud.highcharts.com/embed/n9WSDfgxc (inline chart CSV extracted in-browser) | E43: 2026-07-15 | F43: UK wholesale legs (D21/D22). Annual averages computed (estimated=Y): YA obs-yr 2021: 89.49 (Feb–Dec) / 2022: 273.71 / 2023: 127.45 / 2024: 79.70 / 2025: 81.21 £/MWh; DA 2010 (Jun–Dec): 44.96 … 2025: 83.93 (full series in staging file). Underlying assessments third-party, republished by Ofgem
A44: S41 | B44: NESO Final TNUoS Tariffs tables workbooks 2023/24–2026/27 (docs 275726, 301731, 353061, 376341), sheet T10 Non-locational banded charges | C44: 1 | D44: https://www.neso.energy/document/275726/download ; /301731/ ; /353061/ ; /376341/ | E44: 2026-07-15 | F44: HV4 residual (medium archetype TNUoS, TCR era): 276.988323 / 243.634626 / 317.597969 / 528.912335 £/site/day; T-Demand cross-checks
A45: S42 | B45: NPg (Yorkshire) LC14 CDCM statement 2019/20 via Wayback (20221130063623/…/2022-05/4821.pdf) | C45: 1 | D45: https://web.archive.org/web/20221130063623/https://www.northernpowergrid.com/sites/default/files/2022-05/4821.pdf | E45: 2026-07-15 | F45: DUoS time-band hour definitions (red 16:00–19:30 etc.) for TOU weighting; direct NPg asset URLs now geo-blocked from sandbox (browser route in staging log)
A46: S43 | B46: DESNZ QEP table_341.xlsx — full annual band series 2004–2025 (sheets 3.4.1 Annual excl CCL; Notes band definitions) | C46: 1 | D46: https://assets.publishing.service.gov.uk/media/6942bd3536f089d38be1f246/table_341.xlsx | E46: 2026-07-15 | F46: UK validation overlay: Extra Large (large archetype), Large 20,000–69,999 MWh (medium archetype — 20 GWh at band lower edge, flagged). GN1 cross-check 2024 XL = 21.6979 ✓
A47: S44 | B47: 发改价格〔2023〕526号 annex — P3 T&D for GD/SD/ZJ/HN/蒙西/SC (in-session extraction of 两部制 rows) | C47: 1 | D47: https://www.ndrc.gov.cn/xxgk/zcfb/tz/202305/P020230515609052875117.pdf | E47: 2026-07-15 | F47: cn_td B/C/F filled; cross-checks vs SD Oct-2025 (输配 0.1491) and HN May-2025 (0.168) bills ✓
A48: S45 | B48: Stage-4 staging files (six retrieval legs, primary citations inside): stage4_staging_{uk_wholesale_levies, uk_network, de_wholesale_levies, de_network, cn_catalogue, cn_market}.md | C48: 1 | D48: project folder UK Energy Prices/ | E48: 2026-07-15 | F48: All stage4_uk / stage4_de / stage4_cn raw values; per-series primary sources cited in tab column U
A49: S46 | B49: Ofgem Feed-in Tariffs Annual Reports SY1–SY15 (levelisation fund, relevant supply, EII/GoO exemption mechanics) | C49: 1 | D49: ofgem.gov.uk — 15 PDFs, e.g. /sites/default/files/2025-12/feed_in_tariff_annual_report_sy15_20251210120852.pdf | E49: 2026-07-15 | F49: stage4_uk r20; FiT £/MWh 2015–24 computed fund÷relevant supply; 2010–14 per D27
A50: S47 | B50: EMRS "Key Figures for Payments" DY2018/19–2025/26 + ESC/LCCC annual reports + DESNZ CM scheme updates | C50: 1 | D50: emrsettlement.co.uk via Wayback (incl. SPN 20260715211143 / 20260715212444); lowcarboncontracts.uk | E50: 2026-07-15 | F50: stage4_uk r21; CM settled payments & window demand; DY22/23 pre-final flagged
A51: S48 | B51: NESO half-hourly RF BSUoS settlement files 2010/11–2022/23 + BSUoS fixed-tariff CSV (FT1–FT8 Final) | C51: 1 | D51: neso.energy docs 47481/47476/47471/47466/47461/104301 + api.neso.energy 2016-2023-rf.csv + bsuos-fixed-tariffs.csv | E51: 2026-07-15 | F51: stage4_uk r28–30; own computation (unweighted), x-check CMP250 FMR Table 2 exact
A52: S49 | B52: National Grid (ESO) AAHEDC charging statements / final tariff letters 2010/11–2020/21 | C52: 1 | D52: neso.energy docs 47306/47316/47301/47271/47261/47236/47226/101676/119396/148076/173046 | E52: 2026-07-15 | F52: stage4_uk r31
A53: S50 | B53: SI 2024/409 + SI 2026/243 + both IAs + Elexon NCC levy pages (actual monthly levy totals; estimated levy fund) + DBT consultation response 31.10.2025 + Hansard 04.02.2026 | C53: 1 | D53: legislation.gov.uk; elexon.co.uk NCC supplier & estimated-levy-fund pages; gov.uk | E53: 2026-07-15 | F53: stage4_uk r53 ESL; E2 carve-out reg 18(4)(a); levy timing (90% from levy yr 2027/28)
A54: S51 | B54: NPg (Yorkshire) LC14 statements 2012/13 (Common Crawl WARC), 2015/16 + 2016/17 (Wayback) | C54: 1 | D54: CC-MAIN-2013-20 offset 639035092; web.archive.org 20160530004600/downloads/1481; 20170719052401/downloads/2466 | E54: 2026-07-15 | F54: stage4_uk r34–38 anchor years; sha256 in /tmp/npg_legacy + staging file
A55: S52 | B55: EEX Phelix DE Base Cal-26 daily settlements Oct-24–Sep-25 (Stadtwerke Hamm transparency sheet) + BNetzA press 05.01.2026 + MB 2025 Abb. 78 (front-year averages 2020–24) | C55: 4/1 | D55: stadtwerke-hamm.de …/Strompreis_Phelix_Baseload_Year_Future_Lfj_2026.pdf; bundesnetzagentur.de/1087156 | E55: 2026-07-15 | F55: stage4_de r7 trading-2025 = 87.57 provisional (D29); cross-checks Tier 1
... A142: S145 | B142: DUKES 2025 Chapter 5 (electricity; demand 319 TWh, industrial 82.2 TWh, winter peak 47.4 GW) | C142: 1 | D142: gov.uk | E142: 2026-07-18 | F142: 8.4 demand base; GB peak (5.10.A) per Stage 7
A143: S146 | B143: DESNZ, BICS — govt response to eligibility & approach consultation | C143: 1 | D143: gov.uk/.../british-industrial-competitiveness-scheme...government-response.pdf | E143: 2026-07-18 | F143: 9B BICS scope RO/FiT/CM, eligibility, Exchequer funding
A144: S147 | B144: gov.uk news, "Government cuts electricity bill for 10,000 manufacturers" | C144: 1 | D144: gov.uk/government/news/government-cuts-electricity-bill-for-10000-manufacturers | E144: 2026-07-18 | F144: 9B BICS saving £35-40/MWh, ~10,000 firms, ~£600m/yr
A145: S148 | B145: UK Parliament, Written Ministerial Statement HCWS200 (McDonald) | C145: 1 | D145: questions-statements.parliament.uk/written-statements/detail/2026-07-08/hcws200 | E145: 2026-07-18 | F145: 9B BICS timeline; applications 1 Oct-30 Nov 2026
A146: S149 | B146: gov.uk news, Supercharger — Network Charging Compensation 60%->90% | C146: 1 | D146: gov.uk/government/news/huge-boost-for-uk-industry...cuts-to-electricity-costs | E146: 2026-07-18 | F146: 9C Supercharger NCC 90% (Apr 2026), +£7-10/MWh, <=£420m/yr
A147: S150 | B147: gov.uk news, "Supercharger rolls out" (EII levy exemptions) | C147: 1 | D147: gov.uk/government/news/huge-boost-for-uk-industry-as-government-supercharger-rolls-out | E147: 2026-07-18 | F147: 9B Supercharger 100% RO/CfD/FiT/CM exemption (in force 2024)
A148: S151 | B148: DESNZ, EII certificate for exemption — guidance for applicants | C148: 1 | D148: gov.uk/.../energy-intensive-industries-certificate-for-exemption...pdf | E148: 2026-07-18 | F148: 9B EII eligibility: elec>=20% GVA; NACE4 trade>=4% & elec>=7%
A149: S152 | B149: CMA Subsidy Advice Unit, referral of modified NCC scheme | C149: 1 | D149: gov.uk/cma-cases/referral-of-the-proposed-modified-network-charging-compensation-scheme | E149: 2026-07-18 | F149: 9C NCC subsidy-control cleared (report 19 Dec 2025)
A150: S153 | B150: DESNZ, Review of Electricity Market Arrangements — Summer Update 2025 | C150: 1 | D150: gov.uk/.../review-of-electricity-market-arrangements-rema-summer-update-2025 | E150: 2026-07-18 | F150: 9A zonal rejected; national marginal pricing retained
A151: S154 | B151: DESNZ, Contracts for Difference AR7 reforms — consultation | C151: 1 | D151: gov.uk/.../cfd-allocation-round-7-reforms-consultation.pdf | E151: 2026-07-18 | F151: 9A CfD reform (bid pre-consent; term >15yr consult)
A152: S155 | B152: DESNZ, Capacity Market — government response (maintain security of supply) | C152: 1 | D152: gov.uk/.../capacity-market-consultation-government-response.pdf | E152: 2026-07-18 | F152: 9A CM reform; ~35 GW unabated gas retained
A153: S156 | B153: DESNZ, Corporate Power Purchase Agreements — call for evidence | C153: 1 | D153: gov.uk/government/calls-for-evidence/corporate-power-purchase-agreements | E153: 2026-07-18 | F153: 9A private-wire/CPPA (call for evidence closed Mar 2026)
A154: S157 | B154: DESNZ, Clean Power 2030 Action Plan | C154: 1 | D154: gov.uk/government/publications/clean-power-2030-action-plan | E154: 2026-07-18 | F154: 9A clean-power build-out framing
... A172: S175 | B172: European Commission, Clean Industrial Deal State Aid Framework (CISAF) | C172: 1 | D172: competition-policy.ec.europa.eu/.../clean-industrial-deal-state-aid-framework-cisaf_en | E172: 2026-07-18 | F172: 9D EU state-aid frame (to 2030) for energy-intensive electricity relief
A173: S101 | B173: Germany §24c EnWG network-cost subsidy: BGBl. 2025 I Nr. 317 + joint ÜNB (50Hertz/Amprion/TenneT/TransnetBW) 2026 transmission-tariff announcement 01.10.2025 (ÜNE 6.65→2.86 ct/kWh, −3.79, via €6.5bn federal Bundeszuschuss) | C173: 1 (definition reconstructed 2026-07-18, Stage-10 QC, from citing context stage7_network!T9) | D173: BGBl. 2025 I Nr. 317; netztransparenz.de/ÜNB PR 01.10.2025 | E173: 2026-07-16 (Stage 7); backfilled 2026-07-18 | F173: 7 DE 2026 transmission network charge & €6.5bn subsidy (stage7_network!T9)
A174: S102 | B174: VOID — unused source ID (no citation anywhere in workbook; documented Stage-10 QC) | C174: — | D174: — | E174: 2026-07-18 | F174: (numbering gap, intentionally void)
A175: S103 | B175: VOID — unused source ID (no citation anywhere in workbook; documented Stage-10 QC) | C175: — | D175: — | E175: 2026-07-18 | F175: (numbering gap, intentionally void)
A176: S104 | B176: VOID — unused source ID (no citation anywhere in workbook; documented Stage-10 QC) | C176: — | D176: — | E176: 2026-07-18 | F176: (numbering gap, intentionally void)
A177: S105 | B177: VOID — unused source ID (no citation anywhere in workbook; documented Stage-10 QC) | C177: — | D177: — | E177: 2026-07-18 | F177: (numbering gap, intentionally void)
A178: S106 | B178: SGCC Jiangsu 代理购电 (agency-purchase electricity) monthly price notices (国网江苏 代理购电公告) — JS market price & 系统运行费 components (cited within source S114) | C178: 1 (definition reconstructed 2026-07-18, Stage-10 QC, from citing context sources!B114) | D178: 95598.js.sgcc.com.cn — 代理购电公告 (monthly) | E178: 2026-07-16 (Stage 7); backfilled 2026-07-18 | F178: 7 CN Jiangsu agency-purchase price & 系统运行费 build (cited in S114)
A179: S176 | B179: worldsteel, Energy use in the steel industry (web page, updated May 2026) | C179: 1 | D179: https://worldsteel.org/about-steel/energy-use-in-the-steel-industry/ | E179: 2026-07-19 | F179: 5 Steel electricity-share ranges (BF-BOF 10–15%; scrap-EAF 50–70%; DRI-EAF 25–40%); 2024 avg intensity 20.95 GJ/t (D62 coefficient re-derivation)
A180: S177 | B180: IEA, Cement (tracking page, current edition) — negative check | C180: 1 (absence check) | D180: https://www.iea.org/reports/cement-3 | E180: 2026-07-19 | F180: 5 kWh/t electricity intensity NOT on current page → C132 pinned to 2022 edition (D62)
A181: S178 | B181: NESO, Future Energy Scenarios 2025 — Data Workbook (sheet ED1) | C181: 1 | D181: https://www.neso.energy/document/364551/download | E181: 2026-07-19 | F181: 7 UK forward utilisation: HT system demand + ACS peak 2023–2035 (stage7 §G; Q51 UK leg; D63)
A182: S179 | B182: VEA, EnFG Besondere Ausgleichsregelung explainer — KWKG/Offshore-Umlage caps (15% list-1 / 25% list-2, beyond first GWh) | C182: 2 | D182: https://www.vea.de/newsroom/aktuelles/thema/so-erhalten-sie-grosse-teile-der-kwk-umlage-und-der-offshore-netzumlage-zurueck | E182: 2026-07-19 | F182: 6 DE E2 EnFG 15%-cap memo (stage6 r192–193, Q85). Verify against EnFG §§28–31 statute text at publication (gesetze-im-internet robots-blocked 2026-07-19).
A183: S180 | B183: Ofgem, Energy companies' Consolidated Segmental Statements (CSS) — transparency/index page + OFG1163 guidance (regime expanded to non-legacy suppliers from 29.03.2024) | C183: 1 | D183: https://www.ofgem.gov.uk/transparency-document/energy-companies-consolidated-segmental-statements-css | E183: 2026-07-24 | F183: 4/6 CSS margin overlay (stage4_uk r55–59; stage6 §R wedge note; Q88)
A184: S181 | B184: Supplier CSS filings, non-domestic electricity supply segments 2012–2024: EDF 2012–24; Centrica/BGT 2012–23; SSE FY12/13–23/24; E.ON 2012–20+2023–24; npower/RWE 2012–19; Scottish Power 2012–24; TotalEnergies 2023–24; Drax/Opus 2023–24 (audited-basis disclosures; image-table years transcribed, additivity-checked) | C184: 1 | D184: per-filing URLs in css_nondom_margin_panel.csv (project folder, 73 rows, one URL per filing) | E184: 2026-07-24 | F184: 4/6 CSS panel EBIT/opex series + bracket test (css_margin_bracket_staging.md; Q88)
A185: S182 | B185: BNetzA/Bundeskartellamt, Monitoringbericht Energie 2025 (pub. 26.11.2025) — FIRST edition splitting "Beschaffungskosten" from "Vertrieb und Marge" for non-household cases. Tab. 35 p.166 (Industriekunde 24 GWh/a); Tab. 37 (Gewerbekunde 50 MWh/a); Tab. 38 (household band DC); Tab. 40 p.173 (household by contract category) | C185: 1 | D185: https://data.bundesnetzagentur.de/Bundesnetzagentur/SharedDocs/Mediathek/Monitoringberichte/MonitoringberichtEnergie2025.pdf | E185: 2026-07-24
A186: S183 | B186: BNetzA/Bundeskartellamt, Monitoringberichte Energie 2019–2024 — bundled industrial supply residual ("vom Lieferanten beeinflussbarer Preisbestandteil / Restbetrag", 24 GWh/a): MB2023 Tab. 60 p.179; MB2024 Tab. 53. Used for the pre-2025 series only, flagged NOT usable as margin | C186: 1 | D186: https://data.bundesnetzagentur.de/Bundesnetzagentur/SharedDocs/Mediathek/Monitoringberichte/MonitoringberichtEnergie2024.pdf | E186: 2026-07-24
